Workbook

Sheet README
A1: Commerce Service - Function / API Backlog (traceable)
A2: Project Nexus (e-commerce & auction) | Commerce team | Built from Functions.xlsx (sheet "Commerce Service"), SRS_Commerce_Service_v1.md, DB_Commerce_v2.sql, and the other service sheets for contracts.
A4: How to trace
A5: System SRS section -> COM-* requirement (Trace_Matrix) -> Function ID (Backlog) -> API/trigger (Backlog, API_Catalog) -> Tables (Backlog, DB_Trace) -> Services (Integration_Map) -> Events (Event_Catalog) -> Test cases (Test_Cases).
A7: Sheets
A8: Backlog: 57 functions (48 from Functions.xlsx + 9 added). One row per function with priority, wave, SRS/COM links, tables, services, events, rules, errors.
A9: Trace_Matrix: every COM requirement with the functions, endpoints, tables, events, services and test counts. Coverage column is a formula.
A10: API_Catalog / Error_Codes: contracts of the HTTP APIs and a derived error-code registry (the "Error Codes" sheet referenced by Functions.xlsx does not exist).
A11: DB_Trace: 19 tables vs the functions that write/read them (counts are formulas, checked against the Backlog).
A12: Event_Catalog / Integration_Map: events and cross-service contracts with agreement status.
A13: Test_Cases: generated per function (happy, negative per error code, security, idempotency, contract) plus end-to-end scenarios.
A14: Gaps_Decisions: contract conflicts and open decisions (G01-G04 auction items are resolved by the agreed spec). SRS_Sync: the SRS edits needed to match the agreed spec.
... A22: Tech assumption (.NET): ASP.NET Core + EF Core (enum as string), MassTransit outbox/inbox, Quartz/Hangfire with distributed lock, PostgreSQL.

Sheet Backlog
A1: ID | B1: Module | C1: Function name | D1: Kind | E1: Endpoint / trigger | F1: Priority | G1: Wave | H1: Complexity | I1: Change vs Functions.xlsx | J1: Adjustment note | K1: System SRS ref | L1: COM requirement(s) | M1: Permission | N1: Tables written | O1: Tables read | P1: Integrated services | Q1: Events published | R1: Events consumed | S1: Idempotency / concurrency | T1: Key business rules | U1: Error codes | V1: Depends on | W1: Gaps | X1: # Test cases | Y1: Test coverage
A2: CART-01 | B2: Cart | C2: Get my cart / Lấy giỏ hàng của tôi | D2: Public API | E2: GET /api/v1/carts/me | F2: P0 | G2: 1 | H2: M | I2: ADJUSTED | J2: Catalog call re-pointed to CAT-39 (status/price/saleType) + CAT-24 (display data); stock via FUL-04. GET never creates a cart. | K2: 3.4.1.1; 3.4.1.5 | L2: COM-CART-001; COM-CART-005 | M2: CART.VIEW / Buyer | O2: carts, cart_items | P2: Catalog CAT-39 / CAT-24 (sync, degrade); Fulfillment FUL-04 (sync, optional, cache ~30s) | S2: Read-only | T2: Virtual empty cart when none; group by seller_id; show current price without overwriting snapshot; GET does not touch last_activity_at; degrade (200 + warnings) when Catalog/Fulfillment down. | V2: ORD-26 | W2: G09 | X2: =COUNTIF(Test_Cases!$B$2:$B$1000,A2) -> 4 | Y2: =IF(X2=0,"NO TEST",IF(X2<3,"THIN","OK")) -> OK
A3: CART-02 | B3: Cart | C3: Add item to cart / Thêm sản phẩm vào giỏ | D3: Public API | E3: POST /api/v1/carts/me/items | F3: P0 | G3: 1 | H3: L | I3: ADJUSTED | J3: UNIQUE(cart_id, sku_id) and carts.row_version now exist in DB v2. Auction-only product detected through CAT-39 (Reason=AUCTION_ONLY) -> 409 PRODUCT_IN_AUCTION. | K3: 3.4.1.1; 3.4.1.2 | L3: COM-CART-001; COM-CART-002 | M3: CART.UPDATE / Buyer | N3: carts, cart_items, outbox_messages | O3: checkout_groups, system_settings | P3: Catalog CAT-39 (sync, before TX); Fulfillment FUL-04 (soft check, before TX) | Q3: CartCreated; CartItemAdded | S3: Optimistic lock carts.row_version (retry 1-2x); UPSERT ON CONFLICT (cart_id, sku_id); partial unique uq_carts_active_buyer for first-cart race | T3: qty 1..MAX_QTY_PER_ITEM(99); <=MAX_CART_ITEMS(50) lines; cannot buy own product; no auction product; cart locked when checkout open; unit_price_snapshot = price at first add and never changes on merge; no inventory reservation on add. | U3: 400 VALIDATION_ERROR, 404 PRODUCT_NOT_FOUND, 409 PRODUCT_NOT_AVAILABLE, 409 INSUFFICIENT_STOCK, 409 CART_ITEM_LIMIT_EXCEEDED, 409 CANNOT_BUY_OWN_PRODUCT, 409 PRODUCT_IN_AUCTION, 409 CART_LOCKED, 503 CATALOG_UNAVAILABLE | V3: ORD-26; ORD-20 | W3: G09 | X3: =COUNTIF(Test_Cases!$B$2:$B$1000,A3) -> 15 | Y3: =IF(X3=0,"NO TEST",IF(X3<3,"THIN","OK")) -> OK
A4: CART-03 | B4: Cart | C4: Update cart item quantity / Cập nhật số lượng | D4: Public API | E4: PATCH /api/v1/carts/me/items/{cartItemId} | F4: P0 | G4: 1 | H4: M | I4: ADJUSTED | J4: Catalog check via CAT-39; row_version column now in DB v2. | K4: 3.4.1.3 | L4: COM-CART-003 | M4: CART.UPDATE / Buyer | N4: cart_items, carts, outbox_messages | O4: checkout_groups | P4: Catalog CAT-39 (sync); Fulfillment FUL-04 (sync) | Q4: CartItemUpdated | S4: Optimistic lock carts.row_version (retry 1-2x then 409 CONCURRENT_UPDATE) | T4: qty>=1 and <=MAX_QTY_PER_ITEM and <= available stock; other buyer's item returns 404; refreshes last_activity_at; does not change unit_price_snapshot. | U4: 400 VALIDATION_ERROR, 404 CART_ITEM_NOT_FOUND, 409 INSUFFICIENT_STOCK, 409 PRODUCT_NOT_AVAILABLE, 409 CONCURRENT_UPDATE, 409 CART_LOCKED | V4: CART-02 | W4: G09 | X4: =COUNTIF(Test_Cases!$B$2:$B$1000,A4) -> 11 | Y4: =IF(X4=0,"NO TEST",IF(X4<3,"THIN","OK")) -> OK
A5: CART-04 | B5: Cart | C5: Remove cart item / Xoá một dòng khỏi giỏ | D5: Public API | E5: DELETE /api/v1/carts/me/items/{cartItemId} | F5: P0 | G5: 1 | H5: S | I5: ADJUSTED | J5: Function name was blank in Functions.xlsx (cell B5); filled in. | K5: 3.4.1.4 | L5: COM-CART-004 | M5: CART.REMOVE_ITEM / Buyer | N5: cart_items, carts, outbox_messages | O5: checkout_groups | P5: - | Q5: CartItemRemoved | S5: DELETE is idempotent (200 even if the item is already gone) | T5: Hard delete of cart_items (no deleted_at); recalc item_count/subtotal; cart stays ACTIVE when empty; blocked while checkout open (CART_LOCKED). | U5: 409 CART_LOCKED | V5: CART-02 | X5: =COUNTIF(Test_Cases!$B$2:$B$1000,A5) -> 4 | Y5: =IF(X5=0,"NO TEST",IF(X5<3,"THIN","OK")) -> OK
A6: CART-05 | B6: Cart | C6: Bulk remove / clear cart / Xoá nhiều dòng hoặc xoá hết | D6: Public API | E6: POST /api/v1/carts/me/items:bulk-remove | F6: P1 | G6: 1 | H6: S | I6: UNCHANGED | K6: 3.4.1.4 | L6: COM-CART-004 | M6: CART.REMOVE_ITEM / Buyer | N6: cart_items, carts, outbox_messages | O6: checkout_groups | P6: - | Q6: CartItemRemoved (1 event per batch) | S6: Idempotent: unknown ids ignored | T6: cartItemIds 1..100 XOR all=true; POST :bulk-remove instead of DELETE with body. | U6: 400 VALIDATION_ERROR, 409 CART_LOCKED | V6: CART-04 | X6: =COUNTIF(Test_Cases!$B$2:$B$1000,A6) -> 5 | Y6: =IF(X6=0,"NO TEST",IF(X6<3,"THIN","OK")) -> OK
A7: CART-06 | B7: Cart | C7: Validate cart / Kiểm tra giỏ hàng trước checkout | D7: Public API | E7: POST /api/v1/carts/me/validate (+ internal CartValidator dùng lại ở CHK-01/02) | F7: P0 | G7: 1 | H7: M | I7: ADJUSTED | J7: Use CAT-39 (Purpose=CART/CHECKOUT) as the single source for 'is purchasable'; PRICE_CHANGED is a warning, OUT_OF_STOCK/INACTIVE block checkout. | K7: 3.4.1.6 | L7: COM-CART-006 | M7: CART.VIEW / Buyer | O7: carts, cart_items | P7: Catalog CAT-39 / CAT-24 (sync); Fulfillment FUL-04 (sync) | S7: Read-only; internal CartValidator is reused by CHK-01/CHK-02 | T7: Report only, never auto-fix the cart; if CHECKOUT_PRICE_REVALIDATION=true and price changed return PRICE_CHANGED with the new price so the buyer confirms (SRS COM-CART-006); other issues: OUT_OF_STOCK | INACTIVE | SELLER_SUSPENDED | QTY_EXCEEDS_STOCK. | U7: 409 CART_EMPTY, 503 CATALOG_UNAVAILABLE | V7: CART-02 | W7: G09 | X7: =COUNTIF(Test_Cases!$B$2:$B$1000,A7) -> 6 | Y7: =IF(X7=0,"NO TEST",IF(X7<3,"THIN","OK")) -> OK
A8: CART-07 | B8: Cart | C8: Cart price calculation / Tính giá giỏ hàng | D8: Internal component | E8: PricingService.calculate(items, address?, vouchers?) | F8: P0 | G8: 1 | H8: L | I8: UNCHANGED | J8: Blocked on config PLATFORM_MARKUP_PERCENT (not seeded in DB v2) and tax decision. | K8: 3.4.1.5 | L8: COM-CART-005; COM-CHK-003 | M8: System (internal) | O8: system_settings | P8: DSC-02 (internal call) | S8: Pure function | T8: Shared pricing: product discount -> shop discount -> markup -> system voucher -> ship; invariant total = seller_receive + platform_fee + shipping_fee; platform_fee may be negative. | U8: 422 PRICING_ERROR | V8: DSC-02; ORD-26 | W8: G20; G23 | X8: =COUNTIF(Test_Cases!$B$2:$B$1000,A8) -> 4 | Y8: =IF(X8=0,"NO TEST",IF(X8<3,"THIN","OK")) -> OK
A9: CART-08 | B9: Cart | C9: Cart summary (badge) / Số lượng giỏ hàng | D9: Public API | E9: GET /api/v1/carts/me/summary | F9: P1 | G9: 1 | H9: S | I9: UNCHANGED | K9: 3.4.1.5 | L9: COM-CART-005 | M9: CART.VIEW / Buyer | O9: carts | P9: - | S9: Read-only (cacheable) | T9: Reads denormalized item_count and subtotal_amount; returns 0 when no cart (no auto-create). | X9: =COUNTIF(Test_Cases!$B$2:$B$1000,A9) -> 3 | Y9: =IF(X9=0,"NO TEST",IF(X9<3,"THIN","OK")) -> OK
A10: CART-09 | B10: Cart | C10: Expire inactive carts / Job hết hạn giỏ hàng | D10: Job | E10: chạy mỗi giờ (@Scheduled + ShedLock) | F10: P1 | G10: 1 | H10: S | I10: UNCHANGED | J10: Interval 'hourly' differs from 1-minute jobs elsewhere; confirm. | K10: 3.4.1.1 | L10: COM-CART-007 | M10: System | N10: carts, outbox_messages | O10: checkout_groups, system_settings | P10: - | Q10: CartExpired | S10: SELECT ... FOR UPDATE SKIP LOCKED, batch 500, ShedLock | T10: ACTIVE carts with last_activity_at older than CART_EXPIRATION_DAYS(7) become ABANDONED; skip carts with an open checkout; no delete. | V10: ORD-20; ORD-26 | W10: G26 | X10: =COUNTIF(Test_Cases!$B$2:$B$1000,A10) -> 3 | Y10: =IF(X10=0,"NO TEST",IF(X10<3,"THIN","OK")) -> OK
A11: CART-10 | B11: Cart | C11: Merge guest cart on login / Gộp giỏ khách (OPTIONAL) | D11: Public API | E11: POST /api/v1/carts/me/merge | F11: P2 | G11: 4 | H11: S | I11: ADJUSTED | J11: WON'T for MVP by default: SRS COM-CART-009 says login required, no merge (OQ-04). Kept only as an optional placeholder. | K11: 3.4.1.1 | L11: COM-CART-009 | M11: CART.UPDATE / Buyer | N11: carts, cart_items, outbox_messages | O11: system_settings | P11: Catalog CAT-39; Fulfillment FUL-04 | Q11: CartItemAdded | S11: Same as CART-02 | T11: <=50 items; each item follows CART-02 rules; skipped items returned with reason. | U11: 400 VALIDATION_ERROR, 409 CART_LOCKED | V11: CART-02 | W11: G23 | X11: =COUNTIF(Test_Cases!$B$2:$B$1000,A11) -> 6 | Y11: =IF(X11=0,"NO TEST",IF(X11<3,"THIN","OK")) -> OK
A12: CART-11 | B12: Cart | C12: Cleanup on Product/User events / Dọn giỏ theo sự kiện | D12: Event consumer | E12: topics: catalog.*, user.* | F12: P1 | G12: 1 | H12: M | I12: UNCHANGED | K12: 3.4.1.4 (cart integrity) | L12: COM-CART-008; COM-PLT-003 | M12: System | N12: inbox_messages, cart_items, carts | P12: Catalog / User events | R12: ProductDeleted; ProductStatusChanged; UserDeleted | S12: Inbox (message_id, consumer); at-least-once; batch 500 carts per TX | T12: ProductDeleted removes cart lines; INACTIVE only flagged (shown in CART-01); UserDeleted marks carts ABANDONED + deleted_at. | V12: ORD-24 | X12: =COUNTIF(Test_Cases!$B$2:$B$1000,A12) -> 4 | Y12: =IF(X12=0,"NO TEST",IF(X12<3,"THIN","OK")) -> OK
A13: CHK-01 | B13: Checkout | C13: Checkout preview / Xem trước thanh toán | D13: Public API | E13: POST /api/v1/checkout/preview | F13: P0 | G13: 2 | H13: L | I13: ADJUSTED | J13: Wallet balance comes from Wallet WAL-02 (Payment was split into the Wallet service). Catalog via CAT-39/24; quote via FUL-12. | K13: 3.4.2.1; 3.4.1.5 | L13: COM-CHK-001; COM-CHK-003; COM-CHK-004 | M13: CHECKOUT.START / Buyer | O13: carts, cart_items, discount_codes, discount_code_scopes, discount_code_usages, system_settings | P13: Catalog CAT-39/24; Fulfillment FUL-12 shipping quote (timeout 3000ms); Wallet WAL-02 balance | S13: Read-only; returns quoteId (short TTL) reused by CHK-02 | T13: Split by seller; invalid voucher goes to invalidVouchers (does not fail); quote failure returns 200 with null ship fee + warning; COD not supported. | U13: 409 CART_EMPTY, 409 CART_INVALID | V13: CART-06; CART-07; DSC-02 | W13: G05; G09 | X13: =COUNTIF(Test_Cases!$B$2:$B$1000,A13) -> 6 | Y13: =IF(X13=0,"NO TEST",IF(X13<3,"THIN","OK")) -> OK
A14: CHK-02 | B14: Checkout | C14: Create checkout (group + orders) / Tạo checkout và đơn hàng | D14: Public API | E14: POST /api/v1/checkout | F14: P0 | G14: 2 | H14: XL | I14: ADJUSTED | J14: Inventory reservation contract differs from FUL-06 (event per order) - see G06. Reputation check endpoint differs from User GRPC-04 - see G11. | K14: 3.4.2.1; 3.4.3.1; 3.4.3.7; 3.4.3.8 | L14: COM-CHK-001; COM-CHK-002; COM-CHK-003; COM-CHK-005; COM-CHK-006; COM-CHK-007; COM-ORD-001; COM-PLT-001 | M14: CHECKOUT.START + ORDER.CREATE / Buyer | N14: idempotency_keys, checkout_groups, orders, order_items, order_status_history, discount_codes, discount_code_usages, saga_state, daily_order_sequences, outbox_messages | O14: carts, cart_items, system_settings | P14: Catalog CAT-39 (re-price); User status-trust (GRPC-04 equivalent, undefined); Fulfillment inventory reservation (all-or-nothing per group) | Q14: CheckoutStarted; OrderCreated (per order) | R14: InventoryReserved (Fulfillment, async variant) | S14: Idempotency-Key required; CheckoutSaga (TX-1 / reserve / TX-2 or compensate TX-3); uq_checkout_groups_open_cart | T14: 1 cart -> 1 checkout_group + N orders (per seller); deadline = now + CHECKOUT_TIMEOUT_MINUTES(15); amounts and snapshots frozen; cart kept until paid; SLA create order <= 1.5s. | U14: 400 VALIDATION_ERROR, 409 PRICE_CHANGED, 409 CART_INVALID, 409 CHECKOUT_ALREADY_OPEN, 409 INSUFFICIENT_STOCK, 409 VOUCHER_INVALID, 403 REPUTATION_RESTRICTED, 409 IDEMPOTENCY_KEY_CONFLICT, 409 REQUEST_IN_PROGRESS, 503 FULFILLMENT_UNAVAILABLE | V14: ORD-17; ORD-18; ORD-19; ORD-20; ORD-21; DSC-03; CART-06; CART-07 | W14: G06; G11 | X14: =COUNTIF(Test_Cases!$B$2:$B$1000,A14) -> 18 | Y14: =IF(X14=0,"NO TEST",IF(X14<3,"THIN","OK")) -> OK
A15: CHK-03 | B15: Checkout | C15: Pay checkout group / Thanh toán nhóm đơn | D15: Public API | E15: POST /api/v1/checkout-groups/{checkoutGroupId}/pay | F15: P0 | G15: 2 | H15: L | I15: ADJUSTED | J15: Payment is the Wallet service: WALLET -> event OrderCheckoutRequested (WAL-05A); VNPAY -> WAL-05B direct gateway. Functions.xlsx assumed HTTP POST /internal/v1/payments; contract must be aligned. | K15: 3.4.2.2 | L15: COM-PAY-001 | M15: CHECKOUT.PAY (NEW) / Buyer | N15: checkout_groups, orders, saga_state, idempotency_keys, outbox_messages | O15: orders, checkout_groups | P15: Wallet WAL-05A (event) / WAL-05B (HTTP); payment status query (undefined) | Q15: OrderCheckoutRequested (WALLET path, per WAL-05A) | S15: Idempotency-Key required; optimistic lock row_version; attempt counter payment_attempt_count (max PAYMENT_RETRY_LIMIT=3) | T15: Never returns PAID synchronously (202 PAYMENT_PROCESSING; PAID only via PAY-01); Commerce never debits money itself; no cancel while PAYMENT_PROCESSING. | U15: 404 CHECKOUT_GROUP_NOT_FOUND, 409 CHECKOUT_NOT_PAYABLE, 410 DEADLINE_EXPIRED, 402 INSUFFICIENT_WALLET_BALANCE, 409 PAYMENT_ATTEMPT_LIMIT_REACHED, 502 PAYMENT_GATEWAY_ERROR, 202 PAYMENT_PROCESSING | V15: CHK-02; ORD-19 | W15: G05 | X15: =COUNTIF(Test_Cases!$B$2:$B$1000,A15) -> 12 | Y15: =IF(X15=0,"NO TEST",IF(X15<3,"THIN","OK")) -> OK
A16: CHK-04 | B16: Checkout | C16: Get checkout group / Xem trạng thái checkout | D16: Public API | E16: GET /api/v1/checkout-groups/{checkoutGroupId} | F16: P0 | G16: 2 | H16: S | I16: UNCHANGED | J16: No list endpoint for checkout groups although idx_checkout_groups_buyer exists. | K16: 3.4.2.3; 3.4.3.3 | L16: COM-CHK-009 | M16: ORDER.VIEW / Buyer (own) | O16: checkout_groups, orders | P16: - | S16: Read-only (FE polls every 2-3s, ~2 min) | T16: Own group only (404 otherwise); status set PENDING_PAYMENT | PAYMENT_PROCESSING | PAID | CANCELLED | EXPIRED. | U16: 404 CHECKOUT_GROUP_NOT_FOUND | V16: CHK-02 | X16: =COUNTIF(Test_Cases!$B$2:$B$1000,A16) -> 4 | Y16: =IF(X16=0,"NO TEST",IF(X16<3,"THIN","OK")) -> OK
A17: CHK-05 | B17: Checkout | C17: Cancel checkout group / Huỷ checkout chưa thanh toán | D17: Public API | E17: POST /api/v1/checkout-groups/{checkoutGroupId}/cancel | F17: P0 | G17: 2 | H17: M | I17: UNCHANGED | J17: Matches COM-CHK-010 (cancel the whole group, never single unpaid orders). Events spec API 13 conflicts: see G35. | K17: 3.4.2.4 | L17: COM-CHK-010; COM-CNL-001 | M17: ORDER.CANCEL / Buyer | N17: checkout_groups, orders, order_cancellations, order_status_history, discount_code_usages, discount_codes, saga_state, outbox_messages | P17: Wallet (payment-in-flight check, undefined); Fulfillment release via OrderCancelled event (FUL-10) | Q17: OrderCancelled (per order); CheckoutCancelled | S17: CAS on row_version | T17: Only PENDING_PAYMENT groups; sole path to cancel an unpaid normal order; was_paid=false so no refund; inventory_released updated by ORD-22. | U17: 409 CHECKOUT_NOT_CANCELLABLE, 409 PAYMENT_IN_PROGRESS | V17: ORD-18; DSC-04 | W17: G05 | X17: =COUNTIF(Test_Cases!$B$2:$B$1000,A17) -> 7 | Y17: =IF(X17=0,"NO TEST",IF(X17<3,"THIN","OK")) -> OK
A18: CHK-06 | B18: Checkout | C18: Expire unpaid checkout / Job hết hạn thanh toán | D18: Job | E18: mỗi 1 phút (+ consumer InventoryReservationExpired làm lưới an toàn) | F18: P0 | G18: 2 | H18: M | I18: ADJUSTED | J18: Interval 15 s per Events spec 3.4 (SRS leaves OPEN). Payment status lookup still undefined (G05). | K18: 3.4.2.4; 3.4.3.8 | L18: COM-CHK-008 | M18: System | N18: checkout_groups, orders, order_cancellations, order_status_history, discount_code_usages, discount_codes, saga_state, outbox_messages | O18: checkout_groups | P18: Wallet payment status by referenceIds (batch, undefined); Fulfillment release via event | Q18: CheckoutExpired; OrderCancelled (PAYMENT_TIMEOUT, SYSTEM) | S18: SKIP LOCKED batch 100; every 15 s (spec, PROPOSED, OQ-19) | T18: Cancel group where status=PENDING_PAYMENT and payment_deadline_at < now; if Payment says SUCCEEDED hand over to PAY-01; never blind-cancel. | V18: ORD-18; DSC-04; PAY-01 | W18: G05 | X18: =COUNTIF(Test_Cases!$B$2:$B$1000,A18) -> 4 | Y18: =IF(X18=0,"NO TEST",IF(X18<3,"THIN","OK")) -> OK
A19: PAY-01 | B19: Payment (Commerce side) | C19: Handle payment result / Nhận kết quả thanh toán | D19: Event consumer | E19: PaymentSucceeded | PaymentFailed | PaymentExpired (event do Payment Service phát, cần chốt contract) | F19: P0 | G19: 2 | H19: XL | I19: ADJUSTED | J19: Wallet events are the target (Payment split, OQ-17); Events spec keeps temporary names PaymentSucceeded / PaymentFailed behind an adapter. VNPAY success event does not exist yet. | K19: 3.4.2.3; 3.4.3.7; 3.4.3.8 | L19: COM-PAY-002; COM-PAY-003; COM-PAY-004; COM-AUC-007; COM-AUC-008 | M19: System (service-to-service, JWT dịch vụ / mTLS) | N19: inbox_messages, checkout_groups, orders, auction_orders, order_status_history, order_refunds, discount_codes, discount_code_usages, cart_items, carts, saga_state, outbox_messages | O19: orders, order_items, auction_orders | P19: Wallet events (consume); Fulfillment confirm via OrderPaid (FUL-09); refund via OrderRefundRequested | Q19: OrderPaid (per order); OrderPaymentFailed; CheckoutCompleted (not in SRS 5.2); OrderRefundRequested (late/mismatch) | R19: WalletDebitedSuccess / WalletDebitFailed (target); PaymentSucceeded / PaymentFailed / PaymentExpired (as written) | S19: Inbox (message_id, consumer); optimistic lock row_version | T19: amount must equal total_amount else no PAID + refund; late payment (group EXPIRED/CANCELLED) -> full refund by checkout_group_id; failed/expired -> group back to PENDING_PAYMENT (<=3 attempts); seller_respond_deadline_at = paid_at + 24h. | V19: ORD-18; DSC-04; ORD-19; CHK-03; AO-03 | W19: G05 | X19: =COUNTIF(Test_Cases!$B$2:$B$1000,A19) -> 5 | Y19: =IF(X19=0,"NO TEST",IF(X19<3,"THIN","OK")) -> OK
A20: DSC-01 | B20: Discount | C20: List available vouchers / Danh sách voucher khả dụng | D20: Public API | E20: GET /api/v1/vouchers/available?cartItemIds=&sellerId=&page=&size= | F20: P1 | G20: 2 | H20: M | I20: UNCHANGED | K20: - (not in system SRS; from DB design) | L20: COM-DSC-002 | M20: CART.VIEW / Buyer | O20: discount_codes, discount_code_scopes, discount_code_usages | P20: Catalog (category/product of items for CATEGORY/SKU scope) | S20: Read-only | T20: ACTIVE, visible, in period, not exhausted, per-user limit not reached; hidden codes still usable when typed. | U20: 404 SELLER_NOT_FOUND | W20: G12 | X20: =COUNTIF(Test_Cases!$B$2:$B$1000,A20) -> 5 | Y20: =IF(X20=0,"NO TEST",IF(X20<3,"THIN","OK")) -> OK
A21: DSC-02 | B21: Discount | C21: Validate & calculate voucher / Kiểm tra và tính giảm giá | D21: Internal component | E21: VoucherService.validateAndCalculate(code, userId, scopeContext) | F21: P0 | G21: 1 | H21: L | I21: UNCHANGED | K21: - (not in system SRS; from DB design) | L21: COM-DSC-003; COM-DSC-004; COM-DSC-005 | M21: System (internal) | O21: discount_codes, discount_code_scopes, discount_code_usages | P21: - | S21: Pure / read-only | T21: PERCENT = min(eligible*value/100, max_discount_amount); FIXED = min(value, eligible); order PRODUCT -> SHOP -> markup -> SYSTEM; 1 SYSTEM/group, 1 SHOP/order, 1 PRODUCT/item; SYSTEM pro-rata with remainder on last order. | W21: G12 | X21: =COUNTIF(Test_Cases!$B$2:$B$1000,A21) -> 3 | Y21: =IF(X21=0,"NO TEST",IF(X21<3,"THIN","OK")) -> OK
A22: DSC-03 | B22: Discount | C22: Reserve vouchers / Giữ lượt voucher | D22: Internal component | E22: VoucherService.reserve(checkoutGroupId, orderId?, userId, codes) – gọi trong TX-1 của CHK-02 | F22: P0 | G22: 2 | H22: M | I22: UNCHANGED | K22: - (not in system SRS; from DB design) | L22: COM-DSC-004; COM-DSC-006 | M22: System (internal) | N22: discount_codes, discount_code_usages | O22: discount_code_usages | P22: - | S22: Conditional UPDATE (atomic counter) + pg_advisory_xact_lock(code,user); runs inside CHK-02 TX-1 | T22: reserved_count+1 only if used+reserved < max_uses_total; SYSTEM usage binds checkout_group_id, SHOP/PRODUCT binds order_id. | V22: DSC-02 | X22: =COUNTIF(Test_Cases!$B$2:$B$1000,A22) -> 3 | Y22: =IF(X22=0,"NO TEST",IF(X22<3,"THIN","OK")) -> OK
A23: DSC-04 | B23: Discount | C23: Confirm / Release voucher usage / Xác nhận hoặc trả lại lượt voucher | D23: Internal component | E23: VoucherService.confirm(groupId) / release(orderId|groupId, reason) | F23: P0 | G23: 2 | H23: M | I23: UNCHANGED | J23: BA decision pending: do vouchers return when a buyer cancels after paying. | K23: - (not in system SRS; from DB design) | L23: COM-DSC-006 | M23: System (internal) | N23: discount_codes, discount_code_usages | O23: discount_code_usages | P23: - | S23: Idempotent (USED/RELEASED rows skipped); called inside PAY-01 / CHK-05 / CHK-06 / ORD-05/06/09 TX | T23: confirm: RESERVED->USED (used+1, reserved-1); release: RESERVED/USED->RELEASED. | V23: DSC-03 | W23: G18 | X23: =COUNTIF(Test_Cases!$B$2:$B$1000,A23) -> 3 | Y23: =IF(X23=0,"NO TEST",IF(X23<3,"THIN","OK")) -> OK
A24: DSC-05 | B24: Discount | C24: Create voucher / Tạo voucher | D24: Public API | E24: POST /api/v1/vouchers | F24: P1 | G24: 4 | H24: M | I24: NEW | J24: PROPOSED. DB has discount_codes/discount_code_scopes but Functions.xlsx has no API that creates vouchers; privileges DISCOUNT.* are not in SRS 2.7. | K24: - (gap: no system SRS section) | L24: COM-DSC-001; COM-DSC-003 | M24: DISCOUNT.CREATE (NEW) / Admin, Seller | N24: discount_codes, discount_code_scopes, outbox_messages | O24: discount_codes | P24: Catalog (validate SHOP/PRODUCT/SKU/CATEGORY ref, optional) | S24: Unique lower(code) among non-deleted | T24: Admin creates SYSTEM (owner NULL); Seller creates SHOP/PRODUCT (owner = JWT sub); PERCENT<=100; ends_at>starts_at; scope ALL iff ref NULL. | U24: 400 VALIDATION_ERROR, 409 VOUCHER_CODE_EXISTS, 403 FORBIDDEN | V24: DSC-02 | W24: G12; G29 | X24: =COUNTIF(Test_Cases!$B$2:$B$1000,A24) -> 8 | Y24: =IF(X24=0,"NO TEST",IF(X24<3,"THIN","OK")) -> OK
A25: DSC-06 | B25: Discount | C25: Update / activate / delete voucher / Sửa, bật tắt, xoá voucher | D25: Public API | E25: PATCH /api/v1/vouchers/{voucherId} | F25: P1 | G25: 4 | H25: M | I25: NEW | J25: PROPOSED. Update, activate/deactivate and soft-delete a voucher. | K25: - (gap: no system SRS section) | L25: COM-DSC-001 | M25: DISCOUNT.UPDATE (NEW) / Admin, Seller (own) | N25: discount_codes, discount_code_scopes | O25: discount_codes, discount_code_usages | P25: - | S25: Optimistic update; counters never edited directly | T25: Owner only; status DRAFT->ACTIVE->INACTIVE/EXPIRED; once used, value/type are immutable; soft delete via deleted_at. | U25: 400 VALIDATION_ERROR, 404 VOUCHER_NOT_FOUND, 409 VOUCHER_ALREADY_USED, 403 FORBIDDEN | V25: DSC-05 | W25: G12; G29 | X25: =COUNTIF(Test_Cases!$B$2:$B$1000,A25) -> 8 | Y25: =IF(X25=0,"NO TEST",IF(X25<3,"THIN","OK")) -> OK
A26: DSC-07 | B26: Discount | C26: List vouchers for management / Quản lý danh sách voucher | D26: Public API | E26: GET /api/v1/vouchers | F26: P2 | G26: 4 | H26: S | I26: NEW | J26: PROPOSED. Management list (seller: own codes; admin: all) - distinct from buyer-facing DSC-01. | K26: - (gap: no system SRS section) | L26: COM-DSC-001 | M26: DISCOUNT.VIEW (NEW) / Admin, Seller (own) | O26: discount_codes, discount_code_scopes | P26: - | S26: Read-only | T26: Filter by status/scope; paging <=50; seller sees only own owner_seller_id. | U26: 403 FORBIDDEN | V26: DSC-05 | W26: G12; G29 | X26: =COUNTIF(Test_Cases!$B$2:$B$1000,A26) -> 4 | Y26: =IF(X26=0,"NO TEST",IF(X26<3,"THIN","OK")) -> OK
A27: DSC-08 | B27: Discount | C27: Expire vouchers / Job hết hạn voucher | D27: Job | E27: Scheduled - hourly | F27: P2 | G27: 4 | H27: S | I27: NEW | J27: PROPOSED job: ACTIVE codes whose ends_at < now become EXPIRED. | K27: - (gap: no system SRS section) | L27: COM-DSC-007 | M27: System | N27: discount_codes | O27: discount_codes | P27: - | S27: Batch + SKIP LOCKED | T27: Does not touch RESERVED usages (they are released by checkout expiry). | V27: DSC-05 | W27: G12 | X27: =COUNTIF(Test_Cases!$B$2:$B$1000,A27) -> 3 | Y27: =IF(X27=0,"NO TEST",IF(X27<3,"THIN","OK")) -> OK
A28: ORD-01 | B28: Order | C28: List my orders / Lịch sử đơn hàng của tôi | D28: Public API | E28: GET /api/v1/orders | F28: P0 | G28: 3 | H28: M | I28: UNCHANGED | K28: 3.4.3.4 | L28: COM-ORD-002; COM-ORD-012 | M28: ORDER.LIST / Buyer (own) | O28: orders, auction_orders, order_items | P28: User batch lookup of seller name (cache; endpoint undefined) | S28: Read-only | T28: UNION ALL orders + auction_orders; buyer_id = JWT sub; deleted_at IS NULL; size<=100; range<=1 year; sort whitelist. | U28: 400 VALIDATION_ERROR | W28: G11 | X28: =COUNTIF(Test_Cases!$B$2:$B$1000,A28) -> 5 | Y28: =IF(X28=0,"NO TEST",IF(X28<3,"THIN","OK")) -> OK
A29: ORD-02 | B29: Order | C29: Get order detail / Chi tiết & theo dõi đơn hàng | D29: Public API | E29: GET /api/v1/orders/{orderId}?orderType=REGULAR|AUCTION | F29: P0 | G29: 3 | H29: L | I29: UNCHANGED | K29: 3.4.3.3 | L29: COM-ORD-003 | M29: ORDER.VIEW / Buyer (own), Seller (own), Admin, Support | O29: orders, auction_orders, order_items, order_status_history, order_cancellations, order_refunds, order_invoices | P29: Fulfillment FUL-18/19/20 (shipment, degrade to null) | S29: Read-only | T29: Buyer own / Seller own (paid_at not null only) / Admin, Support all; forbidden => 404; amounts shown by role (platformFee admin only); allowedActions from state machine. | U29: 404 ORDER_NOT_FOUND | V29: ORD-18 | X29: =COUNTIF(Test_Cases!$B$2:$B$1000,A29) -> 5 | Y29: =IF(X29=0,"NO TEST",IF(X29<3,"THIN","OK")) -> OK
A30: ORD-03 | B30: Order | C30: Seller order list / Danh sách đơn của seller | D30: Public API | E30: GET /api/v1/seller/orders | F30: P0 | G30: 3 | H30: M | I30: UNCHANGED | K30: 3.4.3.4 | L30: COM-ORD-004 | M30: ORDER.LIST / Seller (own) | O30: orders, auction_orders | P30: - | S30: Read-only | T30: paid_at IS NOT NULL mandatory; status=PENDING_PAYMENT -> 400; statusCounts in one GROUP BY; PAID near deadline first. | U30: 400 VALIDATION_ERROR | X30: =COUNTIF(Test_Cases!$B$2:$B$1000,A30) -> 4 | Y30: =IF(X30=0,"NO TEST",IF(X30<3,"THIN","OK")) -> OK
A31: ORD-04 | B31: Order | C31: Seller accept order / Seller xác nhận đơn | D31: Public API | E31: POST /api/v1/seller/orders/{orderId}/accept?orderType= | F31: P0 | G31: 3 | H31: M | I31: UNCHANGED | J31: Event renamed OrderConfirmed per Events spec; Fulfillment FUL-13 must switch the listener name (G13). Shipment creation at CONFIRMED is OQ-20 (behind flag). Status CONFIRMED exists in DB v2. | K31: 3.4.3.2 | L31: COM-ORD-005; COM-AUC-007 | M31: ORDER.CONFIRM (SRS OQ-12) / Seller | N31: orders, auction_orders, order_status_history, outbox_messages | O31: orders, auction_orders | P31: Fulfillment creates shipment asynchronously on OrderConfirmed (FUL-13 listener name to switch, G13) | Q31: OrderConfirmed (renamed from OrderSellerAccepted, spec 2.4.5 PROPOSED) | S31: CAS UPDATE ... WHERE status='PAID' AND row_version=? | T31: seller_id = sub; status PAID; now <= seller_respond_deadline_at; sets seller_accepted_at. | U31: 404 ORDER_NOT_FOUND, 409 ORDER_STATE_CONFLICT, 410 DEADLINE_EXPIRED | V31: ORD-18 | W31: G14 | X31: =COUNTIF(Test_Cases!$B$2:$B$1000,A31) -> 9 | Y31: =IF(X31=0,"NO TEST",IF(X31<3,"THIN","OK")) -> OK
A32: ORD-05 | B32: Order | C32: Seller reject order / Seller từ chối đơn | D32: Public API | E32: POST /api/v1/seller/orders/{orderId}/reject?orderType= | F32: P0 | G32: 3 | H32: L | I32: ADJUSTED | J32: reasonCode is frozen to SELLER_REJECTED (SRS 5.6); Functions.xlsx codes OUT_OF_STOCK / CANNOT_FULFILL / OTHER go into reasonNote. Notification and User listen to OrderSellerRejected: they must listen to OrderCancelled instead (G13). | K32: 3.4.3.2; 3.4.2.4 | L32: COM-ORD-006; COM-CNL-001; COM-RFD-001; COM-AUC-008 | M32: ORDER.REJECT (SRS OQ-12) / Seller | N32: orders, auction_orders, order_cancellations, order_refunds, order_status_history, discount_codes, discount_code_usages, saga_state, outbox_messages | O32: orders, auction_orders | P32: Wallet refund via OrderRefundRequested; Fulfillment release via OrderCancelled; User penalty via event | Q32: OrderCancelled (SELLER_REJECTED, SELLER); OrderRefundRequested | S32: OrderCancellationSaga TX-1 (CAS), rest async | T32: status in {PAID, CONFIRMED}; reasonCode SELLER_REJECTED + reasonNote; 100% refund; was_paid=true. | U32: 409 ORDER_STATE_CONFLICT | V32: ORD-18; ORD-06; DSC-04 | W32: G05; G13 | X32: =COUNTIF(Test_Cases!$B$2:$B$1000,A32) -> 6 | Y32: =IF(X32=0,"NO TEST",IF(X32<3,"THIN","OK")) -> OK
A33: ORD-06 | B33: Order | C33: Cancel order / Huỷ đơn (Buyer, Support, Admin) | D33: Public API | E33: POST /api/v1/orders/{orderId}/cancel?orderType= | F33: P0 | G33: 3 | H33: XL | I33: ADJUSTED | J33: Unpaid normal orders must use CHK-05 (COM-CHK-010); Events spec API 13 allows per-order cancel of PENDING_PAYMENT, SRS wins (G35). reasonCode BUYER_CANCELLED or ADMIN_CANCELLED + reasonNote. Write refund data only to order_refunds. | K33: 3.4.2.4 | L33: COM-CNL-001; COM-CNL-002; COM-CNL-003; COM-CNL-004; COM-RFD-001; COM-AUC-008 | M33: ORDER.CANCEL / Buyer (own), Support, Admin | N33: orders, auction_orders, order_cancellations, order_refunds, order_status_history, discount_codes, discount_code_usages, saga_state, idempotency_keys, outbox_messages | O33: checkout_groups | P33: Wallet refund (async, WAL-06); Fulfillment FUL-10 release (async) | Q33: OrderCancelled; OrderRefundRequested (if was_paid) | S33: Idempotency-Key required; OrderCancellationSaga; UNIQUE order_cancellations per order | T33: Buyer: PAID normal order (not yet CONFIRMED) or PENDING_PAYMENT/PAID auction order; Support/Admin: PAID or CONFIRMED; reasonCode from frozen list; no cancel after SHIPPING. | U33: 404 ORDER_NOT_FOUND, 409 ORDER_NOT_CANCELLABLE, 409 PAYMENT_IN_PROGRESS, 409 IDEMPOTENCY_KEY_CONFLICT | V33: ORD-18; ORD-19; DSC-04 | W33: G05; G35 | X33: =COUNTIF(Test_Cases!$B$2:$B$1000,A33) -> 10 | Y33: =IF(X33=0,"NO TEST",IF(X33<3,"THIN","OK")) -> OK
A34: ORD-07 | B34: Order | C34: Confirm received / Buyer xác nhận đã nhận hàng | D34: Public API | E34: POST /api/v1/orders/{orderId}/confirm-received?orderType= | F34: P2 | G34: 4 | H34: S | I34: ADJUSTED | J34: Behind a feature flag, default OFF: buyer early confirmation is OPEN (SRS COM-ORD-009, OQ-11). Two entry points exist (Fulfillment FUL-23, G08). | K34: 3.4.3.2 | L34: COM-ORD-009 | M34: ORDER.CONFIRM_RECEIVED (NEW) / Buyer | N34: orders, auction_orders, order_status_history, outbox_messages | O34: orders, auction_orders | P34: - | Q34: OrderCompleted | S34: CAS DELIVERED -> COMPLETED | T34: buyer_id = sub; status DELIVERED; COMPLETED opens rating (User) and triggers seller payout (Wallet) + invoice. | U34: 409 ORDER_STATE_CONFLICT | V34: ORD-18 | W34: G08 | X34: =COUNTIF(Test_Cases!$B$2:$B$1000,A34) -> 5 | Y34: =IF(X34=0,"NO TEST",IF(X34<3,"THIN","OK")) -> OK
A35: ORD-08 | B35: Order | C35: Auto-complete delivered orders / Job tự hoàn tất đơn | D35: Job | E35: mỗi giờ | F35: P1 | G35: 3 | H35: S | I35: UNCHANGED | J35: Interval hourly per Events spec 3.4. 'No open dispute' check has no data model. | K35: 3.4.3.2 | L35: COM-ORD-009 | M35: System | N35: orders, auction_orders, order_status_history, outbox_messages | O35: orders, auction_orders, system_settings | P35: - | Q35: OrderCompleted (SYSTEM) | S35: Batch 200, SKIP LOCKED, CAS | T35: DELIVERED older than ORDER_AUTO_COMPLETE_DAYS(7, proposed) -> COMPLETED; both order tables. | V35: ORD-18; ORD-26 | W35: G19 | X35: =COUNTIF(Test_Cases!$B$2:$B$1000,A35) -> 3 | Y35: =IF(X35=0,"NO TEST",IF(X35<3,"THIN","OK")) -> OK
A36: ORD-09 | B36: Order | C36: Seller response timeout / Job quá hạn seller phản hồi | D36: Job | E36: mỗi 1 phút | F36: P0 | G36: 3 | H36: M | I36: UNCHANGED | K36: 3.4.3.2; 3.4.2.4 | L36: COM-ORD-007; COM-CNL-002; COM-RFD-001; COM-AUC-007 | M36: System | N36: orders, auction_orders, order_cancellations, order_refunds, order_status_history, discount_codes, discount_code_usages, saga_state, outbox_messages | O36: orders, auction_orders | P36: Wallet refund; Fulfillment release; User penalty (via events) | Q36: OrderCancelled (SELLER_NO_RESPONSE, SYSTEM); OrderRefundRequested | S36: Every minute; batch + SKIP LOCKED; per-order saga | T36: status=PAID and seller_respond_deadline_at < now -> cancel + 100% refund. | V36: ORD-18; ORD-06 | W36: G05 | X36: =COUNTIF(Test_Cases!$B$2:$B$1000,A36) -> 3 | Y36: =IF(X36=0,"NO TEST",IF(X36<3,"THIN","OK")) -> OK
A37: ORD-10 | B37: Order | C37: Handle shipment events / Nhận sự kiện vận chuyển | D37: Event consumer | E37: shipment.* | F37: P0 | G37: 3 | H37: L | I37: ADJUSTED | J37: Per SRS 3.4.3 / OQ-11 and Events spec 2.5: ShipmentFailed / ShipmentReturned are NOT automated. Fulfillment FUL-17 emits only Delivered / DeliveryFailed (G07). | K37: 3.4.3.2 | L37: COM-ORD-008; COM-AUC-007 | M37: System | N37: inbox_messages, orders, auction_orders, order_status_history, order_cancellations, order_refunds, outbox_messages | O37: orders, auction_orders | P37: Fulfillment shipment events | Q37: OrderShipped; OrderDelivered | R37: ShipmentPickedUp; ShipmentInTransit; ShipmentDelivered; ShipmentFailed; ShipmentReturned | S37: Inbox; out-of-order tolerant (Delivered may arrive before InTransit) | T37: PickedUp -> SHIPPING (shipped_at); InTransit -> record only; Delivered -> DELIVERED (2 history rows if from CONFIRMED); Failed / Returned -> log + alert Support, no state change, no refund. | V37: ORD-18; ORD-24 | W37: G07; G25 | X37: =COUNTIF(Test_Cases!$B$2:$B$1000,A37) -> 4 | Y37: =IF(X37=0,"NO TEST",IF(X37<3,"THIN","OK")) -> OK
A38: ORD-11 | B38: Order | C38: Admin list orders / Quản trị xem tất cả đơn | D38: Public API | E38: GET /api/v1/admin/orders | F38: P1 | G38: 3 | H38: M | I38: UNCHANGED | K38: 3.4.3.5 | L38: COM-ORD-010 | M38: ORDER.LIST / Admin, Support | O38: orders, auction_orders | P38: User batch lookup of buyer/seller names | S38: Read-only | T38: At least one filter or date range; range<=1y; size<=100; audit sensitive field access. | U38: 400 VALIDATION_ERROR | W38: G11 | X38: =COUNTIF(Test_Cases!$B$2:$B$1000,A38) -> 5 | Y38: =IF(X38=0,"NO TEST",IF(X38<3,"THIN","OK")) -> OK
A39: ORD-12 | B39: Order | C39: Admin update order status / Admin chỉnh trạng thái ngoại lệ | D39: Public API | E39: PATCH /api/v1/admin/orders/{orderId}/status?orderType= | F39: P1 | G39: 3 | H39: M | I39: UNCHANGED | K39: 3.4.3.5 | L39: COM-ORD-010; COM-ORD-011; COM-PLT-007 | M39: ORDER.UPDATE_STATUS (NEW) / Admin | N39: orders, auction_orders, order_status_history, outbox_messages | O39: orders, auction_orders | P39: Event Log (audit, via event) | Q39: Event of target status (OrderDelivered / OrderCompleted ...) | S39: CAS via OrderStateMachine | T39: Forward whitelist only; never to CANCELLED, REFUNDED, PAID; reason >= 10 chars; actor ADMIN. | U39: 400 VALIDATION_ERROR, 409 INVALID_TRANSITION | V39: ORD-18 | X39: =COUNTIF(Test_Cases!$B$2:$B$1000,A39) -> 7 | Y39: =IF(X39=0,"NO TEST",IF(X39<3,"THIN","OK")) -> OK
A40: ORD-13 | B40: Order | C40: Admin/Support refund / Hoàn tiền thủ công | D40: Public API | E40: POST /api/v1/admin/orders/{orderId}/refund?orderType= | F40: P1 | G40: 3 | H40: M | I40: UNCHANGED | K40: 3.4.2.4; 3.4.3.5; 3.4.3.7 | L40: COM-RFD-001; COM-RFD-002; COM-RFD-005 | M40: ORDER.REFUND / Admin, Support | N40: order_refunds, order_status_history, idempotency_keys, outbox_messages | O40: orders, auction_orders, order_cancellations | P40: Wallet refund (async) | Q40: OrderRefundRequested | S40: Idempotency-Key required; unique active refund per order | T40: Status in DELIVERED | COMPLETED | CANCELLED(paid, not yet refunded); MVP full amount only; does not write order_cancellations. | U40: 409 REFUND_NOT_ALLOWED, 409 REFUND_ALREADY_REQUESTED, 409 IDEMPOTENCY_KEY_CONFLICT | V40: ORD-19; ORD-18 | W40: G05; G17 | X40: =COUNTIF(Test_Cases!$B$2:$B$1000,A40) -> 8 | Y40: =IF(X40=0,"NO TEST",IF(X40<3,"THIN","OK")) -> OK
A41: ORD-14 | B41: Order | C41: Handle refund result / Nhận kết quả hoàn tiền | D41: Event consumer | E41: payment.refund.* | F41: P0 | G41: 3 | H41: M | I41: ADJUSTED | J41: Stop writing order_cancellations.refund_transaction_id (deprecated). Wallet emits WalletRefunded and has no failure event (G05). | K41: 3.4.2.4 | L41: COM-RFD-003; COM-RFD-004 | M41: System | N41: inbox_messages, order_refunds, orders, auction_orders, order_status_history, outbox_messages | O41: order_refunds | P41: Wallet events | Q41: OrderRefundCompleted | R41: RefundCompleted / RefundFailed (as written); WalletRefunded (Wallet WAL-06) | S41: Inbox; unique refund_transaction_id | T41: COMPLETED needs completed_at + refund_transaction_id (DB CHECK); order -> REFUNDED; RefundFailed -> FAILED + alert (no business event). | V41: ORD-18; ORD-24 | W41: G05 | X41: =COUNTIF(Test_Cases!$B$2:$B$1000,A41) -> 4 | Y41: =IF(X41=0,"NO TEST",IF(X41<3,"THIN","OK")) -> OK
A42: ORD-15 | B42: Invoice | C42: Generate invoice / Sinh hoá đơn | D42: Event consumer | E42: Event consumer (OrderCompleted, nội bộ) + worker bất đồng bộ | F42: P1 | G42: 3 | H42: M | I42: ADJUSTED | J42: NOTI-10 does not list InvoiceGenerated, so the email would never be sent (G13). | K42: 3.4.3.6 | L42: COM-INV-001; COM-INV-002; COM-INV-003 | M42: System | N42: order_invoices, daily_order_sequences, outbox_messages | O42: orders, auction_orders | P42: Object Storage (PDF upload); Notification | Q42: InvoiceGenerated (not in SRS 5.2, PROPOSED) | R42: OrderCompleted (internal) | S42: Unique invoice per order | T42: TX-1 inserts invoice (GENERATED, file_url NULL); worker renders PDF and updates file_url; retry, then FAILED + alert. | V42: ORD-17; ORD-20 | W42: G13 | X42: =COUNTIF(Test_Cases!$B$2:$B$1000,A42) -> 4 | Y42: =IF(X42=0,"NO TEST",IF(X42<3,"THIN","OK")) -> OK
A43: ORD-16 | B43: Invoice | C43: Download invoice / Tải hoá đơn | D43: Public API | E43: GET /api/v1/orders/{orderId}/invoice?orderType= | F43: P1 | G43: 3 | H43: S | I43: UNCHANGED | K43: 3.4.3.6 | L43: COM-INV-002 | M43: ORDER.INVOICE.VIEW (NEW) / Buyer (own), Seller (own), Admin, Support | O43: order_invoices, orders, auction_orders | P43: Object Storage presigned URL (TTL 5 min) | S43: Read-only | T43: Never returns raw file_url; 404 INVOICE_NOT_READY until file exists. | U43: 404 ORDER_NOT_FOUND, 404 INVOICE_NOT_READY | V43: ORD-15 | X43: =COUNTIF(Test_Cases!$B$2:$B$1000,A43) -> 6 | Y43: =IF(X43=0,"NO TEST",IF(X43<3,"THIN","OK")) -> OK
A44: ORD-17 | B44: Platform | C44: Generate order number / Sinh mã đơn | D44: Internal component | E44: SequenceService.next(seqType) | F44: P0 | G44: 0 | H44: S | I44: UNCHANGED | K44: 3.4.3.1 | L44: COM-ORD-001; COM-PLT-005 | M44: System (internal) | N44: daily_order_sequences | P44: - | S44: INSERT ... ON CONFLICT DO UPDATE ... RETURNING (short autocommit TX, before business TX) | T44: ORD-/AOR-/INV-YYYYMMDD-NNNNNN; gaps allowed; day by SYSTEM_TIMEZONE (SRS default UTC). | W44: G21 | X44: =COUNTIF(Test_Cases!$B$2:$B$1000,A44) -> 3 | Y44: =IF(X44=0,"NO TEST",IF(X44<3,"THIN","OK")) -> OK
A45: ORD-18 | B45: Platform | C45: Order state machine / Kiểm soát chuyển trạng thái | D45: Internal component | E45: OrderStateMachine.transition(order, toStatus, actor, reason) | F45: P0 | G45: 0 | H45: L | I45: UNCHANGED | K45: 3.4.3.2; 3.4.3.8 | L45: COM-ORD-011; COM-PLT-007; COM-PLT-008 | M45: System (internal) | N45: orders, auction_orders, order_status_history | O45: orders, auction_orders | P45: - | Q45: Event of target status (through outbox) | S45: CAS: UPDATE ... WHERE status=:from AND row_version=:v | T45: Every status change passes here; validates (from,to,actor); sets paid_at / shipped_at ... ; writes history with order_id XOR auction_order_id. | U45: 409 INVALID_TRANSITION, 409 ORDER_STATE_CONFLICT | V45: ORD-20 | X45: =COUNTIF(Test_Cases!$B$2:$B$1000,A45) -> 3 | Y45: =IF(X45=0,"NO TEST",IF(X45<3,"THIN","OK")) -> OK
A46: ORD-19 | B46: Platform | C46: Idempotency handling / Xử lý idempotency | D46: Internal component | E46: IdempotencyFilter (header Idempotency-Key) | F46: P0 | G46: 0 | H46: M | I46: UNCHANGED | K46: 3.4.3.7 | L46: COM-PLT-001 | M46: System | N46: idempotency_keys | O46: idempotency_keys | P46: - | S46: PK (key, scope); request_hash = SHA-256(body); TTL 24h | T46: Missing key 400; same key + other hash 422; in-progress 409; response replayed; job cleans expired keys. | U46: 400 VAL_IDEMPOTENCY_KEY_REQUIRED, 409 IDEMPOTENCY_KEY_CONFLICT, 409 REQUEST_IN_PROGRESS | X46: =COUNTIF(Test_Cases!$B$2:$B$1000,A46) -> 3 | Y46: =IF(X46=0,"NO TEST",IF(X46<3,"THIN","OK")) -> OK
A47: ORD-20 | B47: Platform | C47: Outbox publisher / Phát event từ outbox | D47: Job | E47: mỗi ~1s | F47: P0 | G47: 0 | H47: M | I47: UNCHANGED | J47: Broker technology (Kafka vs RabbitMQ) undecided in Commerce sheet; other services use RabbitMQ. | K47: 2.8; 5.2 | L47: COM-PLT-002; COM-PLT-009 | M47: System | N47: outbox_messages | O47: outbox_messages | P47: Message broker | Q47: All events (id = event_id) | S47: FOR UPDATE SKIP LOCKED; key = aggregate_id; one active publisher or partitioned by hash | T47: PENDING -> PUBLISHED | FAILED | DEAD; broker down never blocks business TX; purge PUBLISHED > 7 days. | W47: G24 | X47: =COUNTIF(Test_Cases!$B$2:$B$1000,A47) -> 4 | Y47: =IF(X47=0,"NO TEST",IF(X47<3,"THIN","OK")) -> OK
A48: ORD-21 | B48: Platform | C48: Saga recovery / Job phục hồi saga treo | D48: Job | E48: mỗi 2 phút | F48: P0 | G48: 2 | H48: L | I48: UNCHANGED | K48: 3.4.3.8 | L48: COM-PLT-004 | M48: System | N48: saga_state, idempotency_keys, checkout_groups, orders, outbox_messages | O48: saga_state, checkout_groups, orders | P48: Wallet payment status; Fulfillment reservation status (both undefined endpoints) | Q48: OrderPaid / OrderCancelled / CheckoutExpired (outcome dependent) | S48: One TX per saga; CAS row_version | T48: Non-terminal saga with updated_at older than 5 min is recovered; also finalizes idempotency_keys left with NULL response. | V48: CHK-02 | W48: G05; G26 | X48: =COUNTIF(Test_Cases!$B$2:$B$1000,A48) -> 3 | Y48: =IF(X48=0,"NO TEST",IF(X48<3,"THIN","OK")) -> OK
A49: ORD-22 | B49: Platform | C49: Handle inventory events / Nhận sự kiện tồn kho | D49: Event consumer | E49: inventory.* | F49: P1 | G49: 2 | H49: M | I49: ADJUSTED | J49: Fulfillment FUL-11 emits InventoryReleased on expiry, not InventoryReservationExpired (SRS 2.8 name). Align. | K49: 3.6.1.4 (integration) | L49: COM-CHK-008; COM-CNL-003 | M49: System | N49: inbox_messages, order_cancellations, checkout_groups, orders, order_status_history, discount_code_usages, discount_codes, outbox_messages | O49: checkout_groups | P49: Fulfillment events | Q49: OrderCancelled (PAYMENT_TIMEOUT, SYSTEM) | R49: InventoryReleased; InventoryReservationExpired | S49: Inbox | T49: InventoryReleased sets inventory_released=true; InventoryReservationExpired is a safety net: cancels only groups still PENDING_PAYMENT, ignored + alert if already PAID. | V49: CHK-06 | W49: G06 | X49: =COUNTIF(Test_Cases!$B$2:$B$1000,A49) -> 4 | Y49: =IF(X49=0,"NO TEST",IF(X49<3,"THIN","OK")) -> OK
A50: ORD-23 | B50: Order | C50: Rating eligibility check / Kiểm tra đủ điều kiện đánh giá | D50: Internal API | E50: GET /internal/v1/orders/{orderId}/rating-eligibility?userId=&productId= | F50: P1 | G50: 3 | H50: S | I50: NEW | J50: From notes in Functions.xlsx (rows 186-189): internal API for Catalog product reviews and User peer reviews. GET /internal/v1/orders/{orderId}/rating-eligibility?userId=&productId= | K50: 3.1.2.1 (rating after completed order) | L50: COM-ORD-013 | M50: System (service-to-service) | O50: orders, order_items, auction_orders | P50: Called by Catalog (CAT-26/27) and User (REVIEW-01) | S50: Read-only | T50: eligible only when order COMPLETED and buyer_id = userId; containsProduct from order_items (many qty = one review); seller check for peer review. | U50: 404 ORDER_NOT_FOUND | X50: =COUNTIF(Test_Cases!$B$2:$B$1000,A50) -> 3 | Y50: =IF(X50=0,"NO TEST",IF(X50<3,"THIN","OK")) -> OK
A51: ORD-24 | B51: Platform | C51: Inbox retry worker / Job thử lại inbox | D51: Job | E51: Scheduled - every 1 min | F51: P1 | G51: 0 | H51: M | I51: NEW | J51: PROPOSED. DB has idx_inbox_retry but no function retries RECEIVED/FAILED inbox rows. | K51: 5.2; 5.3 | L51: COM-PLT-010; COM-PLT-003 | M51: System | N51: inbox_messages | O51: inbox_messages | P51: - | S51: SKIP LOCKED; retry_count with backoff | T51: Retry RECEIVED/FAILED rows; above threshold keep FAILED and alert (dead letter). | W51: G26 | X51: =COUNTIF(Test_Cases!$B$2:$B$1000,A51) -> 3 | Y51: =IF(X51=0,"NO TEST",IF(X51<3,"THIN","OK")) -> OK
A52: ORD-25 | B52: Order | C52: Refund reconciliation alert / Cảnh báo đối soát refund | D52: Job | E52: Scheduled - every 10 min | F52: P2 | G52: 4 | H52: S | I52: NEW | J52: PROPOSED. DB has idx_order_refunds_pending for Support reconciliation but no function uses it. | K52: 3.4.2.4 | L52: COM-RFD-006; COM-RFD-004 | M52: System | N52: outbox_messages | O52: order_refunds | P52: Notification / alerting | Q52: (alert only) | S52: Read-mostly job | T52: Alert when refund stays REQUESTED too long or is FAILED; threshold from config. | V52: ORD-14 | W52: G26 | X52: =COUNTIF(Test_Cases!$B$2:$B$1000,A52) -> 3 | Y52: =IF(X52=0,"NO TEST",IF(X52<3,"THIN","OK")) -> OK
A53: ORD-26 | B53: Platform | C53: Settings provider / Đọc cấu hình hệ thống | D53: Internal component | E53: SettingsProvider.Get<T>(key) | F53: P1 | G53: 0 | H53: S | I53: NEW | J53: PROPOSED internal SettingsProvider: reads system_settings, caches, refreshes on SystemConfigUpdated. | K53: 2.6; 2.8 (SystemConfigUpdated) | L53: COM-PLT-006 | M53: System (internal) | O53: system_settings | P53: - | R53: SystemConfigUpdated | S53: Cache with refresh | T53: Typed by value_type; missing key falls back to default and logs; seed has 7 keys only. | W53: G20 | X53: =COUNTIF(Test_Cases!$B$2:$B$1000,A53) -> 3 | Y53: =IF(X53=0,"NO TEST",IF(X53<3,"THIN","OK")) -> OK
A54: AO-01 | B54: Auction Order | C54: Create auction order from settlement / Tạo đơn đấu giá | D54: Event consumer | E54: Consumer - AuctionSettled (AuctionWon ignored) | F54: P0 | G54: 4 | H54: L | I54: ADJUSTED | J54: Events spec v2.1 [AGREED Auction 2026-10-27]: consume AuctionSettled (emitted when the winner is determined, BEFORE payment). AuctionWon is ignored (Notification only). Auction sheet AUC-26 / AUC-31 in Functions.xlsx is superseded (Auction still to confirm OQ-22). | K54: 3.5.3.4; 3.4.3.1; 3.4.3.8 | L54: COM-AUC-001; COM-AUC-002; COM-AUC-003; COM-ORD-001; COM-AUC-008 | M54: System | N54: inbox_messages, auction_orders, daily_order_sequences, order_status_history, outbox_messages | O54: system_settings | P54: Catalog CAT-24 (image/attributes snapshot); User (optional validation) | Q54: OrderCreated (orderType=AUCTION) | R54: AuctionSettled | S54: Inbox (message_id, consumer) + UNIQUE(auction_id): duplicate returns the same orderId | T54: Required: auctionId, buyerId, sellerId, productId, skuId, winningBidId, finalPriceAmount, determinedAt, paymentDeadlineAt. Missing -> reject: inbox FAILED + AUCTION_SETTLED_INVALID_PAYLOAD, NO fallback. payment_deadline_at = event value as-is. winning_amount > 0. platform_fee via AUCTION_PLATFORM_FEE_PERCENT (OQ-06). shipping_fee/total NULL until AO-02. FEATURE_AUCTION_ENABLED=false stops consuming. | V54: ORD-17; ORD-18; ORD-26 | W54: G20; G33 | X54: =COUNTIF(Test_Cases!$B$2:$B$1000,A54) -> 8 | Y54: =IF(X54=0,"NO TEST",IF(X54<3,"THIN","OK")) -> OK
A55: AO-02 | B55: Auction Order | C55: Submit shipping info & get quote / Nhập địa chỉ và báo giá ship | D55: Public API | E55: PUT /api/v1/auction-orders/{auctionOrderId}/shipping | F55: P0 | G55: 4 | H55: M | I55: ADJUSTED | J55: Events spec v2.1 [AGREED Auction 2026-10-27]: Commerce does NOT call Auction.CheckPaymentDeadline; deadline checked locally against payment_deadline_at. | K55: 3.5.3.4 | L55: COM-AUC-004; COM-AUC-005; COM-PAY-005 | M55: AUCTION.VIEW + ORDER.UPDATE (NEW) / Buyer (winner) | N55: auction_orders | O55: auction_orders | P55: Fulfillment FUL-12 (shipping quote) | S55: Optimistic lock row_version; can be resubmitted until paid | T55: status PENDING_PAYMENT and now < payment_deadline_at (exact to the second, no job needed) else 410 DEADLINE_EXPIRED; total = winning_amount + shipping_fee (DB CHECK); no address change after PAID. | U55: 409 ORDER_STATE_CONFLICT, 410 DEADLINE_EXPIRED, 503 SHIPPING_QUOTE_UNAVAILABLE | V55: AO-01 | X55: =COUNTIF(Test_Cases!$B$2:$B$1000,A55) -> 8 | Y55: =IF(X55=0,"NO TEST",IF(X55<3,"THIN","OK")) -> OK
A56: AO-03 | B56: Auction Order | C56: Pay auction order / Thanh toán đơn đấu giá | D56: Public API | E56: POST /api/v1/auction-orders/{auctionOrderId}/pay | F56: P0 | G56: 4 | H56: M | I56: ADJUSTED | J56: Events spec v2.1 [AGREED Auction 2026-10-27]: no Auction call. Payment through Wallet (see CHK-03). auction_orders has no payment_attempt_count (G16). | K56: 3.4.2.2 | L56: COM-PAY-005; COM-PAY-001 | M56: CHECKOUT.PAY (NEW) / Buyer (winner) | N56: auction_orders, idempotency_keys | O56: auction_orders | P56: Wallet WAL-05A / WAL-05B | Q56: OrderCheckoutRequested (WALLET) | S56: Idempotency-Key required | T56: Needs shipping_fee_amount and total_amount (else 409 SHIPPING_INFO_REQUIRED); blocked exactly at payment_deadline_at (410 DEADLINE_EXPIRED); PAID only through PAY-01. | U56: 409 SHIPPING_INFO_REQUIRED, 409 ORDER_STATE_CONFLICT, 410 DEADLINE_EXPIRED, 402 INSUFFICIENT_WALLET_BALANCE | V56: AO-02; PAY-01; ORD-19 | W56: G05; G16 | X56: =COUNTIF(Test_Cases!$B$2:$B$1000,A56) -> 10 | Y56: =IF(X56=0,"NO TEST",IF(X56<3,"THIN","OK")) -> OK
A57: AO-04 | B57: Auction Order | C57: Auction payment timeout job / Job quá hạn thanh toán đơn đấu giá | D57: Job | E57: mỗi 1 phút | F57: P0 | G57: 4 | H57: M | I57: ADJUSTED | J57: Events spec v2.1 [AGREED Auction 2026-10-27] (job AUC-PAY) + SRS COM-AUC-006 / OQ-01: Commerce enforces the deadline by a scan job. No AuctionOrderPaymentExpired event; Auction does not set its own timer. | K57: 3.5.3.5 | L57: COM-AUC-006 | M57: System | N57: auction_orders, order_cancellations, order_status_history, outbox_messages | O57: auction_orders | P57: - | Q57: OrderCancelled (PAYMENT_TIMEOUT, SYSTEM, wasPaid=false) | S57: SKIP LOCKED batch; every 1 min (PROPOSED, OQ-19) | T57: auction_orders.status=PENDING_PAYMENT and payment_deadline_at < now -> CAS CANCELLED + order_cancellations(PAYMENT_TIMEOUT, SYSTEM, was_paid=false) + history + OrderCancelled. Penalty is decided by User/Auction (OQ-03), not by Commerce. | V57: AO-01; ORD-18 | W57: G04 | X57: =COUNTIF(Test_Cases!$B$2:$B$1000,A57) -> 3 | Y57: =IF(X57=0,"NO TEST",IF(X57<3,"THIN","OK")) -> OK
A58: AO-05 | B58: Auction Order | C58: Handle AuctionCancelled / Xử lý AuctionCancelled | D58: Event consumer | E58: Consumer - AuctionCancelled | F58: P2 | G58: 4 | H58: S | I58: NEW | J58: Events spec v2.1 [AGREED Auction 2026-10-27]: a session is not cancelled after AuctionSettled. If AuctionCancelled still arrives for a session that already has an order: log + alert Support only. Replaces the earlier AuctionFailed consumer (Commerce does not listen to AuctionFailed). | K58: 3.5.3.4 | L58: COM-AUC-009 | M58: System | N58: inbox_messages | O58: auction_orders | P58: - | R58: AuctionCancelled | S58: Inbox; never changes order state | T58: No order for the auction: ignore. Order exists: log + alert Support, no state change, no refund. | V58: AO-01 | W58: G33 | X58: =COUNTIF(Test_Cases!$B$2:$B$1000,A58) -> 4 | Y58: =IF(X58=0,"NO TEST",IF(X58<3,"THIN","OK")) -> OK

Sheet Trace_Matrix
A1: COM requirement | B1: Module | C1: Requirement (short) | D1: System SRS section | E1: MoSCoW | F1: Backlog IDs | G1: # Functions | H1: API / trigger | I1: DB tables | J1: Events | K1: Integrated services | L1: # Test cases | M1: Coverage | N1: Open gaps
A2: COM-CART-001 | B2: Cart | C2: Cart lifecycle: 1 ACTIVE cart per buyer, lazy create | D2: 3.4.1.1 | E2: Must | F2: CART-01, CART-02 | G2: =SUMPRODUCT(--ISNUMBER(SEARCH(A2,Backlog!$L$2:$L$58))) -> 2 | H2: CART-01: GET /api/v1/carts/me; CART-02: POST /api/v1/carts/me/items | I2: cart_items, carts, checkout_groups, outbox_messages, system_settings | J2: CartCreated; CartItemAdded | K2: Catalog CAT-39; Catalog CAT-39 / CAT-24 | L2: =SUMPRODUCT(--ISNUMBER(SEARCH(A2,Test_Cases!$D$2:$D$1000))) -> 18 | M2: =IF(G2=0,"GAP - no function",IF(L2=0,"NO TEST",IF(L2<3,"THIN","COVERED"))) -> COVERED | N2: G09
A3: COM-CART-002 | B3: Cart | C3: Add item (merge by sku, limits 99/50, no own/auction product) | D3: 3.4.1.1; 3.4.1.2 | E3: Must | F3: CART-02 | G3: =SUMPRODUCT(--ISNUMBER(SEARCH(A3,Backlog!$L$2:$L$58))) -> 1 | H3: CART-02: POST /api/v1/carts/me/items | I3: cart_items, carts, checkout_groups, outbox_messages, system_settings | J3: CartCreated; CartItemAdded | K3: Catalog CAT-39 | L3: =SUMPRODUCT(--ISNUMBER(SEARCH(A3,Test_Cases!$D$2:$D$1000))) -> 14 | M3: =IF(G3=0,"GAP - no function",IF(L3=0,"NO TEST",IF(L3<3,"THIN","COVERED"))) -> COVERED | N3: G09
A4: COM-CART-003 | B4: Cart | C4: Update item quantity | D4: 3.4.1.3 | E4: Must | F4: CART-03 | G4: =SUMPRODUCT(--ISNUMBER(SEARCH(A4,Backlog!$L$2:$L$58))) -> 1 | H4: CART-03: PATCH /api/v1/carts/me/items/{cartItemId} | I4: cart_items, carts, checkout_groups, outbox_messages | J4: CartItemUpdated | K4: Catalog CAT-39 | L4: =SUMPRODUCT(--ISNUMBER(SEARCH(A4,Test_Cases!$D$2:$D$1000))) -> 11 | M4: =IF(G4=0,"GAP - no function",IF(L4=0,"NO TEST",IF(L4<3,"THIN","COVERED"))) -> COVERED | N4: G09
A5: COM-CART-004 | B5: Cart | C5: Remove item(s) | D5: 3.4.1.4 | E5: Must | F5: CART-04, CART-05 | G5: =SUMPRODUCT(--ISNUMBER(SEARCH(A5,Backlog!$L$2:$L$58))) -> 2 | H5: CART-04: DELETE /api/v1/carts/me/items/{cartItemId}; CART-05: POST /api/v1/carts/me/items:bulk-remove | I5: cart_items, carts, checkout_groups, outbox_messages | J5: CartItemRemoved; CartItemRemoved (1 event per batch) | L5: =SUMPRODUCT(--ISNUMBER(SEARCH(A5,Test_Cases!$D$2:$D$1000))) -> 9 | M5: =IF(G5=0,"GAP - no function",IF(L5=0,"NO TEST",IF(L5<3,"THIN","COVERED"))) -> COVERED
A6: COM-CART-005 | B6: Cart | C6: View cart and pricing estimate | D6: 3.4.1.5 | E6: Must | F6: CART-01, CART-07, CART-08 | G6: =SUMPRODUCT(--ISNUMBER(SEARCH(A6,Backlog!$L$2:$L$58))) -> 3 | H6: CART-01: GET /api/v1/carts/me; CART-07: PricingService.calculate(items, address?, vouchers?); CART-08: GET /api/v1/carts/me/summary | I6: cart_items, carts, system_settings | K6: Catalog CAT-39 / CAT-24; DSC-02 | L6: =SUMPRODUCT(--ISNUMBER(SEARCH(A6,Test_Cases!$D$2:$D$1000))) -> 11 | M6: =IF(G6=0,"GAP - no function",IF(L6=0,"NO TEST",IF(L6<3,"THIN","COVERED"))) -> COVERED | N6: G09; G20; G23
A7: COM-CART-006 | B7: Cart | C7: Validate cart before checkout | D7: 3.4.1.6 | E7: Must | F7: CART-06 | G7: =SUMPRODUCT(--ISNUMBER(SEARCH(A7,Backlog!$L$2:$L$58))) -> 1 | H7: CART-06: POST /api/v1/carts/me/validate (+ internal CartValidator dùn | I7: cart_items, carts | K7: Catalog CAT-39 / CAT-24 | L7: =SUMPRODUCT(--ISNUMBER(SEARCH(A7,Test_Cases!$D$2:$D$1000))) -> 6 | M7: =IF(G7=0,"GAP - no function",IF(L7=0,"NO TEST",IF(L7<3,"THIN","COVERED"))) -> COVERED | N7: G09
A8: COM-CART-007 | B8: Cart | C8: Cart expiry job (ABANDONED) | D8: 3.4.1.1 | E8: Should | F8: CART-09 | G8: =SUMPRODUCT(--ISNUMBER(SEARCH(A8,Backlog!$L$2:$L$58))) -> 1 | H8: CART-09: chạy mỗi giờ (@Scheduled + ShedLock) | I8: carts, checkout_groups, outbox_messages, system_settings | J8: CartExpired | L8: =SUMPRODUCT(--ISNUMBER(SEARCH(A8,Test_Cases!$D$2:$D$1000))) -> 3 | M8: =IF(G8=0,"GAP - no function",IF(L8=0,"NO TEST",IF(L8<3,"THIN","COVERED"))) -> COVERED | N8: G26
A9: COM-CART-008 | B9: Cart | C9: Cleanup by Catalog/User events | D9: 3.4.1.4 | E9: Should | F9: CART-11 | G9: =SUMPRODUCT(--ISNUMBER(SEARCH(A9,Backlog!$L$2:$L$58))) -> 1 | H9: CART-11: topics: catalog.*, user.* | I9: cart_items, carts, inbox_messages | J9: ProductDeleted; ProductStatusChanged; UserDeleted | K9: Catalog / User events | L9: =SUMPRODUCT(--ISNUMBER(SEARCH(A9,Test_Cases!$D$2:$D$1000))) -> 4 | M9: =IF(G9=0,"GAP - no function",IF(L9=0,"NO TEST",IF(L9<3,"THIN","COVERED"))) -> COVERED
A10: COM-CART-009 | B10: Cart | C10: Guest cart / merge on login (OPEN OQ-04) | D10: 3.4.1.1 | E10: Could | F10: CART-10 | G10: =SUMPRODUCT(--ISNUMBER(SEARCH(A10,Backlog!$L$2:$L$58))) -> 1 | H10: CART-10: POST /api/v1/carts/me/merge | I10: cart_items, carts, outbox_messages, system_settings | J10: CartItemAdded | K10: Catalog CAT-39; Fulfillment FUL-04 | L10: =SUMPRODUCT(--ISNUMBER(SEARCH(A10,Test_Cases!$D$2:$D$1000))) -> 6 | M10: =IF(G10=0,"GAP - no function",IF(L10=0,"NO TEST",IF(L10<3,"THIN","COVERED"))) -> COVERED | N10: G23
A11: COM-CHK-001 | B11: Checkout | C11: Start checkout (preview + create) | D11: 3.4.2.1 | E11: Must | F11: CHK-01, CHK-02 | G11: =SUMPRODUCT(--ISNUMBER(SEARCH(A11,Backlog!$L$2:$L$58))) -> 2 | H11: CHK-01: POST /api/v1/checkout/preview; CHK-02: POST /api/v1/checkout | I11: cart_items, carts, checkout_groups, daily_order_sequences, discount_code_scopes, discount_code_usages, discount_codes, idempotency_keys, order_items, order_status_history, orders, outbox_messages, saga_state, system_settings | J11: CheckoutStarted; InventoryReserved (Fulfillment, async variant); OrderCreated (per order) | K11: Catalog CAT-39; Catalog CAT-39/24; Fulfillment FUL-12 shipping quote | L11: =SUMPRODUCT(--ISNUMBER(SEARCH(A11,Test_Cases!$D$2:$D$1000))) -> 22 | M11: =IF(G11=0,"GAP - no function",IF(L11=0,"NO TEST",IF(L11<3,"THIN","COVERED"))) -> COVERED | N11: G05; G06; G09; G11
A12: COM-CHK-002 | B12: Checkout | C12: Split orders per seller | D12: 3.4.2.1 | E12: Must | F12: CHK-02 | G12: =SUMPRODUCT(--ISNUMBER(SEARCH(A12,Backlog!$L$2:$L$58))) -> 1 | H12: CHK-02: POST /api/v1/checkout | I12: cart_items, carts, checkout_groups, daily_order_sequences, discount_code_usages, discount_codes, idempotency_keys, order_items, order_status_history, orders, outbox_messages, saga_state, system_settings | J12: CheckoutStarted; InventoryReserved (Fulfillment, async variant); OrderCreated (per order) | K12: Catalog CAT-39 | L12: =SUMPRODUCT(--ISNUMBER(SEARCH(A12,Test_Cases!$D$2:$D$1000))) -> 15 | M12: =IF(G12=0,"GAP - no function",IF(L12=0,"NO TEST",IF(L12<3,"THIN","COVERED"))) -> COVERED | N12: G06; G11
A13: COM-CHK-003 | B13: Checkout | C13: Per-order pricing + invariant | D13: 3.4.1.5 | E13: Must | F13: CART-07, CHK-01, CHK-02 | G13: =SUMPRODUCT(--ISNUMBER(SEARCH(A13,Backlog!$L$2:$L$58))) -> 3 | H13: CART-07: PricingService.calculate(items, address?, vouchers?); CHK-01: POST /api/v1/checkout/preview; CHK-02: POST /api/v1/checkout | I13: cart_items, carts, checkout_groups, daily_order_sequences, discount_code_scopes, discount_code_usages, discount_codes, idempotency_keys, order_items, order_status_history, orders, outbox_messages, saga_state, system_settings | J13: CheckoutStarted; InventoryReserved (Fulfillment, async variant); OrderCreated (per order) | K13: Catalog CAT-39; Catalog CAT-39/24; Fulfillment FUL-12 shipping quote; DSC-02 | L13: =SUMPRODUCT(--ISNUMBER(SEARCH(A13,Test_Cases!$D$2:$D$1000))) -> 25 | M13: =IF(G13=0,"GAP - no function",IF(L13=0,"NO TEST",IF(L13<3,"THIN","COVERED"))) -> COVERED | N13: G05; G06; G09; G11; G20; G23
A14: COM-CHK-004 | B14: Checkout | C14: Shipping fee quote | D14: 3.4.2.1 | E14: Must | F14: CHK-01 | G14: =SUMPRODUCT(--ISNUMBER(SEARCH(A14,Backlog!$L$2:$L$58))) -> 1 | H14: CHK-01: POST /api/v1/checkout/preview | I14: cart_items, carts, discount_code_scopes, discount_code_usages, discount_codes, system_settings | K14: Catalog CAT-39/24; Fulfillment FUL-12 shipping quote | L14: =SUMPRODUCT(--ISNUMBER(SEARCH(A14,Test_Cases!$D$2:$D$1000))) -> 6 | M14: =IF(G14=0,"GAP - no function",IF(L14=0,"NO TEST",IF(L14<3,"THIN","COVERED"))) -> COVERED | N14: G05; G09
A15: COM-CHK-005 | B15: Checkout | C15: Persist group + orders in one TX | D15: 3.4.3.1 | E15: Must | F15: CHK-02 | G15: =SUMPRODUCT(--ISNUMBER(SEARCH(A15,Backlog!$L$2:$L$58))) -> 1 | H15: CHK-02: POST /api/v1/checkout | I15: cart_items, carts, checkout_groups, daily_order_sequences, discount_code_usages, discount_codes, idempotency_keys, order_items, order_status_history, orders, outbox_messages, saga_state, system_settings | J15: CheckoutStarted; InventoryReserved (Fulfillment, async variant); OrderCreated (per order) | K15: Catalog CAT-39 | L15: =SUMPRODUCT(--ISNUMBER(SEARCH(A15,Test_Cases!$D$2:$D$1000))) -> 16 | M15: =IF(G15=0,"GAP - no function",IF(L15=0,"NO TEST",IF(L15<3,"THIN","COVERED"))) -> COVERED | N15: G06; G11
A16: COM-CHK-006 | B16: Checkout | C16: Reserve voucher and inventory | D16: 3.4.3.8 | E16: Must | F16: CHK-02 | G16: =SUMPRODUCT(--ISNUMBER(SEARCH(A16,Backlog!$L$2:$L$58))) -> 1 | H16: CHK-02: POST /api/v1/checkout | I16: cart_items, carts, checkout_groups, daily_order_sequences, discount_code_usages, discount_codes, idempotency_keys, order_items, order_status_history, orders, outbox_messages, saga_state, system_settings | J16: CheckoutStarted; InventoryReserved (Fulfillment, async variant); OrderCreated (per order) | K16: Catalog CAT-39 | L16: =SUMPRODUCT(--ISNUMBER(SEARCH(A16,Test_Cases!$D$2:$D$1000))) -> 15 | M16: =IF(G16=0,"GAP - no function",IF(L16=0,"NO TEST",IF(L16<3,"THIN","COVERED"))) -> COVERED | N16: G06; G11
A17: COM-CHK-007 | B17: Checkout | C17: Block parallel checkout per cart | D17: 3.4.2.1 | E17: Must | F17: CHK-02 | G17: =SUMPRODUCT(--ISNUMBER(SEARCH(A17,Backlog!$L$2:$L$58))) -> 1 | H17: CHK-02: POST /api/v1/checkout | I17: cart_items, carts, checkout_groups, daily_order_sequences, discount_code_usages, discount_codes, idempotency_keys, order_items, order_status_history, orders, outbox_messages, saga_state, system_settings | J17: CheckoutStarted; InventoryReserved (Fulfillment, async variant); OrderCreated (per order) | K17: Catalog CAT-39 | L17: =SUMPRODUCT(--ISNUMBER(SEARCH(A17,Test_Cases!$D$2:$D$1000))) -> 16 | M17: =IF(G17=0,"GAP - no function",IF(L17=0,"NO TEST",IF(L17<3,"THIN","COVERED"))) -> COVERED | N17: G06; G11
A18: COM-CHK-008 | B18: Checkout | C18: Checkout expiry job | D18: 3.4.2.4; 3.4.3.8 | E18: Must | F18: CHK-06, ORD-22 | G18: =SUMPRODUCT(--ISNUMBER(SEARCH(A18,Backlog!$L$2:$L$58))) -> 2 | H18: CHK-06: mỗi 1 phút (+ consumer InventoryReservationExpired làm lưới ; ORD-22: inventory.* | I18: checkout_groups, discount_code_usages, discount_codes, inbox_messages, order_cancellations, order_status_history, orders, outbox_messages, saga_state | J18: CheckoutExpired; InventoryReleased; InventoryReservationExpired; OrderCancelled (PAYMENT_TIMEOUT, SYSTEM) | K18: Fulfillment events; Wallet payment status by referenceIds | L18: =SUMPRODUCT(--ISNUMBER(SEARCH(A18,Test_Cases!$D$2:$D$1000))) -> 8 | M18: =IF(G18=0,"GAP - no function",IF(L18=0,"NO TEST",IF(L18<3,"THIN","COVERED"))) -> COVERED | N18: G05; G06
A19: COM-CHK-009 | B19: Checkout | C19: Checkout group view / history | D19: 3.4.2.3 | E19: Must | F19: CHK-04 | G19: =SUMPRODUCT(--ISNUMBER(SEARCH(A19,Backlog!$L$2:$L$58))) -> 1 | H19: CHK-04: GET /api/v1/checkout-groups/{checkoutGroupId} | I19: checkout_groups, orders | L19: =SUMPRODUCT(--ISNUMBER(SEARCH(A19,Test_Cases!$D$2:$D$1000))) -> 4 | M19: =IF(G19=0,"GAP - no function",IF(L19=0,"NO TEST",IF(L19<3,"THIN","COVERED"))) -> COVERED
A20: COM-CHK-010 | B20: Checkout | C20: Buyer cancels unpaid checkout (PROPOSED) | D20: 3.4.2.4 | E20: Should | F20: CHK-05 | G20: =SUMPRODUCT(--ISNUMBER(SEARCH(A20,Backlog!$L$2:$L$58))) -> 1 | H20: CHK-05: POST /api/v1/checkout-groups/{checkoutGroupId}/cancel | I20: checkout_groups, discount_code_usages, discount_codes, order_cancellations, order_status_history, orders, outbox_messages, saga_state | J20: CheckoutCancelled; OrderCancelled (per order) | K20: Wallet | L20: =SUMPRODUCT(--ISNUMBER(SEARCH(A20,Test_Cases!$D$2:$D$1000))) -> 7 | M20: =IF(G20=0,"GAP - no function",IF(L20=0,"NO TEST",IF(L20<3,"THIN","COVERED"))) -> COVERED | N20: G05
A21: COM-PAY-001 | B21: Payment (Commerce side) | C21: Initiate payment for group / auction order | D21: 3.4.2.2 | E21: Must | F21: CHK-03, AO-03 | G21: =SUMPRODUCT(--ISNUMBER(SEARCH(A21,Backlog!$L$2:$L$58))) -> 2 | H21: CHK-03: POST /api/v1/checkout-groups/{checkoutGroupId}/pay; AO-03: POST /api/v1/auction-orders/{auctionOrderId}/pay | I21: auction_orders, checkout_groups, idempotency_keys, orders, outbox_messages, saga_state | J21: OrderCheckoutRequested (WALLET path, per WAL-05A); OrderCheckoutRequested (WALLET) | K21: Wallet WAL-05A; Wallet WAL-05A / WAL-05B | L21: =SUMPRODUCT(--ISNUMBER(SEARCH(A21,Test_Cases!$D$2:$D$1000))) -> 22 | M21: =IF(G21=0,"GAP - no function",IF(L21=0,"NO TEST",IF(L21<3,"THIN","COVERED"))) -> COVERED | N21: G05; G16
A22: COM-PAY-002 | B22: Payment (Commerce side) | C22: Payment success handling | D22: 3.4.3.7; 3.4.3.8 | E22: Must | F22: PAY-01 | G22: =SUMPRODUCT(--ISNUMBER(SEARCH(A22,Backlog!$L$2:$L$58))) -> 1 | H22: PAY-01: PaymentSucceeded | PaymentFailed | PaymentExpired (event do | I22: auction_orders, cart_items, carts, checkout_groups, discount_code_usages, discount_codes, inbox_messages, order_items, order_refunds, order_status_history, orders, outbox_messages, saga_state | J22: CheckoutCompleted (not in SRS 5.2); OrderPaid (per order); OrderPaymentFailed; OrderRefundRequested (late/mismatch); PaymentSucceeded / PaymentFailed / PaymentExpired (as written); WalletDebitedSuccess / WalletDebitFailed (target) | K22: Wallet events | L22: =SUMPRODUCT(--ISNUMBER(SEARCH(A22,Test_Cases!$D$2:$D$1000))) -> 5 | M22: =IF(G22=0,"GAP - no function",IF(L22=0,"NO TEST",IF(L22<3,"THIN","COVERED"))) -> COVERED | N22: G05
A23: COM-PAY-003 | B23: Payment (Commerce side) | C23: Payment failure / retry limit | D23: 3.4.3.8 | E23: Must | F23: PAY-01 | G23: =SUMPRODUCT(--ISNUMBER(SEARCH(A23,Backlog!$L$2:$L$58))) -> 1 | H23: PAY-01: PaymentSucceeded | PaymentFailed | PaymentExpired (event do | I23: auction_orders, cart_items, carts, checkout_groups, discount_code_usages, discount_codes, inbox_messages, order_items, order_refunds, order_status_history, orders, outbox_messages, saga_state | J23: CheckoutCompleted (not in SRS 5.2); OrderPaid (per order); OrderPaymentFailed; OrderRefundRequested (late/mismatch); PaymentSucceeded / PaymentFailed / PaymentExpired (as written); WalletDebitedSuccess / WalletDebitFailed (target) | K23: Wallet events | L23: =SUMPRODUCT(--ISNUMBER(SEARCH(A23,Test_Cases!$D$2:$D$1000))) -> 4 | M23: =IF(G23=0,"GAP - no function",IF(L23=0,"NO TEST",IF(L23<3,"THIN","COVERED"))) -> COVERED | N23: G05
A24: COM-PAY-004 | B24: Payment (Commerce side) | C24: Late or mismatched payment -> refund | D24: 3.4.3.8 | E24: Must | F24: PAY-01 | G24: =SUMPRODUCT(--ISNUMBER(SEARCH(A24,Backlog!$L$2:$L$58))) -> 1 | H24: PAY-01: PaymentSucceeded | PaymentFailed | PaymentExpired (event do | I24: auction_orders, cart_items, carts, checkout_groups, discount_code_usages, discount_codes, inbox_messages, order_items, order_refunds, order_status_history, orders, outbox_messages, saga_state | J24: CheckoutCompleted (not in SRS 5.2); OrderPaid (per order); OrderPaymentFailed; OrderRefundRequested (late/mismatch); PaymentSucceeded / PaymentFailed / PaymentExpired (as written); WalletDebitedSuccess / WalletDebitFailed (target) | K24: Wallet events | L24: =SUMPRODUCT(--ISNUMBER(SEARCH(A24,Test_Cases!$D$2:$D$1000))) -> 5 | M24: =IF(G24=0,"GAP - no function",IF(L24=0,"NO TEST",IF(L24<3,"THIN","COVERED"))) -> COVERED | N24: G05
A25: COM-PAY-005 | B25: Payment (Commerce side) | C25: Auction order payment preconditions | D25: 3.4.2.2 | E25: Must | F25: AO-02, AO-03 | G25: =SUMPRODUCT(--ISNUMBER(SEARCH(A25,Backlog!$L$2:$L$58))) -> 2 | H25: AO-02: PUT /api/v1/auction-orders/{auctionOrderId}/shipping; AO-03: POST /api/v1/auction-orders/{auctionOrderId}/pay | I25: auction_orders, idempotency_keys | J25: OrderCheckoutRequested (WALLET) | K25: Fulfillment FUL-12; Wallet WAL-05A / WAL-05B | L25: =SUMPRODUCT(--ISNUMBER(SEARCH(A25,Test_Cases!$D$2:$D$1000))) -> 18 | M25: =IF(G25=0,"GAP - no function",IF(L25=0,"NO TEST",IF(L25<3,"THIN","COVERED"))) -> COVERED | N25: G05; G16
A26: COM-ORD-001 | B26: Order | C26: Order creation + order number | D26: 3.4.3.1 | E26: Must | F26: CHK-02, ORD-17, AO-01 | G26: =SUMPRODUCT(--ISNUMBER(SEARCH(A26,Backlog!$L$2:$L$58))) -> 3 | H26: CHK-02: POST /api/v1/checkout; ORD-17: SequenceService.next(seqType); AO-01: Consumer - AuctionSettled (AuctionWon ignored) | I26: auction_orders, cart_items, carts, checkout_groups, daily_order_sequences, discount_code_usages, discount_codes, idempotency_keys, inbox_messages, order_items, order_status_history, orders, outbox_messages, saga_state, system_settings | J26: AuctionSettled; CheckoutStarted; InventoryReserved (Fulfillment, async variant); OrderCreated (orderType=AUCTION); OrderCreated (per order) | K26: Catalog CAT-24; Catalog CAT-39 | L26: =SUMPRODUCT(--ISNUMBER(SEARCH(A26,Test_Cases!$D$2:$D$1000))) -> 22 | M26: =IF(G26=0,"GAP - no function",IF(L26=0,"NO TEST",IF(L26<3,"THIN","COVERED"))) -> COVERED | N26: G06; G11; G20; G21; G33
A27: COM-ORD-002 | B27: Order | C27: Buyer order list | D27: 3.4.3.4 | E27: Must | F27: ORD-01 | G27: =SUMPRODUCT(--ISNUMBER(SEARCH(A27,Backlog!$L$2:$L$58))) -> 1 | H27: ORD-01: GET /api/v1/orders | I27: auction_orders, order_items, orders | K27: User batch lookup of seller name | L27: =SUMPRODUCT(--ISNUMBER(SEARCH(A27,Test_Cases!$D$2:$D$1000))) -> 5 | M27: =IF(G27=0,"GAP - no function",IF(L27=0,"NO TEST",IF(L27<3,"THIN","COVERED"))) -> COVERED | N27: G11
A28: COM-ORD-003 | B28: Order | C28: Order detail + status history | D28: 3.4.3.3 | E28: Must | F28: ORD-02 | G28: =SUMPRODUCT(--ISNUMBER(SEARCH(A28,Backlog!$L$2:$L$58))) -> 1 | H28: ORD-02: GET /api/v1/orders/{orderId}?orderType=REGULAR|AUCTION | I28: auction_orders, order_cancellations, order_invoices, order_items, order_refunds, order_status_history, orders | K28: Fulfillment FUL-18/19/20 | L28: =SUMPRODUCT(--ISNUMBER(SEARCH(A28,Test_Cases!$D$2:$D$1000))) -> 5 | M28: =IF(G28=0,"GAP - no function",IF(L28=0,"NO TEST",IF(L28<3,"THIN","COVERED"))) -> COVERED
A29: COM-ORD-004 | B29: Order | C29: Seller order list (paid only) | D29: 3.4.3.4 | E29: Must | F29: ORD-03 | G29: =SUMPRODUCT(--ISNUMBER(SEARCH(A29,Backlog!$L$2:$L$58))) -> 1 | H29: ORD-03: GET /api/v1/seller/orders | I29: auction_orders, orders | L29: =SUMPRODUCT(--ISNUMBER(SEARCH(A29,Test_Cases!$D$2:$D$1000))) -> 4 | M29: =IF(G29=0,"GAP - no function",IF(L29=0,"NO TEST",IF(L29<3,"THIN","COVERED"))) -> COVERED
A30: COM-ORD-005 | B30: Order | C30: Seller accepts order | D30: 3.4.3.2 | E30: Must | F30: ORD-04 | G30: =SUMPRODUCT(--ISNUMBER(SEARCH(A30,Backlog!$L$2:$L$58))) -> 1 | H30: ORD-04: POST /api/v1/seller/orders/{orderId}/accept?orderType= | I30: auction_orders, order_status_history, orders, outbox_messages | J30: OrderConfirmed (renamed from OrderSellerAccepted, spec 2.4.5 PROPOSED) | K30: Fulfillment creates shipment asynchronously on OrderConfirme | L30: =SUMPRODUCT(--ISNUMBER(SEARCH(A30,Test_Cases!$D$2:$D$1000))) -> 9 | M30: =IF(G30=0,"GAP - no function",IF(L30=0,"NO TEST",IF(L30<3,"THIN","COVERED"))) -> COVERED | N30: G14
A31: COM-ORD-006 | B31: Order | C31: Seller rejects order (PROPOSED) | D31: 3.4.3.2 | E31: Must | F31: ORD-05 | G31: =SUMPRODUCT(--ISNUMBER(SEARCH(A31,Backlog!$L$2:$L$58))) -> 1 | H31: ORD-05: POST /api/v1/seller/orders/{orderId}/reject?orderType= | I31: auction_orders, discount_code_usages, discount_codes, order_cancellations, order_refunds, order_status_history, orders, outbox_messages, saga_state | J31: OrderCancelled (SELLER_REJECTED, SELLER); OrderRefundRequested | K31: Wallet refund via OrderRefundRequested; Fulfillment release | L31: =SUMPRODUCT(--ISNUMBER(SEARCH(A31,Test_Cases!$D$2:$D$1000))) -> 6 | M31: =IF(G31=0,"GAP - no function",IF(L31=0,"NO TEST",IF(L31<3,"THIN","COVERED"))) -> COVERED | N31: G05; G13
A32: COM-ORD-007 | B32: Order | C32: Seller response timeout job | D32: 3.4.3.2 | E32: Must | F32: ORD-09 | G32: =SUMPRODUCT(--ISNUMBER(SEARCH(A32,Backlog!$L$2:$L$58))) -> 1 | H32: ORD-09: mỗi 1 phút | I32: auction_orders, discount_code_usages, discount_codes, order_cancellations, order_refunds, order_status_history, orders, outbox_messages, saga_state | J32: OrderCancelled (SELLER_NO_RESPONSE, SYSTEM); OrderRefundRequested | K32: Wallet refund; Fulfillment release; User penalty | L32: =SUMPRODUCT(--ISNUMBER(SEARCH(A32,Test_Cases!$D$2:$D$1000))) -> 4 | M32: =IF(G32=0,"GAP - no function",IF(L32=0,"NO TEST",IF(L32<3,"THIN","COVERED"))) -> COVERED | N32: G05
A33: COM-ORD-008 | B33: Order | C33: Shipment sync (shipping/delivered) | D33: 3.4.3.2 | E33: Must | F33: ORD-10 | G33: =SUMPRODUCT(--ISNUMBER(SEARCH(A33,Backlog!$L$2:$L$58))) -> 1 | H33: ORD-10: shipment.* | I33: auction_orders, inbox_messages, order_cancellations, order_refunds, order_status_history, orders, outbox_messages | J33: OrderDelivered; OrderShipped; ShipmentDelivered; ShipmentFailed; ShipmentInTransit; ShipmentPickedUp; ShipmentReturned | K33: Fulfillment shipment events | L33: =SUMPRODUCT(--ISNUMBER(SEARCH(A33,Test_Cases!$D$2:$D$1000))) -> 5 | M33: =IF(G33=0,"GAP - no function",IF(L33=0,"NO TEST",IF(L33<3,"THIN","COVERED"))) -> COVERED | N33: G07; G25
A34: COM-ORD-009 | B34: Order | C34: Complete order (buyer / auto) | D34: 3.4.3.2 | E34: Should | F34: ORD-07, ORD-08 | G34: =SUMPRODUCT(--ISNUMBER(SEARCH(A34,Backlog!$L$2:$L$58))) -> 2 | H34: ORD-07: POST /api/v1/orders/{orderId}/confirm-received?orderType=; ORD-08: mỗi giờ | I34: auction_orders, order_status_history, orders, outbox_messages, system_settings | J34: OrderCompleted; OrderCompleted (SYSTEM) | L34: =SUMPRODUCT(--ISNUMBER(SEARCH(A34,Test_Cases!$D$2:$D$1000))) -> 9 | M34: =IF(G34=0,"GAP - no function",IF(L34=0,"NO TEST",IF(L34<3,"THIN","COVERED"))) -> COVERED | N34: G08; G19
A35: COM-ORD-010 | B35: Order | C35: Admin/Support order management | D35: 3.4.3.5 | E35: Should | F35: ORD-11, ORD-12 | G35: =SUMPRODUCT(--ISNUMBER(SEARCH(A35,Backlog!$L$2:$L$58))) -> 2 | H35: ORD-11: GET /api/v1/admin/orders; ORD-12: PATCH /api/v1/admin/orders/{orderId}/status?orderType= | I35: auction_orders, order_status_history, orders, outbox_messages | J35: Event of target status (OrderDelivered / OrderCompleted ...) | K35: Event Log; User batch lookup of buyer/seller names | L35: =SUMPRODUCT(--ISNUMBER(SEARCH(A35,Test_Cases!$D$2:$D$1000))) -> 12 | M35: =IF(G35=0,"GAP - no function",IF(L35=0,"NO TEST",IF(L35<3,"THIN","COVERED"))) -> COVERED | N35: G11
A36: COM-ORD-011 | B36: Order | C36: Enforce state machine | D36: 3.4.3.2 | E36: Must | F36: ORD-12, ORD-18 | G36: =SUMPRODUCT(--ISNUMBER(SEARCH(A36,Backlog!$L$2:$L$58))) -> 2 | H36: ORD-12: PATCH /api/v1/admin/orders/{orderId}/status?orderType=; ORD-18: OrderStateMachine.transition(order, toStatus, actor, reason) | I36: auction_orders, order_status_history, orders, outbox_messages | J36: Event of target status (OrderDelivered / OrderCompleted ...); Event of target status (through outbox) | K36: Event Log | L36: =SUMPRODUCT(--ISNUMBER(SEARCH(A36,Test_Cases!$D$2:$D$1000))) -> 10 | M36: =IF(G36=0,"GAP - no function",IF(L36=0,"NO TEST",IF(L36<3,"THIN","COVERED"))) -> COVERED
A37: COM-ORD-012 | B37: Order | C37: Retention: soft delete only | D37: 5.8 | E37: Should | F37: ORD-01 | G37: =SUMPRODUCT(--ISNUMBER(SEARCH(A37,Backlog!$L$2:$L$58))) -> 1 | H37: ORD-01: GET /api/v1/orders | I37: auction_orders, order_items, orders | K37: User batch lookup of seller name | L37: =SUMPRODUCT(--ISNUMBER(SEARCH(A37,Test_Cases!$D$2:$D$1000))) -> 5 | M37: =IF(G37=0,"GAP - no function",IF(L37=0,"NO TEST",IF(L37<3,"THIN","COVERED"))) -> COVERED | N37: G11
A38: COM-ORD-013 | B38: Order | C38: Rating eligibility API (NEW, from Functions.xlsx notes) | D38: 3.1.2.1 | E38: Should | F38: ORD-23 | G38: =SUMPRODUCT(--ISNUMBER(SEARCH(A38,Backlog!$L$2:$L$58))) -> 1 | H38: ORD-23: GET /internal/v1/orders/{orderId}/rating-eligibility?userId= | I38: auction_orders, order_items, orders | K38: Called by Catalog | L38: =SUMPRODUCT(--ISNUMBER(SEARCH(A38,Test_Cases!$D$2:$D$1000))) -> 3 | M38: =IF(G38=0,"GAP - no function",IF(L38=0,"NO TEST",IF(L38<3,"THIN","COVERED"))) -> COVERED
A39: COM-AUC-001 | B39: Auction Order | C39: Create auction order from Auction result | D39: 3.5.3.4 | E39: Must | F39: AO-01 | G39: =SUMPRODUCT(--ISNUMBER(SEARCH(A39,Backlog!$L$2:$L$58))) -> 1 | H39: AO-01: Consumer - AuctionSettled (AuctionWon ignored) | I39: auction_orders, daily_order_sequences, inbox_messages, order_status_history, outbox_messages, system_settings | J39: AuctionSettled; OrderCreated (orderType=AUCTION) | K39: Catalog CAT-24 | L39: =SUMPRODUCT(--ISNUMBER(SEARCH(A39,Test_Cases!$D$2:$D$1000))) -> 6 | M39: =IF(G39=0,"GAP - no function",IF(L39=0,"NO TEST",IF(L39<3,"THIN","COVERED"))) -> COVERED | N39: G20; G33
A40: COM-AUC-002 | B40: Auction Order | C40: Idempotent creation per auction_id | D40: 3.5.3.4 | E40: Must | F40: AO-01 | G40: =SUMPRODUCT(--ISNUMBER(SEARCH(A40,Backlog!$L$2:$L$58))) -> 1 | H40: AO-01: Consumer - AuctionSettled (AuctionWon ignored) | I40: auction_orders, daily_order_sequences, inbox_messages, order_status_history, outbox_messages, system_settings | J40: AuctionSettled; OrderCreated (orderType=AUCTION) | K40: Catalog CAT-24 | L40: =SUMPRODUCT(--ISNUMBER(SEARCH(A40,Test_Cases!$D$2:$D$1000))) -> 5 | M40: =IF(G40=0,"GAP - no function",IF(L40=0,"NO TEST",IF(L40<3,"THIN","COVERED"))) -> COVERED | N40: G20; G33
A41: COM-AUC-003 | B41: Auction Order | C41: Report orderId back to Auction | D41: 3.5.3.4 | E41: Must | F41: AO-01 | G41: =SUMPRODUCT(--ISNUMBER(SEARCH(A41,Backlog!$L$2:$L$58))) -> 1 | H41: AO-01: Consumer - AuctionSettled (AuctionWon ignored) | I41: auction_orders, daily_order_sequences, inbox_messages, order_status_history, outbox_messages, system_settings | J41: AuctionSettled; OrderCreated (orderType=AUCTION) | K41: Catalog CAT-24 | L41: =SUMPRODUCT(--ISNUMBER(SEARCH(A41,Test_Cases!$D$2:$D$1000))) -> 4 | M41: =IF(G41=0,"GAP - no function",IF(L41=0,"NO TEST",IF(L41<3,"THIN","COVERED"))) -> COVERED | N41: G20; G33
A42: COM-AUC-004 | B42: Auction Order | C42: Shipping address + fee quote | D42: 3.5.3.4 | E42: Must | F42: AO-02 | G42: =SUMPRODUCT(--ISNUMBER(SEARCH(A42,Backlog!$L$2:$L$58))) -> 1 | H42: AO-02: PUT /api/v1/auction-orders/{auctionOrderId}/shipping | I42: auction_orders | K42: Fulfillment FUL-12 | L42: =SUMPRODUCT(--ISNUMBER(SEARCH(A42,Test_Cases!$D$2:$D$1000))) -> 9 | M42: =IF(G42=0,"GAP - no function",IF(L42=0,"NO TEST",IF(L42<3,"THIN","COVERED"))) -> COVERED
A43: COM-AUC-005 | B43: Auction Order | C43: Payment deadline (24h) | D43: 3.5.3.4 | E43: Must | F43: AO-02 | G43: =SUMPRODUCT(--ISNUMBER(SEARCH(A43,Backlog!$L$2:$L$58))) -> 1 | H43: AO-02: PUT /api/v1/auction-orders/{auctionOrderId}/shipping | I43: auction_orders | K43: Fulfillment FUL-12 | L43: =SUMPRODUCT(--ISNUMBER(SEARCH(A43,Test_Cases!$D$2:$D$1000))) -> 10 | M43: =IF(G43=0,"GAP - no function",IF(L43=0,"NO TEST",IF(L43<3,"THIN","COVERED"))) -> COVERED
A44: COM-AUC-006 | B44: Auction Order | C44: Payment timeout handling | D44: 3.5.3.5 | E44: Must | F44: AO-04 | G44: =SUMPRODUCT(--ISNUMBER(SEARCH(A44,Backlog!$L$2:$L$58))) -> 1 | H44: AO-04: mỗi 1 phút | I44: auction_orders, order_cancellations, order_status_history, outbox_messages | J44: OrderCancelled (PAYMENT_TIMEOUT, SYSTEM, wasPaid=false) | L44: =SUMPRODUCT(--ISNUMBER(SEARCH(A44,Test_Cases!$D$2:$D$1000))) -> 4 | M44: =IF(G44=0,"GAP - no function",IF(L44=0,"NO TEST",IF(L44<3,"THIN","COVERED"))) -> COVERED | N44: G04
A45: COM-AUC-007 | B45: Auction Order | C45: Post-payment flow same as normal order | D45: 3.5.3.4 | E45: Should | F45: PAY-01, ORD-04, ORD-09, ORD-10 | G45: =SUMPRODUCT(--ISNUMBER(SEARCH(A45,Backlog!$L$2:$L$58))) -> 4 | H45: PAY-01: PaymentSucceeded | PaymentFailed | PaymentExpired (event do ; ORD-04: POST /api/v1/seller/orders/{orderId}/accept?orderType=; ORD-09: mỗi 1 phút; ORD-10: shipment.* | I45: auction_orders, cart_items, carts, checkout_groups, discount_code_usages, discount_codes, inbox_messages, order_cancellations, order_items, order_refunds, order_status_history, orders, outbox_messages, saga_state | J45: CheckoutCompleted (not in SRS 5.2); OrderCancelled (SELLER_NO_RESPONSE, SYSTEM); OrderConfirmed (renamed from OrderSellerAccepted, spec 2.4.5 PROPOSED); OrderDelivered; OrderPaid (per order); OrderPaymentFailed; OrderRefundRequested; OrderRefundRequested (late/mismatch); OrderShipped; PaymentSucceeded / PaymentFailed / PaymentExpired (as written); ShipmentDelivered; ShipmentFailed; ShipmentInTransit; ShipmentPickedUp; ShipmentReturned; WalletDebitedSuccess / WalletDebitFailed (target) | K45: Fulfillment creates shipment asynchronously on OrderConfirme; Fulfillment shipment events; Wallet events; Wallet refund; Fulfillment release; User penalty | L45: =SUMPRODUCT(--ISNUMBER(SEARCH(A45,Test_Cases!$D$2:$D$1000))) -> 19 | M45: =IF(G45=0,"GAP - no function",IF(L45=0,"NO TEST",IF(L45<3,"THIN","COVERED"))) -> COVERED | N45: G05; G07; G14; G25
A46: COM-AUC-008 | B46: Auction Order | C46: Events carry orderType/auctionId | D46: 5.4 | E46: Must | F46: PAY-01, ORD-05, ORD-06, AO-01 | G46: =SUMPRODUCT(--ISNUMBER(SEARCH(A46,Backlog!$L$2:$L$58))) -> 4 | H46: PAY-01: PaymentSucceeded | PaymentFailed | PaymentExpired (event do ; ORD-05: POST /api/v1/seller/orders/{orderId}/reject?orderType=; ORD-06: POST /api/v1/orders/{orderId}/cancel?orderType=; AO-01: Consumer - AuctionSettled (AuctionWon ignored) | I46: auction_orders, cart_items, carts, checkout_groups, daily_order_sequences, discount_code_usages, discount_codes, idempotency_keys, inbox_messages, order_cancellations, order_items, order_refunds, order_status_history, orders, outbox_messages, saga_state, system_settings | J46: AuctionSettled; CheckoutCompleted (not in SRS 5.2); OrderCancelled; OrderCancelled (SELLER_REJECTED, SELLER); OrderCreated (orderType=AUCTION); OrderPaid (per order); OrderPaymentFailed; OrderRefundRequested; OrderRefundRequested (if was_paid); OrderRefundRequested (late/mismatch); PaymentSucceeded / PaymentFailed / PaymentExpired (as written); WalletDebitedSuccess / WalletDebitFailed (target) | K46: Catalog CAT-24; Wallet events; Wallet refund; Wallet refund via OrderRefundRequested; Fulfillment release | L46: =SUMPRODUCT(--ISNUMBER(SEARCH(A46,Test_Cases!$D$2:$D$1000))) -> 23 | M46: =IF(G46=0,"GAP - no function",IF(L46=0,"NO TEST",IF(L46<3,"THIN","COVERED"))) -> COVERED | N46: G05; G13; G20; G33; G35
A47: COM-AUC-009 | B47: Auction Order | C47: Handle AuctionCancelled: log + alert only (NEW, not in SRS) | D47: 3.5.3.5 | E47: Could | F47: AO-05 | G47: =SUMPRODUCT(--ISNUMBER(SEARCH(A47,Backlog!$L$2:$L$58))) -> 1 | H47: AO-05: Consumer - AuctionCancelled | I47: auction_orders, inbox_messages | J47: AuctionCancelled | L47: =SUMPRODUCT(--ISNUMBER(SEARCH(A47,Test_Cases!$D$2:$D$1000))) -> 4 | M47: =IF(G47=0,"GAP - no function",IF(L47=0,"NO TEST",IF(L47<3,"THIN","COVERED"))) -> COVERED | N47: G33
A48: COM-CNL-001 | B48: Cancellation | C48: Cancellation eligibility | D48: 3.4.2.4 | E48: Must | F48: CHK-05, ORD-05, ORD-06 | G48: =SUMPRODUCT(--ISNUMBER(SEARCH(A48,Backlog!$L$2:$L$58))) -> 3 | H48: CHK-05: POST /api/v1/checkout-groups/{checkoutGroupId}/cancel; ORD-05: POST /api/v1/seller/orders/{orderId}/reject?orderType=; ORD-06: POST /api/v1/orders/{orderId}/cancel?orderType= | I48: auction_orders, checkout_groups, discount_code_usages, discount_codes, idempotency_keys, order_cancellations, order_refunds, order_status_history, orders, outbox_messages, saga_state | J48: CheckoutCancelled; OrderCancelled; OrderCancelled (SELLER_REJECTED, SELLER); OrderCancelled (per order); OrderRefundRequested; OrderRefundRequested (if was_paid) | K48: Wallet; Wallet refund; Wallet refund via OrderRefundRequested; Fulfillment release | L48: =SUMPRODUCT(--ISNUMBER(SEARCH(A48,Test_Cases!$D$2:$D$1000))) -> 23 | M48: =IF(G48=0,"GAP - no function",IF(L48=0,"NO TEST",IF(L48<3,"THIN","COVERED"))) -> COVERED | N48: G05; G13; G35
A49: COM-CNL-002 | B49: Cancellation | C49: Cancellation processing (one TX) | D49: 3.4.2.4 | E49: Must | F49: ORD-06, ORD-09 | G49: =SUMPRODUCT(--ISNUMBER(SEARCH(A49,Backlog!$L$2:$L$58))) -> 2 | H49: ORD-06: POST /api/v1/orders/{orderId}/cancel?orderType=; ORD-09: mỗi 1 phút | I49: auction_orders, checkout_groups, discount_code_usages, discount_codes, idempotency_keys, order_cancellations, order_refunds, order_status_history, orders, outbox_messages, saga_state | J49: OrderCancelled; OrderCancelled (SELLER_NO_RESPONSE, SYSTEM); OrderRefundRequested; OrderRefundRequested (if was_paid) | K49: Wallet refund; Wallet refund; Fulfillment release; User penalty | L49: =SUMPRODUCT(--ISNUMBER(SEARCH(A49,Test_Cases!$D$2:$D$1000))) -> 14 | M49: =IF(G49=0,"GAP - no function",IF(L49=0,"NO TEST",IF(L49<3,"THIN","COVERED"))) -> COVERED | N49: G05; G35
A50: COM-CNL-003 | B50: Cancellation | C50: Release inventory and voucher | D50: 3.4.2.4 | E50: Must | F50: ORD-06, ORD-22 | G50: =SUMPRODUCT(--ISNUMBER(SEARCH(A50,Backlog!$L$2:$L$58))) -> 2 | H50: ORD-06: POST /api/v1/orders/{orderId}/cancel?orderType=; ORD-22: inventory.* | I50: auction_orders, checkout_groups, discount_code_usages, discount_codes, idempotency_keys, inbox_messages, order_cancellations, order_refunds, order_status_history, orders, outbox_messages, saga_state | J50: InventoryReleased; InventoryReservationExpired; OrderCancelled; OrderCancelled (PAYMENT_TIMEOUT, SYSTEM); OrderRefundRequested (if was_paid) | K50: Fulfillment events; Wallet refund | L50: =SUMPRODUCT(--ISNUMBER(SEARCH(A50,Test_Cases!$D$2:$D$1000))) -> 14 | M50: =IF(G50=0,"GAP - no function",IF(L50=0,"NO TEST",IF(L50<3,"THIN","COVERED"))) -> COVERED | N50: G05; G06; G35
A51: COM-CNL-004 | B51: Cancellation | C51: Refund trigger when was_paid | D51: 3.4.2.4 | E51: Must | F51: ORD-06 | G51: =SUMPRODUCT(--ISNUMBER(SEARCH(A51,Backlog!$L$2:$L$58))) -> 1 | H51: ORD-06: POST /api/v1/orders/{orderId}/cancel?orderType= | I51: auction_orders, checkout_groups, discount_code_usages, discount_codes, idempotency_keys, order_cancellations, order_refunds, order_status_history, orders, outbox_messages, saga_state | J51: OrderCancelled; OrderRefundRequested (if was_paid) | K51: Wallet refund | L51: =SUMPRODUCT(--ISNUMBER(SEARCH(A51,Test_Cases!$D$2:$D$1000))) -> 11 | M51: =IF(G51=0,"GAP - no function",IF(L51=0,"NO TEST",IF(L51<3,"THIN","COVERED"))) -> COVERED | N51: G05; G35
A52: COM-RFD-001 | B52: Refund | C52: Create refund request | D52: 3.4.2.4 | E52: Must | F52: ORD-05, ORD-06, ORD-09, ORD-13 | G52: =SUMPRODUCT(--ISNUMBER(SEARCH(A52,Backlog!$L$2:$L$58))) -> 4 | H52: ORD-05: POST /api/v1/seller/orders/{orderId}/reject?orderType=; ORD-06: POST /api/v1/orders/{orderId}/cancel?orderType=; ORD-09: mỗi 1 phút; ORD-13: POST /api/v1/admin/orders/{orderId}/refund?orderType= | I52: auction_orders, checkout_groups, discount_code_usages, discount_codes, idempotency_keys, order_cancellations, order_refunds, order_status_history, orders, outbox_messages, saga_state | J52: OrderCancelled; OrderCancelled (SELLER_NO_RESPONSE, SYSTEM); OrderCancelled (SELLER_REJECTED, SELLER); OrderRefundRequested; OrderRefundRequested (if was_paid) | K52: Wallet refund; Wallet refund via OrderRefundRequested; Fulfillment release ; Wallet refund; Fulfillment release; User penalty | L52: =SUMPRODUCT(--ISNUMBER(SEARCH(A52,Test_Cases!$D$2:$D$1000))) -> 27 | M52: =IF(G52=0,"GAP - no function",IF(L52=0,"NO TEST",IF(L52<3,"THIN","COVERED"))) -> COVERED | N52: G05; G13; G17; G35
A53: COM-RFD-002 | B53: Refund | C53: Refund uniqueness / partial refund | D53: 3.4.2.4 | E53: Must | F53: ORD-13 | G53: =SUMPRODUCT(--ISNUMBER(SEARCH(A53,Backlog!$L$2:$L$58))) -> 1 | H53: ORD-13: POST /api/v1/admin/orders/{orderId}/refund?orderType= | I53: auction_orders, idempotency_keys, order_cancellations, order_refunds, order_status_history, orders, outbox_messages | J53: OrderRefundRequested | K53: Wallet refund | L53: =SUMPRODUCT(--ISNUMBER(SEARCH(A53,Test_Cases!$D$2:$D$1000))) -> 8 | M53: =IF(G53=0,"GAP - no function",IF(L53=0,"NO TEST",IF(L53<3,"THIN","COVERED"))) -> COVERED | N53: G05; G17
A54: COM-RFD-003 | B54: Refund | C54: Handle refund result | D54: 3.4.2.4 | E54: Must | F54: ORD-14 | G54: =SUMPRODUCT(--ISNUMBER(SEARCH(A54,Backlog!$L$2:$L$58))) -> 1 | H54: ORD-14: payment.refund.* | I54: auction_orders, inbox_messages, order_refunds, order_status_history, orders, outbox_messages | J54: OrderRefundCompleted; RefundCompleted / RefundFailed (as written); WalletRefunded (Wallet WAL-06) | K54: Wallet events | L54: =SUMPRODUCT(--ISNUMBER(SEARCH(A54,Test_Cases!$D$2:$D$1000))) -> 5 | M54: =IF(G54=0,"GAP - no function",IF(L54=0,"NO TEST",IF(L54<3,"THIN","COVERED"))) -> COVERED | N54: G05
A55: COM-RFD-004 | B55: Refund | C55: Handle refund failure | D55: 3.4.2.4 | E55: Must | F55: ORD-14, ORD-25 | G55: =SUMPRODUCT(--ISNUMBER(SEARCH(A55,Backlog!$L$2:$L$58))) -> 2 | H55: ORD-14: payment.refund.*; ORD-25: Scheduled - every 10 min | I55: auction_orders, inbox_messages, order_refunds, order_status_history, orders, outbox_messages | J55: (alert only); OrderRefundCompleted; RefundCompleted / RefundFailed (as written); WalletRefunded (Wallet WAL-06) | K55: Notification / alerting; Wallet events | L55: =SUMPRODUCT(--ISNUMBER(SEARCH(A55,Test_Cases!$D$2:$D$1000))) -> 7 | M55: =IF(G55=0,"GAP - no function",IF(L55=0,"NO TEST",IF(L55<3,"THIN","COVERED"))) -> COVERED | N55: G05; G26
A56: COM-RFD-005 | B56: Refund | C56: Manual refund by Admin/Support | D56: 3.4.3.5 | E56: Should | F56: ORD-13 | G56: =SUMPRODUCT(--ISNUMBER(SEARCH(A56,Backlog!$L$2:$L$58))) -> 1 | H56: ORD-13: POST /api/v1/admin/orders/{orderId}/refund?orderType= | I56: auction_orders, idempotency_keys, order_cancellations, order_refunds, order_status_history, orders, outbox_messages | J56: OrderRefundRequested | K56: Wallet refund | L56: =SUMPRODUCT(--ISNUMBER(SEARCH(A56,Test_Cases!$D$2:$D$1000))) -> 8 | M56: =IF(G56=0,"GAP - no function",IF(L56=0,"NO TEST",IF(L56<3,"THIN","COVERED"))) -> COVERED | N56: G05; G17
A57: COM-RFD-006 | B57: Refund | C57: Refund reconciliation alert (NEW) | D57: 3.4.2.4 | E57: Could | F57: ORD-25 | G57: =SUMPRODUCT(--ISNUMBER(SEARCH(A57,Backlog!$L$2:$L$58))) -> 1 | H57: ORD-25: Scheduled - every 10 min | I57: order_refunds, outbox_messages | J57: (alert only) | K57: Notification / alerting | L57: =SUMPRODUCT(--ISNUMBER(SEARCH(A57,Test_Cases!$D$2:$D$1000))) -> 3 | M57: =IF(G57=0,"GAP - no function",IF(L57=0,"NO TEST",IF(L57<3,"THIN","COVERED"))) -> COVERED | N57: G26
A58: COM-DSC-001 | B58: Discount | C58: Voucher management | D58: (none) | E58: Should | F58: DSC-05, DSC-06, DSC-07 | G58: =SUMPRODUCT(--ISNUMBER(SEARCH(A58,Backlog!$L$2:$L$58))) -> 3 | H58: DSC-05: POST /api/v1/vouchers; DSC-06: PATCH /api/v1/vouchers/{voucherId}; DSC-07: GET /api/v1/vouchers | I58: discount_code_scopes, discount_code_usages, discount_codes, outbox_messages | K58: Catalog | L58: =SUMPRODUCT(--ISNUMBER(SEARCH(A58,Test_Cases!$D$2:$D$1000))) -> 20 | M58: =IF(G58=0,"GAP - no function",IF(L58=0,"NO TEST",IF(L58<3,"THIN","COVERED"))) -> COVERED | N58: G12; G29
A59: COM-DSC-002 | B59: Discount | C59: List available vouchers | D59: (none) | E59: Should | F59: DSC-01 | G59: =SUMPRODUCT(--ISNUMBER(SEARCH(A59,Backlog!$L$2:$L$58))) -> 1 | H59: DSC-01: GET /api/v1/vouchers/available?cartItemIds=&sellerId=&page=& | I59: discount_code_scopes, discount_code_usages, discount_codes | K59: Catalog | L59: =SUMPRODUCT(--ISNUMBER(SEARCH(A59,Test_Cases!$D$2:$D$1000))) -> 5 | M59: =IF(G59=0,"GAP - no function",IF(L59=0,"NO TEST",IF(L59<3,"THIN","COVERED"))) -> COVERED | N59: G12
A60: COM-DSC-003 | B60: Discount | C60: Voucher scope | D60: (none) | E60: Must | F60: DSC-02, DSC-05 | G60: =SUMPRODUCT(--ISNUMBER(SEARCH(A60,Backlog!$L$2:$L$58))) -> 2 | H60: DSC-02: VoucherService.validateAndCalculate(code, userId, scopeConte; DSC-05: POST /api/v1/vouchers | I60: discount_code_scopes, discount_code_usages, discount_codes, outbox_messages | K60: Catalog | L60: =SUMPRODUCT(--ISNUMBER(SEARCH(A60,Test_Cases!$D$2:$D$1000))) -> 11 | M60: =IF(G60=0,"GAP - no function",IF(L60=0,"NO TEST",IF(L60<3,"THIN","COVERED"))) -> COVERED | N60: G12; G29
A61: COM-DSC-004 | B61: Discount | C61: Voucher validity rules | D61: (none) | E61: Must | F61: DSC-02, DSC-03 | G61: =SUMPRODUCT(--ISNUMBER(SEARCH(A61,Backlog!$L$2:$L$58))) -> 2 | H61: DSC-02: VoucherService.validateAndCalculate(code, userId, scopeConte; DSC-03: VoucherService.reserve(checkoutGroupId, orderId?, userId, co | I61: discount_code_scopes, discount_code_usages, discount_codes | L61: =SUMPRODUCT(--ISNUMBER(SEARCH(A61,Test_Cases!$D$2:$D$1000))) -> 6 | M61: =IF(G61=0,"GAP - no function",IF(L61=0,"NO TEST",IF(L61<3,"THIN","COVERED"))) -> COVERED | N61: G12
A62: COM-DSC-005 | B62: Discount | C62: Discount calculation + stacking | D62: (none) | E62: Must | F62: DSC-02 | G62: =SUMPRODUCT(--ISNUMBER(SEARCH(A62,Backlog!$L$2:$L$58))) -> 1 | H62: DSC-02: VoucherService.validateAndCalculate(code, userId, scopeConte | I62: discount_code_scopes, discount_code_usages, discount_codes | L62: =SUMPRODUCT(--ISNUMBER(SEARCH(A62,Test_Cases!$D$2:$D$1000))) -> 3 | M62: =IF(G62=0,"GAP - no function",IF(L62=0,"NO TEST",IF(L62<3,"THIN","COVERED"))) -> COVERED | N62: G12
A63: COM-DSC-006 | B63: Discount | C63: Usage lifecycle reserve/confirm/release | D63: (none) | E63: Must | F63: DSC-03, DSC-04 | G63: =SUMPRODUCT(--ISNUMBER(SEARCH(A63,Backlog!$L$2:$L$58))) -> 2 | H63: DSC-03: VoucherService.reserve(checkoutGroupId, orderId?, userId, co; DSC-04: VoucherService.confirm(groupId) / release(orderId|groupId, r | I63: discount_code_usages, discount_codes | L63: =SUMPRODUCT(--ISNUMBER(SEARCH(A63,Test_Cases!$D$2:$D$1000))) -> 6 | M63: =IF(G63=0,"GAP - no function",IF(L63=0,"NO TEST",IF(L63<3,"THIN","COVERED"))) -> COVERED | N63: G18
A64: COM-DSC-007 | B64: Discount | C64: Voucher expiry job (PROPOSED) | D64: (none) | E64: Could | F64: DSC-08 | G64: =SUMPRODUCT(--ISNUMBER(SEARCH(A64,Backlog!$L$2:$L$58))) -> 1 | H64: DSC-08: Scheduled - hourly | I64: discount_codes | L64: =SUMPRODUCT(--ISNUMBER(SEARCH(A64,Test_Cases!$D$2:$D$1000))) -> 3 | M64: =IF(G64=0,"GAP - no function",IF(L64=0,"NO TEST",IF(L64<3,"THIN","COVERED"))) -> COVERED | N64: G12
A65: COM-INV-001 | B65: Invoice | C65: Generate invoice | D65: 3.4.3.6 | E65: Should | F65: ORD-15 | G65: =SUMPRODUCT(--ISNUMBER(SEARCH(A65,Backlog!$L$2:$L$58))) -> 1 | H65: ORD-15: Event consumer (OrderCompleted, nội bộ) + worker bất đồng bộ | I65: auction_orders, daily_order_sequences, order_invoices, orders, outbox_messages | J65: InvoiceGenerated (not in SRS 5.2, PROPOSED); OrderCompleted (internal) | K65: Object Storage | L65: =SUMPRODUCT(--ISNUMBER(SEARCH(A65,Test_Cases!$D$2:$D$1000))) -> 5 | M65: =IF(G65=0,"GAP - no function",IF(L65=0,"NO TEST",IF(L65<3,"THIN","COVERED"))) -> COVERED | N65: G13
A66: COM-INV-002 | B66: Invoice | C66: Deliver invoice (Notification / download) | D66: 3.4.3.6 | E66: Should | F66: ORD-15, ORD-16 | G66: =SUMPRODUCT(--ISNUMBER(SEARCH(A66,Backlog!$L$2:$L$58))) -> 2 | H66: ORD-15: Event consumer (OrderCompleted, nội bộ) + worker bất đồng bộ; ORD-16: GET /api/v1/orders/{orderId}/invoice?orderType= | I66: auction_orders, daily_order_sequences, order_invoices, orders, outbox_messages | J66: InvoiceGenerated (not in SRS 5.2, PROPOSED); OrderCompleted (internal) | K66: Object Storage; Object Storage presigned URL | L66: =SUMPRODUCT(--ISNUMBER(SEARCH(A66,Test_Cases!$D$2:$D$1000))) -> 10 | M66: =IF(G66=0,"GAP - no function",IF(L66=0,"NO TEST",IF(L66<3,"THIN","COVERED"))) -> COVERED | N66: G13
A67: COM-INV-003 | B67: Invoice | C67: Invoice failure + retry | D67: 3.4.3.6 | E67: Should | F67: ORD-15 | G67: =SUMPRODUCT(--ISNUMBER(SEARCH(A67,Backlog!$L$2:$L$58))) -> 1 | H67: ORD-15: Event consumer (OrderCompleted, nội bộ) + worker bất đồng bộ | I67: auction_orders, daily_order_sequences, order_invoices, orders, outbox_messages | J67: InvoiceGenerated (not in SRS 5.2, PROPOSED); OrderCompleted (internal) | K67: Object Storage | L67: =SUMPRODUCT(--ISNUMBER(SEARCH(A67,Test_Cases!$D$2:$D$1000))) -> 4 | M67: =IF(G67=0,"GAP - no function",IF(L67=0,"NO TEST",IF(L67<3,"THIN","COVERED"))) -> COVERED | N67: G13
A68: COM-PLT-001 | B68: Platform | C68: Idempotency keys | D68: 3.4.3.7 | E68: Must | F68: CHK-02, ORD-19 | G68: =SUMPRODUCT(--ISNUMBER(SEARCH(A68,Backlog!$L$2:$L$58))) -> 2 | H68: CHK-02: POST /api/v1/checkout; ORD-19: IdempotencyFilter (header Idempotency-Key) | I68: cart_items, carts, checkout_groups, daily_order_sequences, discount_code_usages, discount_codes, idempotency_keys, order_items, order_status_history, orders, outbox_messages, saga_state, system_settings | J68: CheckoutStarted; InventoryReserved (Fulfillment, async variant); OrderCreated (per order) | K68: Catalog CAT-39 | L68: =SUMPRODUCT(--ISNUMBER(SEARCH(A68,Test_Cases!$D$2:$D$1000))) -> 19 | M68: =IF(G68=0,"GAP - no function",IF(L68=0,"NO TEST",IF(L68<3,"THIN","COVERED"))) -> COVERED | N68: G06; G11
A69: COM-PLT-002 | B69: Platform | C69: Transactional outbox | D69: 2.8; 5.2 | E69: Must | F69: ORD-20 | G69: =SUMPRODUCT(--ISNUMBER(SEARCH(A69,Backlog!$L$2:$L$58))) -> 1 | H69: ORD-20: mỗi ~1s | I69: outbox_messages | J69: All events (id = event_id) | K69: Message broker | L69: =SUMPRODUCT(--ISNUMBER(SEARCH(A69,Test_Cases!$D$2:$D$1000))) -> 4 | M69: =IF(G69=0,"GAP - no function",IF(L69=0,"NO TEST",IF(L69<3,"THIN","COVERED"))) -> COVERED | N69: G24
A70: COM-PLT-003 | B70: Platform | C70: Inbox dedupe | D70: 5.2 | E70: Must | F70: CART-11, ORD-24 | G70: =SUMPRODUCT(--ISNUMBER(SEARCH(A70,Backlog!$L$2:$L$58))) -> 2 | H70: CART-11: topics: catalog.*, user.*; ORD-24: Scheduled - every 1 min | I70: cart_items, carts, inbox_messages | J70: ProductDeleted; ProductStatusChanged; UserDeleted | K70: Catalog / User events | L70: =SUMPRODUCT(--ISNUMBER(SEARCH(A70,Test_Cases!$D$2:$D$1000))) -> 7 | M70: =IF(G70=0,"GAP - no function",IF(L70=0,"NO TEST",IF(L70<3,"THIN","COVERED"))) -> COVERED | N70: G26
A71: COM-PLT-004 | B71: Platform | C71: Saga + recovery | D71: 3.4.3.8 | E71: Must | F71: ORD-21 | G71: =SUMPRODUCT(--ISNUMBER(SEARCH(A71,Backlog!$L$2:$L$58))) -> 1 | H71: ORD-21: mỗi 2 phút | I71: checkout_groups, idempotency_keys, orders, outbox_messages, saga_state | J71: OrderPaid / OrderCancelled / CheckoutExpired (outcome dependent) | K71: Wallet payment status; Fulfillment reservation status | L71: =SUMPRODUCT(--ISNUMBER(SEARCH(A71,Test_Cases!$D$2:$D$1000))) -> 4 | M71: =IF(G71=0,"GAP - no function",IF(L71=0,"NO TEST",IF(L71<3,"THIN","COVERED"))) -> COVERED | N71: G05; G26
A72: COM-PLT-005 | B72: Platform | C72: Daily document sequence | D72: 3.4.3.1 | E72: Must | F72: ORD-17 | G72: =SUMPRODUCT(--ISNUMBER(SEARCH(A72,Backlog!$L$2:$L$58))) -> 1 | H72: ORD-17: SequenceService.next(seqType) | I72: daily_order_sequences | L72: =SUMPRODUCT(--ISNUMBER(SEARCH(A72,Test_Cases!$D$2:$D$1000))) -> 3 | M72: =IF(G72=0,"GAP - no function",IF(L72=0,"NO TEST",IF(L72<3,"THIN","COVERED"))) -> COVERED | N72: G21
A73: COM-PLT-006 | B73: Platform | C73: System settings | D73: 2.6 | E73: Should | F73: ORD-26 | G73: =SUMPRODUCT(--ISNUMBER(SEARCH(A73,Backlog!$L$2:$L$58))) -> 1 | H73: ORD-26: SettingsProvider.Get<T>(key) | I73: system_settings | J73: SystemConfigUpdated | L73: =SUMPRODUCT(--ISNUMBER(SEARCH(A73,Test_Cases!$D$2:$D$1000))) -> 3 | M73: =IF(G73=0,"GAP - no function",IF(L73=0,"NO TEST",IF(L73<3,"THIN","COVERED"))) -> COVERED | N73: G20
A74: COM-PLT-007 | B74: Platform | C74: Audit / status history | D74: 5.8 | E74: Must | F74: ORD-12, ORD-18 | G74: =SUMPRODUCT(--ISNUMBER(SEARCH(A74,Backlog!$L$2:$L$58))) -> 2 | H74: ORD-12: PATCH /api/v1/admin/orders/{orderId}/status?orderType=; ORD-18: OrderStateMachine.transition(order, toStatus, actor, reason) | I74: auction_orders, order_status_history, orders, outbox_messages | J74: Event of target status (OrderDelivered / OrderCompleted ...); Event of target status (through outbox) | K74: Event Log | L74: =SUMPRODUCT(--ISNUMBER(SEARCH(A74,Test_Cases!$D$2:$D$1000))) -> 10 | M74: =IF(G74=0,"GAP - no function",IF(L74=0,"NO TEST",IF(L74<3,"THIN","COVERED"))) -> COVERED
A75: COM-PLT-008 | B75: Platform | C75: Optimistic locking + SKIP LOCKED | D75: 5.2 | E75: Must | F75: ORD-18 | G75: =SUMPRODUCT(--ISNUMBER(SEARCH(A75,Backlog!$L$2:$L$58))) -> 1 | H75: ORD-18: OrderStateMachine.transition(order, toStatus, actor, reason) | I75: auction_orders, order_status_history, orders | J75: Event of target status (through outbox) | L75: =SUMPRODUCT(--ISNUMBER(SEARCH(A75,Test_Cases!$D$2:$D$1000))) -> 3 | M75: =IF(G75=0,"GAP - no function",IF(L75=0,"NO TEST",IF(L75<3,"THIN","COVERED"))) -> COVERED
A76: COM-PLT-009 | B76: Platform | C76: Observability | D76: 5.5 | E76: Should | F76: ORD-20 | G76: =SUMPRODUCT(--ISNUMBER(SEARCH(A76,Backlog!$L$2:$L$58))) -> 1 | H76: ORD-20: mỗi ~1s | I76: outbox_messages | J76: All events (id = event_id) | K76: Message broker | L76: =SUMPRODUCT(--ISNUMBER(SEARCH(A76,Test_Cases!$D$2:$D$1000))) -> 3 | M76: =IF(G76=0,"GAP - no function",IF(L76=0,"NO TEST",IF(L76<3,"THIN","COVERED"))) -> COVERED | N76: G24
A77: COM-PLT-010 | B77: Platform | C77: Inbox retry worker (NEW) | D77: 5.2 | E77: Should | F77: ORD-24 | G77: =SUMPRODUCT(--ISNUMBER(SEARCH(A77,Backlog!$L$2:$L$58))) -> 1 | H77: ORD-24: Scheduled - every 1 min | I77: inbox_messages | L77: =SUMPRODUCT(--ISNUMBER(SEARCH(A77,Test_Cases!$D$2:$D$1000))) -> 3 | M77: =IF(G77=0,"GAP - no function",IF(L77=0,"NO TEST",IF(L77<3,"THIN","COVERED"))) -> COVERED | N77: G26

Sheet API_Catalog
A1: ID | B1: Kind | C1: Method | D1: Path | E1: Name | F1: Permission | G1: Idempotency-Key | H1: Request | I1: Response | J1: Validation | K1: Errors | L1: Change
A2: CART-01 | B2: Public API | C2: GET | D2: /api/v1/carts/me | E2: Get my cart / Lấy giỏ hàng của tôi | F2: CART.VIEW / Buyer | G2: - | H2: Header: Authorization: Bearer <JWT> Query: includeInvalid=true|false (default true) | I2: 200 {cartId (null nếu chưa có giỏ), status, itemCount, subtotalAmount, lastActivityAt, groups:[{sellerId, sellerName, items:[{cartItemId, productId, skuId, productName, skuAttributes, imageUrl, quantity, unitPriceSnapshot, currentUnitPrice, lineTotal, priceChanged, stockAvailable, itemStatus: OK|OUT_OF_STOCK|INACTIVE|PRICE_CHANGED}]}], warnings:[]} | J2: buyerId lấy từ JWT, KHÔNG nhận từ client. | L2: ADJUSTED
A3: CART-02 | B3: Public API | C3: POST | D3: /api/v1/carts/me/items | E3: Add item to cart / Thêm sản phẩm vào giỏ | F3: CART.UPDATE / Buyer | G3: - | H3: Body: {productId: uuid, skuId: uuid, quantity: int} | I3: 200 {cartItemId, quantity, unitPriceSnapshot, cart:{itemCount, subtotalAmount}} | J3: - quantity: số nguyên 1..MAX_QTY_PER_ITEM (config, vd 99) - productId/skuId đúng UUID, SKU thuộc product - Product status = ACTIVE, seller chưa bị khoá - Không mua hàng của chính mình (buyerId ≠ sellerId) - Product không đang bán theo auction (Catalog trả saleMode ≠ AUCTION / không có auction ACTIVE) - Cart không bị khoá: không có checkout_groups PENDING_PAYMENT / PAYMENT_PROCESSING (CART_LOCKED) - Tổng qty sau cộng dồn ≤ tồn khả dụng (soft check) và ≤ MAX_QTY_PER_ITEM (check lại trong SQL upsert) - Số dòng khác nhau ≤ MAX_CART_ITEMS (vd 50) | K3: 400 VALIDATION_ERROR, 404 PRODUCT_NOT_FOUND, 409 PRODUCT_NOT_AVAILABLE, 409 INSUFFICIENT_STOCK, 409 CART_ITEM_LIMIT_EXCEEDED, 409 CANNOT_BUY_OWN_PRODUCT, 409 PRODUCT_IN_AUCTION, 409 CART_LOCKED, 503 CATALOG_UNAVAILABLE | L3: ADJUSTED
A4: CART-03 | B4: Public API | C4: PATCH | D4: /api/v1/carts/me/items/{cartItemId} | E4: Update cart item quantity / Cập nhật số lượng | F4: CART.UPDATE / Buyer | G4: - | H4: Path: cartItemId Body: {quantity: int} | I4: 200 {cartItemId, quantity, lineTotal, cart:{itemCount, subtotalAmount}} | J4: - quantity ≥ 1 và ≤ MAX_QTY_PER_ITEM (muốn xoá dùng DELETE) - Item thuộc cart ACTIVE của chính buyer - quantity ≤ tồn khả dụng - Cart không bị khoá (CART_LOCKED) | K4: 400 VALIDATION_ERROR, 404 CART_ITEM_NOT_FOUND, 409 INSUFFICIENT_STOCK, 409 PRODUCT_NOT_AVAILABLE, 409 CONCURRENT_UPDATE, 409 CART_LOCKED | L4: ADJUSTED
A5: CART-04 | B5: Public API | C5: DELETE | D5: /api/v1/carts/me/items/{cartItemId} | E5: Remove cart item / Xoá một dòng khỏi giỏ | F5: CART.REMOVE_ITEM / Buyer | G5: - | H5: Path: cartItemId | I5: 200 {cart:{itemCount, subtotalAmount}} | J5: - Item thuộc cart ACTIVE của buyer - Idempotent: item đã xoá / không tồn tại / không thuộc buyer → vẫn trả 200 (không lộ tồn tại) - Cart không bị khoá (CART_LOCKED) | K5: 409 CART_LOCKED | L5: ADJUSTED
A6: CART-05 | B6: Public API | C6: POST | D6: /api/v1/carts/me/items:bulk-remove | E6: Bulk remove / clear cart / Xoá nhiều dòng hoặc xoá hết | F6: CART.REMOVE_ITEM / Buyer | G6: - | H6: Body: {cartItemIds:[uuid]} hoặc {all:true} | I6: 200 {removedCount, cart:{itemCount, subtotalAmount}} | J6: - cartItemIds 1..100, hoặc all=true (loại trừ nhau) - Mọi id thuộc cart của buyer (id lạ bỏ qua) | K6: 400 VALIDATION_ERROR, 409 CART_LOCKED | L6: UNCHANGED
A7: CART-06 | B7: Public API | C7: POST | D7: /api/v1/carts/me/validate | E7: Validate cart / Kiểm tra giỏ hàng trước checkout | F7: CART.VIEW / Buyer | G7: - | H7: Body: {cartItemIds?: [uuid]} (rỗng = cả giỏ) | I7: 200 {valid: bool, items:[{cartItemId, issues:[PRICE_CHANGED|OUT_OF_STOCK|INACTIVE|SELLER_SUSPENDED|QTY_EXCEEDS_STOCK], currentUnitPrice, availableQty}]} | J7: - Cart ACTIVE, không rỗng - cartItemIds thuộc cart | K7: 409 CART_EMPTY, 503 CATALOG_UNAVAILABLE | L7: ADJUSTED
A8: CART-08 | B8: Public API | C8: GET | D8: /api/v1/carts/me/summary | E8: Cart summary (badge) / Số lượng giỏ hàng | F8: CART.VIEW / Buyer | G8: - | H8: Header: Authorization | I8: 200 {itemCount, subtotalAmount} | J8: — | L8: UNCHANGED
A9: CART-10 | B9: Public API | C9: POST | D9: /api/v1/carts/me/merge | E9: Merge guest cart on login / Gộp giỏ khách (OPTIONAL) | F9: CART.UPDATE / Buyer | G9: - | H9: Body: {items:[{skuId, quantity}]} | I9: 200 {mergedCount, skippedItems:[{skuId, reason}], cart:{…}} | J9: - ≤ 50 item; mỗi item áp dụng rule của CART-02 | K9: 400 VALIDATION_ERROR, 409 CART_LOCKED | L9: ADJUSTED
A10: CHK-01 | B10: Public API | C10: POST | D10: /api/v1/checkout/preview | E10: Checkout preview / Xem trước thanh toán | F10: CHECKOUT.START / Buyer | G10: - | H10: Body: {cartItemIds?:[uuid], shippingAddress:{receiverName, street, ward, district, province, ghnDistrictId, ghnWardCode}, contactPhone, paymentMethod: WALLET|VNPAY, carrierCode?, vouchers:{system?:code, shops:[{sellerId, code}], products:[{skuId, code}]}} | I10: 200 {orders:[{sellerId, items[], itemsAmount, productDiscountAmount, shopDiscountAmount, platformMarkupAmount, systemDiscountAmount, shippingFeeAmount, totalAmount, shippingOptions[], quoteId}], grandTotal, appliedVouchers[], invalidVouchers:[{code, reason}], walletBalance?, warnings[]} | J10: - Cart không rỗng, các item hợp lệ (CART-06) - shippingAddress đủ trường; contactPhone regex VN (^(0|\+84)\d{9}$) - paymentMethod ∈ {WALLET, VNPAY} (COD chưa hỗ trợ MVP) - Voucher sai KHÔNG làm fail preview, đưa vào invalidVouchers | K10: 409 CART_EMPTY, 409 CART_INVALID | L10: ADJUSTED
A11: CHK-02 | B11: Public API | C11: POST | D11: /api/v1/checkout | E11: Create checkout (group + orders) / Tạo checkout và đơn hàng | F11: CHECKOUT.START + ORDER.CREATE / Buyer | G11: Required | H11: Header: Idempotency-Key: <uuid> (bắt buộc) Body: như CHK-01 + expectedGrandTotal, quoteId (từ CHK-01) | I11: 201 {checkoutGroupId, status:'PENDING_PAYMENT', totalAmount, paymentDeadlineAt, orders:[{orderId, orderNo, sellerId, totalAmount, status}]} Replay cùng key → trả lại đúng response đã lưu. | J11: - Idempotency-Key UUID; cùng key + request_hash khác → 422 - expectedGrandTotal == tổng tính lại (lệch → 409 PRICE_CHANGED + giá mới) - Cart ACTIVE của buyer; chưa có checkout PENDING_PAYMENT cho cart (partial unique index) - Item hợp lệ (CART-06), địa chỉ + phone hợp lệ - Buyer không bị khoá / reputation đủ (FEATURE_REPUTATION_ENFORCEMENT) - Voucher: ACTIVE, trong thời gian, đủ min_order_amount, còn lượt | K11: 400 VALIDATION_ERROR, 409 PRICE_CHANGED, 409 CART_INVALID, 409 CHECKOUT_ALREADY_OPEN, 409 INSUFFICIENT_STOCK, 409 VOUCHER_INVALID, 403 REPUTATION_RESTRICTED, 409 IDEMPOTENCY_KEY_CONFLICT, 409 REQUEST_IN_PROGRESS, 503 FULFILLMENT_UNAVAILABLE | L11: ADJUSTED
A12: CHK-03 | B12: Public API | C12: POST | D12: /api/v1/checkout-groups/{checkoutGroupId}/pay | E12: Pay checkout group / Thanh toán nhóm đơn | F12: CHECKOUT.PAY (NEW) / Buyer | G12: Required | H12: Header: Idempotency-Key Body: {paymentMethod: WALLET|VNPAY, returnUrl?} | I12: WALLET: 202 {status:'PAYMENT_PROCESSING'} — KHÔNG trả PAID đồng bộ; PAID chỉ do PAY-01 set (FE poll CHK-04) VNPAY: 202 {status:'PAYMENT_PROCESSING', paymentUrl, expiresAt} | J12: - Group thuộc buyer - status = PENDING_PAYMENT và now < payment_deadline_at - saga_state = AWAITING_PAYMENT (đã giữ tồn kho) - returnUrl thuộc whitelist domain - Chưa vượt PAYMENT_RETRY_LIMIT (3) — đếm bằng saga_state.state_data.paymentAttempts (hoặc cột checkout_groups.payment_attempt_count) | K12: 404 CHECKOUT_GROUP_NOT_FOUND, 409 CHECKOUT_NOT_PAYABLE, 410 DEADLINE_EXPIRED, 402 INSUFFICIENT_WALLET_BALANCE, 409 PAYMENT_ATTEMPT_LIMIT_REACHED, 502 PAYMENT_GATEWAY_ERROR, 202 PAYMENT_PROCESSING | L12: ADJUSTED
A13: CHK-04 | B13: Public API | C13: GET | D13: /api/v1/checkout-groups/{checkoutGroupId} | E13: Get checkout group / Xem trạng thái checkout | F13: ORDER.VIEW / Buyer (own) | G13: - | H13: Path: checkoutGroupId | I13: 200 {id, status, totalAmount, paymentMethod, paymentDeadlineAt, walletTransactionId, orders:[{orderId, orderNo, status, totalAmount}]} | J13: - Group thuộc buyer (không thì 404) | K13: 404 CHECKOUT_GROUP_NOT_FOUND | L13: UNCHANGED
A14: CHK-05 | B14: Public API | C14: POST | D14: /api/v1/checkout-groups/{checkoutGroupId}/cancel | E14: Cancel checkout group / Huỷ checkout chưa thanh toán | F14: ORDER.CANCEL / Buyer | G14: - | H14: Body: {reasonCode, reasonNote?} | I14: 200 {status:'CANCELLED'} | J14: - status = PENDING_PAYMENT (không phải PAYMENT_PROCESSING) - reasonCode hợp lệ | K14: 409 CHECKOUT_NOT_CANCELLABLE, 409 PAYMENT_IN_PROGRESS | L14: UNCHANGED
A15: DSC-01 | B15: Public API | C15: GET | D15: /api/v1/vouchers/available?cartItemIds=&sellerId=&page=&size= | E15: List available vouchers / Danh sách voucher khả dụng | F15: CART.VIEW / Buyer | G15: - | H15: Query như trên | I15: 200 {items:[{code, name, scopeType, discountType, discountValue, maxDiscountAmount, minOrderAmount, endsAt, eligible, ineligibleReason, remainingUses}], paging} | J15: - size ≤ 50 - Lọc: status=ACTIVE, starts_at ≤ now ≤ ends_at, deleted_at IS NULL, is_visible=true, used_count+reserved_count < max_uses_total, số lần buyer đã dùng (RESERVED+USED) < max_uses_per_user | K15: 404 SELLER_NOT_FOUND | L15: UNCHANGED
A16: DSC-05 | B16: Public API | C16: POST | D16: /api/v1/vouchers | E16: Create voucher / Tạo voucher | F16: DISCOUNT.CREATE (NEW) / Admin, Seller | G16: - | H16: TBD - design in sprint planning (NEW function) | I16: TBD - design in sprint planning (NEW function) | J16: TBD - design in sprint planning (NEW function) | K16: 400 VALIDATION_ERROR, 409 VOUCHER_CODE_EXISTS, 403 FORBIDDEN | L16: NEW
A17: DSC-06 | B17: Public API | C17: PATCH | D17: /api/v1/vouchers/{voucherId} | E17: Update / activate / delete voucher / Sửa, bật tắt, xoá voucher | F17: DISCOUNT.UPDATE (NEW) / Admin, Seller (own) | G17: - | H17: TBD - design in sprint planning (NEW function) | I17: TBD - design in sprint planning (NEW function) | J17: TBD - design in sprint planning (NEW function) | K17: 400 VALIDATION_ERROR, 404 VOUCHER_NOT_FOUND, 409 VOUCHER_ALREADY_USED, 403 FORBIDDEN | L17: NEW
A18: DSC-07 | B18: Public API | C18: GET | D18: /api/v1/vouchers | E18: List vouchers for management / Quản lý danh sách voucher | F18: DISCOUNT.VIEW (NEW) / Admin, Seller (own) | G18: - | H18: TBD - design in sprint planning (NEW function) | I18: TBD - design in sprint planning (NEW function) | J18: TBD - design in sprint planning (NEW function) | K18: 403 FORBIDDEN | L18: NEW
A19: ORD-01 | B19: Public API | C19: GET | D19: /api/v1/orders | E19: List my orders / Lịch sử đơn hàng của tôi | F19: ORDER.LIST / Buyer (own) | G19: - | H19: Query: status, orderType=ALL|REGULAR|AUCTION, fromDate, toDate, keyword (orderNo), page=0, size=20, sort=createdAt,desc | I19: 200 {items:[{orderId, orderNo, orderType, sellerId, sellerName, status, totalAmount, itemCount, firstItem:{name, imageUrl}, createdAt, paymentDeadlineAt}], page, size, totalItems, totalPages} Rỗng → items:[] (FE hiện 'No Data') | J19: - size ≤ 100; status thuộc enum; fromDate ≤ toDate, khoảng ≤ 1 năm - sort whitelist (createdAt, totalAmount) | K19: 400 VALIDATION_ERROR | L19: UNCHANGED
A20: ORD-02 | B20: Public API | C20: GET | D20: /api/v1/orders/{orderId}?orderType=REGULAR|AUCTION | E20: Get order detail / Chi tiết & theo dõi đơn hàng | F20: ORDER.VIEW / Buyer (own), Seller (own), Admin, Support | G20: - | H20: Path: orderId; Query: orderType (default REGULAR) | I20: 200 {orderId, orderNo, orderType, status, paymentMethod, shippingAddress, contactPhone, amounts:{itemsAmount, productDiscountAmount, shopDiscountAmount, platformMarkupAmount, systemDiscountAmount, shippingFeeAmount, totalAmount}, items[{productName, skuCode, skuAttributes, imageUrl, quantity, unitPrice, unitPriceAfterDiscount, lineTotal}], statusHistory[{fromStatus, toStatus, actorRole, reason, createdAt}], shipment?{carrier, trackingNo, status, events[]}, invoice?{invoiceNo, status}, cancellation?{reasonCode, wasPaid}, timestamps{…}, allowedActions:['CANCEL','CONFIRM_RECEIVED',…} AUCTION thêm: auctionId, winningBidId, winningAmount. | J20: - Buyer: buyer_id = sub. Seller: seller_id = sub. Admin/Support: tất cả - Không đủ quyền → 404 (không lộ tồn tại) - Seller chỉ xem order có paid_at IS NOT NULL (không thấy PENDING_PAYMENT hoặc đơn huỷ trước khi trả tiền) → còn lại 404 | K20: 404 ORDER_NOT_FOUND | L20: UNCHANGED
... A32: AO-03 | B32: Public API | C32: POST | D32: /api/v1/auction-orders/{auctionOrderId}/pay | E32: Pay auction order / Thanh toán đơn đấu giá | F32: CHECKOUT.PAY (NEW) / Buyer (winner) | G32: Required | H32: Header: Idempotency-Key Body: {paymentMethod: WALLET|VNPAY, returnUrl?} | I32: Như CHK-03 | J32: - buyer_id = sub; status = PENDING_PAYMENT; now < payment_deadline_at - shipping_fee_amount và total_amount KHÔNG NULL (đã làm AO-02) → thiếu 409 SHIPPING_INFO_REQUIRED | K32: 409 SHIPPING_INFO_REQUIRED, 409 ORDER_STATE_CONFLICT, 410 DEADLINE_EXPIRED, 402 INSUFFICIENT_WALLET_BALANCE | L32: ADJUSTED

Sheet DB_Trace
A1: Table | B1: Purpose | C1: Written by (function IDs) | D1: Read by (function IDs) | E1: # writers | F1: # readers | G1: Check
A2: carts | B2: Buyer cart header, 1 ACTIVE per buyer, row_version | C2: CART-02, CART-03, CART-04, CART-05, CART-09, CART-10, CART-11, PAY-01 | D2: CART-01, CART-06, CART-08, CHK-01, CHK-02 | E2: =SUMPRODUCT(--ISNUMBER(SEARCH(", "&A2&",",", "&Backlog!$N$2:$N$58&","))) -> 8 | F2: =SUMPRODUCT(--ISNUMBER(SEARCH(", "&A2&",",", "&Backlog!$O$2:$O$58&","))) -> 5 | G2: =IF(E2+F2=0,"UNUSED",IF(E2=0,"READ-ONLY (seed / Admin-Config)","OK")) -> OK
A3: cart_items | B3: Cart lines, UNIQUE(cart_id, sku_id), price snapshot | C3: CART-02, CART-03, CART-04, CART-05, CART-10, CART-11, PAY-01 | D3: CART-01, CART-06, CHK-01, CHK-02 | E3: =SUMPRODUCT(--ISNUMBER(SEARCH(", "&A3&",",", "&Backlog!$N$2:$N$58&","))) -> 7 | F3: =SUMPRODUCT(--ISNUMBER(SEARCH(", "&A3&",",", "&Backlog!$O$2:$O$58&","))) -> 4 | G3: =IF(E3+F3=0,"UNUSED",IF(E3=0,"READ-ONLY (seed / Admin-Config)","OK")) -> OK
A4: checkout_groups | B4: 1 checkout = N orders, deadline, payment attempts | C4: CHK-02, CHK-03, CHK-05, CHK-06, PAY-01, ORD-21, ORD-22 | D4: CART-02, CART-03, CART-04, CART-05, CART-09, CHK-03, CHK-04, CHK-06, ORD-06, ORD-21, ORD-22 | E4: =SUMPRODUCT(--ISNUMBER(SEARCH(", "&A4&",",", "&Backlog!$N$2:$N$58&","))) -> 7 | F4: =SUMPRODUCT(--ISNUMBER(SEARCH(", "&A4&",",", "&Backlog!$O$2:$O$58&","))) -> 11 | G4: =IF(E4+F4=0,"UNUSED",IF(E4=0,"READ-ONLY (seed / Admin-Config)","OK")) -> OK
A5: orders | B5: Normal order per seller, snapshots, amounts, status | C5: CHK-02, CHK-03, CHK-05, CHK-06, PAY-01, ORD-04, ORD-05, ORD-06, ORD-07, ORD-08, ORD-09, ORD-10, ORD-12, ORD-14, ORD-18, ORD-21, ORD-22 | D5: CHK-03, CHK-04, PAY-01, ORD-01, ORD-02, ORD-03, ORD-04, ORD-05, ORD-07, ORD-08, ORD-09, ORD-10, ORD-11, ORD-12, ORD-13, ORD-15, ORD-16, ORD-18, ORD-21, ORD-23 | E5: =SUMPRODUCT(--ISNUMBER(SEARCH(", "&A5&",",", "&Backlog!$N$2:$N$58&","))) -> 17 | F5: =SUMPRODUCT(--ISNUMBER(SEARCH(", "&A5&",",", "&Backlog!$O$2:$O$58&","))) -> 20 | G5: =IF(E5+F5=0,"UNUSED",IF(E5=0,"READ-ONLY (seed / Admin-Config)","OK")) -> OK
A6: order_items | B6: Order lines (snapshot) | C6: CHK-02 | D6: PAY-01, ORD-01, ORD-02, ORD-23 | E6: =SUMPRODUCT(--ISNUMBER(SEARCH(", "&A6&",",", "&Backlog!$N$2:$N$58&","))) -> 1 | F6: =SUMPRODUCT(--ISNUMBER(SEARCH(", "&A6&",",", "&Backlog!$O$2:$O$58&","))) -> 4 | G6: =IF(E6+F6=0,"UNUSED",IF(E6=0,"READ-ONLY (seed / Admin-Config)","OK")) -> OK
A7: order_status_history | B7: Status audit, order_id XOR auction_order_id | C7: CHK-02, CHK-05, CHK-06, PAY-01, ORD-04, ORD-05, ORD-06, ORD-07, ORD-08, ORD-09, ORD-10, ORD-12, ORD-13, ORD-14, ORD-18, ORD-22, AO-01, AO-04 | D7: ORD-02 | E7: =SUMPRODUCT(--ISNUMBER(SEARCH(", "&A7&",",", "&Backlog!$N$2:$N$58&","))) -> 18 | F7: =SUMPRODUCT(--ISNUMBER(SEARCH(", "&A7&",",", "&Backlog!$O$2:$O$58&","))) -> 1 | G7: =IF(E7+F7=0,"UNUSED",IF(E7=0,"READ-ONLY (seed / Admin-Config)","OK")) -> OK
A8: order_cancellations | B8: Cancellation facts (reason, actor, was_paid) | C8: CHK-05, CHK-06, ORD-05, ORD-06, ORD-09, ORD-10, ORD-22, AO-04 | D8: ORD-02, ORD-13 | E8: =SUMPRODUCT(--ISNUMBER(SEARCH(", "&A8&",",", "&Backlog!$N$2:$N$58&","))) -> 8 | F8: =SUMPRODUCT(--ISNUMBER(SEARCH(", "&A8&",",", "&Backlog!$O$2:$O$58&","))) -> 2 | G8: =IF(E8+F8=0,"UNUSED",IF(E8=0,"READ-ONLY (seed / Admin-Config)","OK")) -> OK
A9: order_refunds | B9: Refund lifecycle (REQUESTED/COMPLETED/FAILED) | C9: PAY-01, ORD-05, ORD-06, ORD-09, ORD-10, ORD-13, ORD-14 | D9: ORD-02, ORD-14, ORD-25 | E9: =SUMPRODUCT(--ISNUMBER(SEARCH(", "&A9&",",", "&Backlog!$N$2:$N$58&","))) -> 7 | F9: =SUMPRODUCT(--ISNUMBER(SEARCH(", "&A9&",",", "&Backlog!$O$2:$O$58&","))) -> 3 | G9: =IF(E9+F9=0,"UNUSED",IF(E9=0,"READ-ONLY (seed / Admin-Config)","OK")) -> OK
A10: order_invoices | B10: Invoice per order | C10: ORD-15 | D10: ORD-02, ORD-16 | E10: =SUMPRODUCT(--ISNUMBER(SEARCH(", "&A10&",",", "&Backlog!$N$2:$N$58&","))) -> 1 | F10: =SUMPRODUCT(--ISNUMBER(SEARCH(", "&A10&",",", "&Backlog!$O$2:$O$58&","))) -> 2 | G10: =IF(E10+F10=0,"UNUSED",IF(E10=0,"READ-ONLY (seed / Admin-Config)","OK")) -> OK
A11: auction_orders | B11: Auction order, 1 auction = 1 order | C11: PAY-01, ORD-04, ORD-05, ORD-06, ORD-07, ORD-08, ORD-09, ORD-10, ORD-12, ORD-14, ORD-18, AO-01, AO-02, AO-03, AO-04 | D11: PAY-01, ORD-01, ORD-02, ORD-03, ORD-04, ORD-05, ORD-07, ORD-08, ORD-09, ORD-10, ORD-11, ORD-12, ORD-13, ORD-15, ORD-16, ORD-18, ORD-23, AO-02, AO-03, AO-04, AO-05 | E11: =SUMPRODUCT(--ISNUMBER(SEARCH(", "&A11&",",", "&Backlog!$N$2:$N$58&","))) -> 15 | F11: =SUMPRODUCT(--ISNUMBER(SEARCH(", "&A11&",",", "&Backlog!$O$2:$O$58&","))) -> 21 | G11: =IF(E11+F11=0,"UNUSED",IF(E11=0,"READ-ONLY (seed / Admin-Config)","OK")) -> OK
A12: discount_codes | B12: Vouchers + counters | C12: CHK-02, CHK-05, CHK-06, PAY-01, DSC-03, DSC-04, DSC-05, DSC-06, DSC-08, ORD-05, ORD-06, ORD-09, ORD-22 | D12: CHK-01, DSC-01, DSC-02, DSC-05, DSC-06, DSC-07, DSC-08 | E12: =SUMPRODUCT(--ISNUMBER(SEARCH(", "&A12&",",", "&Backlog!$N$2:$N$58&","))) -> 13 | F12: =SUMPRODUCT(--ISNUMBER(SEARCH(", "&A12&",",", "&Backlog!$O$2:$O$58&","))) -> 7 | G12: =IF(E12+F12=0,"UNUSED",IF(E12=0,"READ-ONLY (seed / Admin-Config)","OK")) -> OK
A13: discount_code_scopes | B13: Voucher scope | C13: DSC-05, DSC-06 | D13: CHK-01, DSC-01, DSC-02, DSC-07 | E13: =SUMPRODUCT(--ISNUMBER(SEARCH(", "&A13&",",", "&Backlog!$N$2:$N$58&","))) -> 2 | F13: =SUMPRODUCT(--ISNUMBER(SEARCH(", "&A13&",",", "&Backlog!$O$2:$O$58&","))) -> 4 | G13: =IF(E13+F13=0,"UNUSED",IF(E13=0,"READ-ONLY (seed / Admin-Config)","OK")) -> OK
... A18: inbox_messages | B18: Consumer dedupe | C18: CART-11, PAY-01, ORD-10, ORD-14, ORD-22, ORD-24, AO-01, AO-05 | D18: ORD-24 | E18: =SUMPRODUCT(--ISNUMBER(SEARCH(", "&A18&",",", "&Backlog!$N$2:$N$58&","))) -> 8 | F18: =SUMPRODUCT(--ISNUMBER(SEARCH(", "&A18&",",", "&Backlog!$O$2:$O$58&","))) -> 1 | G18: =IF(E18+F18=0,"UNUSED",IF(E18=0,"READ-ONLY (seed / Admin-Config)","OK")) -> OK
A19: daily_order_sequences | B19: Daily document numbers | C19: CHK-02, ORD-15, ORD-17, AO-01 | E19: =SUMPRODUCT(--ISNUMBER(SEARCH(", "&A19&",",", "&Backlog!$N$2:$N$58&","))) -> 4 | F19: =SUMPRODUCT(--ISNUMBER(SEARCH(", "&A19&",",", "&Backlog!$O$2:$O$58&","))) -> 0 | G19: =IF(E19+F19=0,"UNUSED",IF(E19=0,"READ-ONLY (seed / Admin-Config)","OK")) -> OK
A20: system_settings | B20: Typed config | D20: CART-02, CART-07, CART-09, CART-10, CHK-01, CHK-02, ORD-08, ORD-26, AO-01 | E20: =SUMPRODUCT(--ISNUMBER(SEARCH(", "&A20&",",", "&Backlog!$N$2:$N$58&","))) -> 0 | F20: =SUMPRODUCT(--ISNUMBER(SEARCH(", "&A20&",",", "&Backlog!$O$2:$O$58&","))) -> 9 | G20: =IF(E20+F20=0,"UNUSED",IF(E20=0,"READ-ONLY (seed / Admin-Config)","OK")) -> READ-ONLY (seed / Admin-Config)

Sheet Event_Catalog
A1: Event | B1: Producer | C1: Consumers | D1: Published by (Commerce function) | E1: Consumed by (Commerce function) | F1: Status | G1: Note
A2: CartCreated | B2: Commerce | C2: Notification, Event Log | D2: CART-02 | F2: In SRS 5.2
A3: CartItemAdded | B3: Commerce | C3: Notification, Event Log | D3: CART-02, CART-10 | F3: In SRS 5.2
A4: CartItemUpdated | B4: Commerce | C4: Notification, Event Log | D4: CART-03 | F4: In SRS 5.2
A5: CartItemRemoved | B5: Commerce | C5: Notification, Event Log | D5: CART-04, CART-05 | F5: In SRS 5.2
A6: CartExpired | B6: Commerce | C6: Notification, Event Log | D6: CART-09 | F6: In SRS 5.2
A7: CheckoutStarted | B7: Commerce | C7: Event Log | D7: CHK-02 | F7: In SRS 5.2
A8: CheckoutCompleted | B8: Commerce | C8: Notification | D8: PAY-01 | F8: Not in SRS (proposed) | G8: Needs SRS 5.2 review
A9: CheckoutExpired | B9: Commerce | C9: Fulfillment, Notification | D9: CHK-06, ORD-21 | F9: Not in SRS (proposed) | G9: Needs SRS 5.2 review
A10: CheckoutCancelled | B10: Commerce | C10: Notification | D10: CHK-05 | F10: Not in SRS (proposed) | G10: Needs SRS 5.2 review
A11: OrderCreated | B11: Commerce | C11: Notification, Event Log, Auction (orderType=AUCTION) | D11: CHK-02, AO-01 | F11: Agreed (Auction) | G11: Auction learns orderId this way; no AuctionOrderCreated event
A12: OrderCheckoutRequested | B12: Commerce | C12: Wallet (WAL-05A) | D12: CHK-03, AO-03 | F12: Wallet contract | G12: WALLET path; spec uses temporary Payment request
A13: OrderPaid | B13: Commerce | C13: Fulfillment, Notification, Auction (AUCTION only) | D13: PAY-01, ORD-21 | F13: Agreed (Auction) | G13: Payload per spec 2.3
A14: OrderPaymentFailed | B14: Commerce | C14: Notification; Auction optional | D14: PAY-01 | F14: Agreed (Auction) | G14: Auction does not need it
A15: OrderCancelled | B15: Commerce | C15: Fulfillment, Notification, Auction (AUCTION), User | D15: CHK-05, CHK-06, ORD-05, ORD-06, ORD-09, ORD-21, ORD-22, AO-04 | F15: Agreed (Auction) | G15: reasonCode frozen to 5 values
A16: OrderConfirmed | B16: Commerce | C16: Fulfillment-Shipping, Notification | D16: ORD-04 | F16: PROPOSED (spec 2.4.5) | G16: Renamed from OrderSellerAccepted; Fulfillment FUL-13 must switch (G13)
A17: OrderShipped | B17: Commerce | C17: Notification | D17: ORD-10 | F17: Not in SRS (proposed)
A18: OrderDelivered | B18: Commerce | C18: Notification | D18: ORD-10, ORD-12 | F18: Not in SRS (proposed)
A19: OrderCompleted | B19: Commerce | C19: Notification, User (rating) | D19: ORD-07, ORD-08, ORD-12 | E19: ORD-15 | F19: In SRS 5.2 | G19: Seller payout is OPEN (OQ-24)
A20: OrderRefundRequested | B20: Commerce | C20: Payment / Wallet WAL-06 | D20: PAY-01, ORD-05, ORD-06, ORD-09, ORD-13 | F20: In SRS 5.2
A21: OrderRefundCompleted | B21: Commerce | C21: Notification | D21: ORD-14 | F21: In SRS 5.2
A22: InvoiceGenerated | B22: Commerce | C22: Notification | D22: ORD-15 | F22: Not in SRS (proposed) | G22: COM-INV-002 has no event name
A23: AuctionSettled | B23: Auction | C23: Commerce AO-01 | E23: AO-01 | F23: Agreed (Auction) | G23: Emitted when the winner is determined, before payment; paymentDeadlineAt + skuId required
A24: AuctionWon | B24: Auction | C24: Notification only | F24: Agreed (Auction) | G24: Commerce ignores it
A25: AuctionCancelled | B25: Auction | C25: Commerce AO-05 | E25: AO-05 | F25: Agreed (Auction) | G25: Existing order: log + alert Support only
A26: AuctionPaymentTimedOut | B26: Auction | C26: User / others | F26: Auction-owned | G26: Emitted by Auction after OrderCancelled(PAYMENT_TIMEOUT); NOT used to deduct reputation (spec 2.6)
A27: PaymentSucceeded / PaymentFailed / PaymentExpired | B27: Payment | C27: Commerce PAY-01 | D27: PAY-01 | E27: PAY-01 | F27: Temporary names (OQ-17) | G27: Behind an adapter; Wallet WalletDebitedSuccess / WalletDebitFailed are the candidates
A28: WalletDebitedSuccess | B28: Wallet | C28: Commerce PAY-01 | E28: PAY-01 | F28: Wallet contract
A29: WalletDebitFailed | B29: Wallet | C29: Commerce PAY-01 | E29: PAY-01 | F29: Wallet contract
A30: RefundCompleted / RefundFailed | B30: Payment | C30: Commerce ORD-14 | D30: ORD-14 | E30: ORD-14 | F30: Temporary names (OQ-17) | G30: WalletRefunded is the Wallet candidate; no failure event yet (G05)
A31: WalletRefunded | B31: Wallet | C31: Commerce ORD-14 | E31: ORD-14 | F31: Wallet contract
A32: ShipmentPickedUp / ShipmentInTransit / ShipmentReturned | B32: Fulfillment | C32: Commerce ORD-10 | E32: ORD-10 | F32: Not emitted yet | G32: FUL-17 emits only Delivered / DeliveryFailed (G07)
A33: ShipmentDelivered | B33: Fulfillment | C33: Commerce ORD-10 | E33: ORD-10 | F33: In SRS 5.3
A34: ShipmentFailed | B34: Fulfillment | C34: Commerce ORD-10 | E34: ORD-10 | F34: In SRS 5.3 | G34: Log + alert only
A35: InventoryReserved | B35: Fulfillment | C35: Commerce CHK-02 | E35: CHK-02 | F35: In SRS 5.3 | G35: Sync vs event is OQ-07
A36: InventoryReservationFailed | B36: Fulfillment | C36: Commerce CHK-02 | F36: PROPOSED (spec) | G36: Compensation trigger
A37: InventoryReleased | B37: Fulfillment | C37: Commerce ORD-22 | E37: ORD-22 | F37: In SRS 5.3
A38: InventoryReservationExpired | B38: Fulfillment | C38: Commerce ORD-22 | E38: ORD-22 | F38: In SRS 5.3 | G38: Safety net only
A39: ProductDeleted / ProductStatusChanged | B39: Catalog | C39: Commerce CART-11 | E39: CART-11 | F39: In SRS 5.3
A40: UserDeleted | B40: User | C40: Commerce CART-11 | E40: CART-11 | F40: Functions.xlsx
A41: SystemConfigUpdated | B41: Admin/Config | C41: Commerce ORD-26 | E41: ORD-26 | F41: SRS 2.8

Sheet Integration_Map
A1: Service | B1: Commerce functions | C1: Contract | D1: Status
A2: Catalog | B2: CART-01; CART-02; CART-03; CART-06; CHK-01; CHK-02; CART-10; AO-01 | C2: Sync REST CAT-39 (purchasable check + price) and CAT-24 (display data); NOT skus:batch-get | D2: Adjust (G09)
A3: Catalog | B3: CART-11 | C3: Events ProductDeleted / ProductStatusChanged | D3: Agreed
A4: Catalog | B4: ORD-23 | C4: Catalog (CAT-26/27) calls Commerce rating-eligibility | D4: NEW (Commerce owns)
A5: Fulfillment - Inventory | B5: CART-01; CART-02; CART-03; CART-06 | C5: FUL-04 availability batch (soft check, cache 30s) | D5: Agreed
A6: Fulfillment - Inventory | B6: CHK-02 | C6: Reserve stock for the whole group before TX-2; FUL-06 is event-per-order | D6: Mismatch (G06)
A7: Fulfillment - Inventory | B7: CHK-05; CHK-06; ORD-05; ORD-06; ORD-09; AO-05 | C7: Release via OrderCancelled (FUL-10) | D7: Agreed
A8: Fulfillment - Inventory | B8: ORD-22 | C8: InventoryReleased (FUL-11) | D8: Agreed
A9: Fulfillment - Shipping | B9: CHK-01; CHK-02; AO-02 | C9: Quote FUL-12 (timeout 3s); fee frozen into order | D9: Agreed
A10: Fulfillment - Shipping | B10: ORD-04; PAY-01 | C10: OrderConfirmed (FUL-13, name to switch) / OrderPaid (FUL-09) trigger shipments | D10: Agreed
A11: Fulfillment - Shipping | B11: ORD-02 | C11: FUL-18/19/20 shipment tracking (degrade to null) | D11: Agreed
A12: Fulfillment - Shipping | B12: ORD-10 | C12: Shipment events | D12: Partially emitted (G07)
... A31: User | B31: ORD-05; ORD-09; AO-04 | C31: Penalty owner is User/Auction (OQ-03); Commerce does not deduct reputation | D31: Open (G04)

Sheet Test_Cases
A1: TC ID | B1: Function ID | C1: Module | D1: COM requirement(s) | E1: Type | F1: Priority | G1: Level | H1: Title | I1: Precondition | J1: Steps | K1: Expected result | L1: Status
A2: TC-CART-01-01 | B2: CART-01 | C2: Cart | D2: COM-CART-001; COM-CART-005 | E2: Functional | F2: P0 | G2: Integration | H2: Happy path: Get my cart | I2: Valid actor, valid data, dependencies up | J2: Call GET /api/v1/carts/me with a valid request | K2: Success status; response matches contract; DB rows and outbox events as listed in Backlog | L2: Not run
A3: TC-CART-01-02 | B3: CART-01 | C3: Cart | D3: COM-CART-001; COM-CART-005 | E3: Security | F3: P0 | G3: Integration | H3: Authn/Authz: missing token -> 401, wrong role or foreign resource -> 403/404 | I3: Permission required: CART.VIEW / Buyer | J3: Call GET /api/v1/carts/me without JWT, then with a user of another role/owner | K3: 401 without token; 403 (or 404 to hide existence) for non-owner; no data leak | L3: Not run
A4: TC-CART-01-03 | B4: CART-01 | C4: Cart | D4: COM-CART-001; COM-CART-005 | E4: Business rule | F4: P0 | G4: Unit | H4: Rule: Virtual empty cart when none | I4: Data at the rule boundary | J4: Execute with value just inside and just outside the limit | K4: Inside accepted, outside rejected with documented code | L4: Not run
A5: TC-CART-01-04 | B5: CART-01 | C5: Cart | D5: COM-CART-001; COM-CART-005 | E5: Contract | F5: P0 | G5: Contract | H5: Contract with: Catalog CAT-39 / CAT-24 (sync, degrade); Fulfillment FUL-04 (sync, optional, cache ~30s) | I5: Provider stub (Pact/WireMock) | J5: Verify request/response or event schema; simulate provider timeout | K5: Schema matches; timeout follows documented degrade/error (see Integration_Map) | L5: Not run
A6: TC-CART-02-01 | B6: CART-02 | C6: Cart | D6: COM-CART-001; COM-CART-002 | E6: Functional | F6: P0 | G6: Integration | H6: Happy path: Add item to cart | I6: Valid actor, valid data, dependencies up | J6: Call POST /api/v1/carts/me/items with a valid request | K6: Success status; response matches contract; DB rows and outbox events as listed in Backlog | L6: Not run
A7: TC-CART-02-02 | B7: CART-02 | C7: Cart | D7: COM-CART-001; COM-CART-002 | E7: Negative | F7: P0 | G7: Integration | H7: VALIDATION_ERROR -> HTTP 400 | I7: State/input that triggers VALIDATION_ERROR | J7: Call POST /api/v1/carts/me/items | K7: HTTP 400 VALIDATION_ERROR; transaction rolled back; no event written to outbox | L7: Not run
A8: TC-CART-02-03 | B8: CART-02 | C8: Cart | D8: COM-CART-001; COM-CART-002 | E8: Negative | F8: P0 | G8: Integration | H8: PRODUCT_NOT_FOUND -> HTTP 404 | I8: State/input that triggers PRODUCT_NOT_FOUND | J8: Call POST /api/v1/carts/me/items | K8: HTTP 404 PRODUCT_NOT_FOUND; transaction rolled back; no event written to outbox | L8: Not run
A9: TC-CART-02-04 | B9: CART-02 | C9: Cart | D9: COM-CART-001; COM-CART-002 | E9: Negative | F9: P0 | G9: Integration | H9: PRODUCT_NOT_AVAILABLE -> HTTP 409 | I9: State/input that triggers PRODUCT_NOT_AVAILABLE | J9: Call POST /api/v1/carts/me/items | K9: HTTP 409 PRODUCT_NOT_AVAILABLE; transaction rolled back; no event written to outbox | L9: Not run
A10: TC-CART-02-05 | B10: CART-02 | C10: Cart | D10: COM-CART-001; COM-CART-002 | E10: Negative | F10: P0 | G10: Integration | H10: INSUFFICIENT_STOCK -> HTTP 409 | I10: State/input that triggers INSUFFICIENT_STOCK | J10: Call POST /api/v1/carts/me/items | K10: HTTP 409 INSUFFICIENT_STOCK; transaction rolled back; no event written to outbox | L10: Not run
A11: TC-CART-02-06 | B11: CART-02 | C11: Cart | D11: COM-CART-001; COM-CART-002 | E11: Negative | F11: P0 | G11: Integration | H11: CART_ITEM_LIMIT_EXCEEDED -> HTTP 409 | I11: State/input that triggers CART_ITEM_LIMIT_EXCEEDED | J11: Call POST /api/v1/carts/me/items | K11: HTTP 409 CART_ITEM_LIMIT_EXCEEDED; transaction rolled back; no event written to outbox | L11: Not run
A12: TC-CART-02-07 | B12: CART-02 | C12: Cart | D12: COM-CART-001; COM-CART-002 | E12: Negative | F12: P0 | G12: Integration | H12: CANNOT_BUY_OWN_PRODUCT -> HTTP 409 | I12: State/input that triggers CANNOT_BUY_OWN_PRODUCT | J12: Call POST /api/v1/carts/me/items | K12: HTTP 409 CANNOT_BUY_OWN_PRODUCT; transaction rolled back; no event written to outbox | L12: Not run
... A312: TC-E2E-15 | B312: AO-05 | C312: E2E | D312: COM-AUC-009 | E312: E2E | F312: P0 | G312: E2E | H312: E2E AuctionCancelled for existing order | I312: Clean environment, stubs/real services per scenario. Functions: AO-05 | J312: Deliver AuctionCancelled for a session that already has an order | K312: Order untouched; log + alert Support | L312: Not run

Sheet Gaps_Decisions
A1: ID | B1: Type | C1: Issue | D1: Proposal / options | E1: Owner | F1: Status | G1: Affected functions
A2: G01 | B2: Decision | C2: Decision resolved with Auction 2026-10-27: Commerce enforces the 24h deadline by job (AO-04) and emits OrderCancelled(PAYMENT_TIMEOUT). Auction computes paymentDeadlineAt = determinedAt + 24h and owns AUCTION_PAYMENT_DEADLINE_HOURS. Matches SRS OQ-01 recommendation. | D2: Closed - no action; SRS section 4.5/5.7/7 must be updated (see SRS_Sync). | E2: Backlog Lead + Auction lead | F2: Resolved | G2: AO-02; AO-03; AO-04; AO-05
A3: G02 | B3: Contract | C3: Auction event that creates the order is AuctionSettled (emitted before payment); AuctionWon is ignored. Earlier plan AuctionOrderRequested is dropped. | D3: Closed. Confirm OQ-22 (SETTLED state name) and OQ-23 (same eventId on retry) with Auction. | E3: Commerce | F3: Resolved | G3: AO-01
A4: G03 | B4: Contract | C4: Order id goes back to Auction through OrderCreated with orderType=AUCTION. AuctionOrderCreated is not used. | D4: Closed. | E4: Commerce + Auction | F4: Resolved | G4: AO-01; CHK-02
A5: G04 | B5: Decision | C5: OQ-03: who deducts reputation on PAYMENT_TIMEOUT. Spec proposes User listens to OrderCancelled(PAYMENT_TIMEOUT) filtered by AUCTION and owns PAYMENT_TIMEOUT_PENALTY_SCORE; AuctionPaymentTimedOut is not used for penalties. Needs User to confirm. | D5: Confirm with User; one owner only to avoid double penalty. | E5: Auction + User | F5: Open | G5: AO-04; AO-05; ORD-05
A6: G05 | B6: Contract | C6: Payment was split into Wallet. Functions.xlsx assumes POST /internal/v1/payments, GET payments?referenceId, PaymentSucceeded/Failed/Expired, RefundCompleted/Failed. | D6: Adopt WAL-05A/B, WalletDebitedSuccess/Failed, WalletRefunded. Still needed from Wallet: payment-status lookup, refund-failed event, VNPAY success event. | E6: Wallet | F6: Open | G6: CHK-03; CHK-05; CHK-06; PAY-01; ORD-13; ORD-14; ORD-21; AO-03
A7: G06 | B7: Contract | C7: Commerce expects all-or-nothing reserve for a whole group; Fulfillment FUL-06 reserves from an event per order. | D7: Either Commerce emits one OrderCreated per order and treats reservation as async saga step, or Fulfillment adds a group-level API. Recommend async per order + saga compensation. | E7: Fulfillment | F7: Open | G7: CHK-02; ORD-22
A8: G07 | B8: Contract | C8: FUL-17 emits only ShipmentDelivered / DeliveryFailed. PickedUp, InTransit, Returned not emitted. | D8: Fulfillment to emit them, or Commerce moves to SHIPPING from OrderSellerAccepted + first tracking event. | E8: Fulfillment | F8: Open | G8: ORD-10
A9: G08 | B9: Design | C9: Two entry points to complete an order: Commerce ORD-07 and Fulfillment FUL-23. | D9: Keep ORD-07 as the only mutation; FUL-23 calls it (or emits event only). | E9: Commerce + Fulfillment | F9: Open | G9: ORD-07
A10: G09 | B10: Contract | C10: Functions.xlsx references Catalog POST /internal/v1/skus:batch-get; Catalog sheet defines CAT-39 and CAT-24. | D10: Use CAT-39 for purchasability/price, CAT-24 for display data. | E10: Catalog | F10: Proposed fix | G10: CART-01..CART-06; CHK-01; CHK-02; CART-10
A11: G10 | B11: Naming | C11: Error names follow SRS and Events spec section 5 (CHECKOUT_ALREADY_OPEN, INVALID_TRANSITION, DEADLINE_EXPIRED, IDEMPOTENCY_KEY_CONFLICT 409 ...). Mapping to Functions.xlsx names is in Error_Codes. | D11: Closed in this workbook; update Functions.xlsx / API spec. | E11: Commerce | F11: Resolved | G11: CHK-02
A12: G11 | B12: Contract | C12: User endpoints referenced but not defined: status/trust check at checkout, batch name lookup. | D12: Ask User service to expose them or fall back to cached names. | E12: User | F12: Open | G12: CHK-02; ORD-01; ORD-11
... A37: G31 | B37: Tech | C37: Namespace (com.nexus), dataschema host and where JSON Schemas live are assumed. | D37: Create contracts/ repo folder with JSON Schemas + CI compatibility check. | E37: Architect | F37: Open | G37: ORD-20

Sheet SRS_Sync
A1: # | B1: SRS_Commerce_Service_v1 section | C1: Current SRS text | D1: Proposed change (agreed or from this workbook) | E1: Source | F1: Earlier diff ref
A2: S01 | B2: 4.5 COM-AUC-001, 5.3, 10.1 | C2: Order is created from AuctionWon | D2: Create from AuctionSettled (emitted when the winner is determined, before payment); AuctionWon ignored by Commerce | E2: Events spec 0.2 #1, 2.5 | F2: A1
A3: S02 | B3: 4.5 COM-AUC-005 | C3: paymentDeadlineAt from the event, fallback settledAt + 24h | D3: paymentDeadlineAt and skuId are mandatory; if missing reject (inbox FAILED), no fallback; value used as-is | E3: Events spec 0.2 #2, 2.5.3 | F3: A2, A3
A4: S03 | B4: 7 Config | C4: AUCTION_PAYMENT_DEADLINE_HOURS listed as Commerce config | D4: Owned by Auction; Commerce does not keep it | E4: Events spec 1.2, 2.6 | F4: A4
A5: S04 | B5: 5.2, 5.7 item 1 | C5: Auction listens to OrderPaymentFailed | D5: Auction does not need it (optional consumer) | E5: Events spec 2.4.4, 6.1 #9 | F5: A5
A6: S05 | B6: 5.7 | C6: Header: PROPOSED, not confirmed by Auction | D6: Mark AGREED (Auction 2026-10-27); add AuctionSettled, AuctionWon ignored, OrderCreated(AUCTION) as the way Auction gets orderId | E6: Events spec 2.6, 6.1 | F6: A1
A7: S06 | B7: 5.7 item 2, OQ-01 | C7: Auction emits AuctionPaymentTimeout | D7: Name is AuctionPaymentTimedOut, owned by Auction, not used to deduct reputation | E7: Events spec 2.6 #4 | F7: A6
A8: S07 | B8: 5.3 | C8: AuctionCancelled: no effect | D8: Existing order: log + alert Support, never change state (not expected to happen) | E8: Events spec 2.5, 2.6 #5 | F8: -
A9: S08 | B9: 10 OQ-01, OQ-02 | C9: Open | D9: Close both. OQ-03 remains open with the spec proposal. Add OQ-21 (5 vs 15 min), OQ-22, OQ-23, OQ-24 | E9: Events spec 6.2 | F9: -
A10: S09 | B10: 10.1 | C10: Auction orders created from AuctionWon | D10: Created from AuctionSettled | E10: Events spec 6.1 | F10: A1
A11: S10 | B11: 5.2 | C11: No seller-confirm event | D11: Add OrderConfirmed [PROPOSED] (renamed from OrderSellerAccepted, OQ-20) | E11: Events spec 2.4.5 | F11: A7
A12: S11 | B12: 5.3 | C12: Inventory events | D12: Add InventoryReservationFailed [PROPOSED] as compensation trigger | E12: Events spec 2.5 | F12: A7
... A19: S18 | B19: System SRS 3.5.3.5 | C19: Auction enforces the deadline and applies penalty | D19: Out of Commerce scope but now contradicted: system SRS must say Commerce enforces, Auction computes the deadline | E19: Events spec 2.6 | F19: -

Sheet Error_Codes
A1: HTTP | B1: Error code (SRS / Events spec name) | C1: Used by functions | D1: # functions | E1: Functions.xlsx name (legacy)
A2: 400 | B2: VALIDATION_ERROR | C2: CART-02, CART-03, CART-05, CART-10, CHK-02, DSC-05, DSC-06, ORD-01, ORD-03, ORD-11, ORD-12 | D2: 11
A3: 400 | B3: VAL_IDEMPOTENCY_KEY_REQUIRED | C3: ORD-19 | D3: 1 | E3: IDEMPOTENCY_KEY_REQUIRED
A4: 402 | B4: INSUFFICIENT_WALLET_BALANCE | C4: CHK-03, AO-03 | D4: 2
A5: 403 | B5: FORBIDDEN | C5: DSC-05, DSC-06, DSC-07 | D5: 3
A6: 403 | B6: REPUTATION_RESTRICTED | C6: CHK-02 | D6: 1
A7: 404 | B7: CART_ITEM_NOT_FOUND | C7: CART-03 | D7: 1
A8: 404 | B8: CHECKOUT_GROUP_NOT_FOUND | C8: CHK-03, CHK-04 | D8: 2 | E8: CHECKOUT_NOT_FOUND
A9: 404 | B9: INVOICE_NOT_READY | C9: ORD-16 | D9: 1
A10: 404 | B10: ORDER_NOT_FOUND | C10: ORD-02, ORD-04, ORD-06, ORD-16, ORD-23 | D10: 5
A11: 404 | B11: PRODUCT_NOT_FOUND | C11: CART-02 | D11: 1
A12: 404 | B12: SELLER_NOT_FOUND | C12: DSC-01 | D12: 1
A13: 404 | B13: VOUCHER_NOT_FOUND | C13: DSC-06 | D13: 1
A14: 409 | B14: CANNOT_BUY_OWN_PRODUCT | C14: CART-02 | D14: 1
A15: 409 | B15: CART_EMPTY | C15: CART-06, CHK-01 | D15: 2
A16: 409 | B16: CART_INVALID | C16: CHK-01, CHK-02 | D16: 2
A17: 409 | B17: CART_ITEM_LIMIT_EXCEEDED | C17: CART-02 | D17: 1
A18: 409 | B18: CART_LOCKED | C18: CART-02, CART-03, CART-04, CART-05, CART-10 | D18: 5
A19: 409 | B19: CHECKOUT_ALREADY_OPEN | C19: CHK-02 | D19: 1 | E19: CHECKOUT_ALREADY_PENDING
A20: 409 | B20: CHECKOUT_NOT_CANCELLABLE | C20: CHK-05 | D20: 1
A21: 409 | B21: CHECKOUT_NOT_PAYABLE | C21: CHK-03 | D21: 1
A22: 409 | B22: CONCURRENT_UPDATE | C22: CART-03 | D22: 1
A23: 409 | B23: IDEMPOTENCY_KEY_CONFLICT | C23: CHK-02, ORD-06, ORD-13, ORD-19 | D23: 4 | E23: IDEMPOTENCY_KEY_REUSED
A24: 409 | B24: INSUFFICIENT_STOCK | C24: CART-02, CART-03, CHK-02 | D24: 3
A25: 409 | B25: INVALID_TRANSITION | C25: ORD-12, ORD-18 | D25: 2 | E25: INVALID_STATUS_TRANSITION
A26: 409 | B26: ORDER_NOT_CANCELLABLE | C26: ORD-06 | D26: 1
A27: 409 | B27: ORDER_STATE_CONFLICT | C27: ORD-04, ORD-05, ORD-07, ORD-18, AO-02, AO-03 | D27: 6
A28: 409 | B28: PAYMENT_ATTEMPT_LIMIT_REACHED | C28: CHK-03 | D28: 1 | E28: PAYMENT_RETRY_LIMIT_EXCEEDED
A29: 409 | B29: PAYMENT_IN_PROGRESS | C29: CHK-05, ORD-06 | D29: 2
A30: 409 | B30: PRICE_CHANGED | C30: CHK-02 | D30: 1
A31: 409 | B31: PRODUCT_IN_AUCTION | C31: CART-02 | D31: 1
A32: 409 | B32: PRODUCT_NOT_AVAILABLE | C32: CART-02, CART-03 | D32: 2
A33: 409 | B33: REFUND_ALREADY_REQUESTED | C33: ORD-13 | D33: 1
A34: 409 | B34: REFUND_NOT_ALLOWED | C34: ORD-13 | D34: 1
A35: 409 | B35: REQUEST_IN_PROGRESS | C35: CHK-02, ORD-19 | D35: 2
A36: 409 | B36: SHIPPING_INFO_REQUIRED | C36: AO-03 | D36: 1
A37: 409 | B37: VOUCHER_ALREADY_USED | C37: DSC-06 | D37: 1
A38: 409 | B38: VOUCHER_CODE_EXISTS | C38: DSC-05 | D38: 1
A39: 409 | B39: VOUCHER_INVALID | C39: CHK-02 | D39: 1
A40: 410 | B40: DEADLINE_EXPIRED | C40: CHK-03, ORD-04, AO-02, AO-03 | D40: 4 | E40: PAYMENT_DEADLINE_PASSED
A41: 422 | B41: PRICING_ERROR | C41: CART-07 | D41: 1
A42: 502 | B42: PAYMENT_GATEWAY_ERROR | C42: CHK-03 | D42: 1
A43: 503 | B43: CATALOG_UNAVAILABLE | C43: CART-02, CART-06 | D43: 2
A44: 503 | B44: FULFILLMENT_UNAVAILABLE | C44: CHK-02 | D44: 1
A45: 503 | B45: SHIPPING_QUOTE_UNAVAILABLE | C45: AO-02 | D45: 1

Sheet Coverage_Summary
A1: Coverage summary (all values are live formulas)
A3: Functions by module
A4: Module | B4: Count
A5: Auction Order | B5: =COUNTIF(Backlog!$B$2:$B$58,A5) -> 5
A6: Cart | B6: =COUNTIF(Backlog!$B$2:$B$58,A6) -> 11
A7: Checkout | B7: =COUNTIF(Backlog!$B$2:$B$58,A7) -> 6
A8: Discount | B8: =COUNTIF(Backlog!$B$2:$B$58,A8) -> 8
A9: Invoice | B9: =COUNTIF(Backlog!$B$2:$B$58,A9) -> 2
A10: Order | B10: =COUNTIF(Backlog!$B$2:$B$58,A10) -> 16
A11: Payment (Commerce side) | B11: =COUNTIF(Backlog!$B$2:$B$58,A11) -> 1
A12: Platform | B12: =COUNTIF(Backlog!$B$2:$B$58,A12) -> 8
A13: Total | B13: =SUM(B5:B12) -> 57
A15: Functions by priority
A16: Priority | B16: Count
A17: P0 | B17: =COUNTIF(Backlog!$F$2:$F$58,A17) -> 34
A18: P1 | B18: =COUNTIF(Backlog!$F$2:$F$58,A18) -> 17
A19: P2 | B19: =COUNTIF(Backlog!$F$2:$F$58,A19) -> 6
A20: Total | B20: =SUM(B17:B19) -> 57
A22: Functions by wave (0 = foundation)
A23: Wave | B23: Count
A24: 0 | B24: =COUNTIF(Backlog!$G$2:$G$58,A24) -> 6
A25: 1 | B25: =COUNTIF(Backlog!$G$2:$G$58,A25) -> 11
A26: 2 | B26: =COUNTIF(Backlog!$G$2:$G$58,A26) -> 12
A27: 3 | B27: =COUNTIF(Backlog!$G$2:$G$58,A27) -> 16
A28: 4 | B28: =COUNTIF(Backlog!$G$2:$G$58,A28) -> 12
A29: Total | B29: =SUM(B24:B28) -> 57
A31: Functions by change vs Functions.xlsx
A32: Change | B32: Count
A33: UNCHANGED | B33: =COUNTIF(Backlog!$I$2:$I$58,A33) -> 26
A34: ADJUSTED | B34: =COUNTIF(Backlog!$I$2:$I$58,A34) -> 22
A35: NEW | B35: =COUNTIF(Backlog!$I$2:$I$58,A35) -> 9
A36: Total | B36: =SUM(B33:B35) -> 57
A38: Functions by kind
A39: Kind | B39: Count
A40: Public API | B40: =COUNTIF(Backlog!$D$2:$D$58,A40) -> 30
A41: Internal API | B41: =COUNTIF(Backlog!$D$2:$D$58,A41) -> 1
A42: Internal component | B42: =COUNTIF(Backlog!$D$2:$D$58,A42) -> 8
A43: Job | B43: =COUNTIF(Backlog!$D$2:$D$58,A43) -> 10
A44: Event consumer | B44: =COUNTIF(Backlog!$D$2:$D$58,A44) -> 8
A45: Total | B45: =SUM(B40:B44) -> 57
A47: Requirement coverage (Trace_Matrix)
A48: Status | B48: Count
A49: COVERED | B49: =COUNTIF(Trace_Matrix!$M$2:$M$1000,A49) -> 76
A50: THIN | B50: =COUNTIF(Trace_Matrix!$M$2:$M$1000,A50) -> 0
A51: NO TEST | B51: =COUNTIF(Trace_Matrix!$M$2:$M$1000,A51) -> 0
A52: GAP - no function | B52: =COUNTIF(Trace_Matrix!$M$2:$M$1000,A52) -> 0
A53: Total | B53: =SUM(B49:B52) -> 76
A54: Check: total requirements | B54: =COUNTA(Trace_Matrix!$A$2:$A$77) -> 76
A56: Test cases by type
A57: Type | B57: Count
A58: Functional | B58: =COUNTIF(Test_Cases!$E$2:$E$1000,A58) -> 57
A59: Negative | B59: =COUNTIF(Test_Cases!$E$2:$E$1000,A59) -> 89
A60: Security | B60: =COUNTIF(Test_Cases!$E$2:$E$1000,A60) -> 30
A61: Idempotency/Concurrency | B61: =COUNTIF(Test_Cases!$E$2:$E$1000,A61) -> 33
A62: Business rule | B62: =COUNTIF(Test_Cases!$E$2:$E$1000,A62) -> 38
A63: Boundary | B63: =COUNTIF(Test_Cases!$E$2:$E$1000,A63) -> 18
A64: Contract | B64: =COUNTIF(Test_Cases!$E$2:$E$1000,A64) -> 31
A65: E2E | B65: =COUNTIF(Test_Cases!$E$2:$E$1000,A65) -> 15
A66: Total | B66: =SUM(B58:B65) -> 311
A68: Open items
A69: Gap status | B69: Count
A70: Open | B70: =COUNTIF(Gaps_Decisions!$F$2:$F$1000,A70) -> 25
A71: Proposed fix | B71: =COUNTIF(Gaps_Decisions!$F$2:$F$1000,A71) -> 3
A72: Assumption | B72: =COUNTIF(Gaps_Decisions!$F$2:$F$1000,A72) -> 2
A73: Total | B73: =SUM(B70:B72) -> 30
A75: Functions without tests | B75: =COUNTIF(Backlog!$Y$2:$Y$58,"NO TEST") -> 0
A76: Tables unused / read-only (DB_Trace) | B76: =COUNTIF(DB_Trace!$G$2:$G$20,"<>OK") -> 1

Sheet CloudEvents_Spec
A1: Area | B1: Item | C1: Commerce rule / value | D1: Notes
A2: Standard | B2: Spec | C2: CloudEvents v1.0.2, JSON event format, STRUCTURED content mode | D2: Body is the full envelope; Content-Type: application/cloudevents+json; charset=utf-8. Reason: broker-agnostic, easy to log/replay/store in outbox.
A3: Standard | B3: Delivery | C3: At-least-once; consumer dedupe on (source, id) | D3: Matches existing inbox PK (message_id, consumer): message_id = CloudEvents id. A republish MUST keep the same id.
A4: Attribute | B4: id (required) | C4: outbox_messages.id (uuid, string form) | D4: Globally unique per source. Never regenerate on retry.
A5: Attribute | B5: source (required) | C5: /services/commerce | D5: URI-reference identifying the producer service. Constant per service (Auction: /services/auction, Wallet: /services/wallet, Fulfillment: /services/fulfillment).
A6: Attribute | B6: specversion (required) | C6: 1.0 | D6: Constant.
A7: Attribute | B7: type (required) | C7: com.nexus.commerce.<aggregate>.<action>.v<major> | D7: Reverse-DNS, lowercase, dot-separated, kebab-case words, version suffix. Example: com.nexus.commerce.order.paid.v1. outbox_messages.event_type stores this value.
A8: Attribute | B8: subject (optional, we always set) | C8: aggregate id (outbox_messages.aggregate_id) | D8: orderId / auctionOrderId / checkoutGroupId / cartId. Lets consumers filter without parsing data.
A9: Attribute | B9: time (optional, we always set) | C9: outbox_messages.occurred_at, RFC 3339 UTC | D9: Business time of the fact, not publish time.
A10: Attribute | B10: datacontenttype | C10: application/json | D10: Describes the data member.
A11: Attribute | B11: dataschema | C11: https://schemas.nexus.internal/commerce/<aggregate>-<action>/<major>.<minor> | D11: Assumed host; schema is JSON Schema stored in repo (contracts/). See G31.
A12: Extension | B12: traceparent | C12: W3C Trace Context | D12: Distributed Tracing extension; required for checkout (SRS 5.5). Copy from current Activity.
... A33: Example | B33: OrderPaid envelope (formatted) | C33: { "specversion": "1.0", "id": "7c1f…-uuid", "source": "/services/commerce", "type": "com.nexus.commerce.order.paid.v1", "subject": "<orderId>", "time": "2026-10-27T07:10:00Z", "datacontenttype": "application/json", "dataschema": "https://schemas.nexus.internal/commerce/order-paid/1.0", "traceparent": "00-…", "correlationid": "<checkoutGroupId>", "causationid": "<id event của Wallet>", "partitionkey": "<orderId>", "ordertype": "AUCTION", "data": { "orderId": "…", "orderType": "AUCTION", "auctionId": "…", "amount": "125000", "currency": "VND", "paidAt": "…" } } | D33: Same shape as the catalog column

Sheet CloudEvents_Catalog
A1: Legacy name (= spec eventType) | B1: CloudEvents type | C1: source | D1: subject | E1: Aggregate (= spec aggregateType) | F1: ordertype extension | G1: data (JSON, formatted) | H1: Full example envelope (JSON) | I1: Published by | J1: Consumers | K1: Agreement | L1: Schema
A2: CartCreated | B2: com.nexus.commerce.cart.created.v1 | C2: /services/commerce | D2: cartId | E2: Cart | F2: - | G2: { "cartId": "<cartId>", "buyerId": "<buyerId>" } | H2: { "specversion": "1.0", "id": "<uuid = outbox_messages.id>", "source": "/services/commerce", "type": "com.nexus.commerce.cart.created.v1", "subject": "<cartId>", "time": "2026-10-27T07:10:00Z", "datacontenttype": "application/json", "dataschema": "https://schemas.nexus.internal/commerce/cart-created/1.0", "traceparent": "00-<trace-id>-<span-id>-01", "correlationid": "<correlationId>", "causationid": "<id of causing event>", "partitionkey": "<cartId>", "legacytype": "CartCreated", "data": { "cartId": "<cartId>", "buyerId": "<buyerId>" } } | I2: CART-02 | J2: Notification, Event Log | K2: In SRS 5.2 | L2: Draft
A3: CartItemAdded | B3: com.nexus.commerce.cart.item-added.v1 | C3: /services/commerce | D3: cartId | E3: Cart | F3: - | G3: { "cartId": "<cartId>", "cartItemId": "<cartItemId>", "productId": "<productId>", "skuId": "<skuId>", "quantity": 1 } | H3: { "specversion": "1.0", "id": "<uuid = outbox_messages.id>", "source": "/services/commerce", "type": "com.nexus.commerce.cart.item-added.v1", "subject": "<cartId>", "time": "2026-10-27T07:10:00Z", "datacontenttype": "application/json", "dataschema": "https://schemas.nexus.internal/commerce/cart-item-added/1.0", "traceparent": "00-<trace-id>-<span-id>-01", "correlationid": "<correlationId>", "causationid": "<id of causing event>", "partitionkey": "<cartId>", "legacytype": "CartItemAdded", "data": { "cartId": "<cartId>", "cartItemId": "<cartItemId>", "productId": "<productId>", "skuId": "<skuId>", "quantity": 1 } } | I3: CART-02 | J3: Notification, Event Log | K3: In SRS 5.2 | L3: Draft
A4: CartItemUpdated | B4: com.nexus.commerce.cart.item-updated.v1 | C4: /services/commerce | D4: cartId | E4: Cart | F4: - | G4: { "cartId": "<cartId>", "cartItemId": "<cartItemId>", "quantity": 1 } | H4: { "specversion": "1.0", "id": "<uuid = outbox_messages.id>", "source": "/services/commerce", "type": "com.nexus.commerce.cart.item-updated.v1", "subject": "<cartId>", "time": "2026-10-27T07:10:00Z", "datacontenttype": "application/json", "dataschema": "https://schemas.nexus.internal/commerce/cart-item-updated/1.0", "traceparent": "00-<trace-id>-<span-id>-01", "correlationid": "<correlationId>", "causationid": "<id of causing event>", "partitionkey": "<cartId>", "legacytype": "CartItemUpdated", "data": { "cartId": "<cartId>", "cartItemId": "<cartItemId>", "quantity": 1 } } | I4: CART-03 | J4: Notification, Event Log | K4: In SRS 5.2 | L4: Draft
A5: CartItemRemoved | B5: com.nexus.commerce.cart.item-removed.v1 | C5: /services/commerce | D5: cartId | E5: Cart | F5: - | G5: { "cartId": "<cartId>", "cartItemId": "<cartItemId>" } | H5: { "specversion": "1.0", "id": "<uuid = outbox_messages.id>", "source": "/services/commerce", "type": "com.nexus.commerce.cart.item-removed.v1", "subject": "<cartId>", "time": "2026-10-27T07:10:00Z", "datacontenttype": "application/json", "dataschema": "https://schemas.nexus.internal/commerce/cart-item-removed/1.0", "traceparent": "00-<trace-id>-<span-id>-01", "correlationid": "<correlationId>", "causationid": "<id of causing event>", "partitionkey": "<cartId>", "legacytype": "CartItemRemoved", "data": { "cartId": "<cartId>", "cartItemId": "<cartItemId>" } } | I5: CART-04; CART-05; CART-11 | J5: Notification, Event Log | K5: In SRS 5.2 | L5: Draft
A6: CartExpired | B6: com.nexus.commerce.cart.expired.v1 | C6: /services/commerce | D6: cartId | E6: Cart | F6: - | G6: { "cartId": "<cartId>", "buyerId": "<buyerId>", "lastActivityAt": "2026-10-27T07:10:00Z" } | H6: { "specversion": "1.0", "id": "<uuid = outbox_messages.id>", "source": "/services/commerce", "type": "com.nexus.commerce.cart.expired.v1", "subject": "<cartId>", "time": "2026-10-27T07:10:00Z", "datacontenttype": "application/json", "dataschema": "https://schemas.nexus.internal/commerce/cart-expired/1.0", "traceparent": "00-<trace-id>-<span-id>-01", "correlationid": "<correlationId>", "causationid": "<id of causing event>", "partitionkey": "<cartId>", "legacytype": "CartExpired", "data": { "cartId": "<cartId>", "buyerId": "<buyerId>", "lastActivityAt": "2026-10-27T07:10:00Z" } } | I6: CART-09 | J6: Notification, Event Log | K6: In SRS 5.2 | L6: Draft
A7: CheckoutStarted | B7: com.nexus.commerce.checkout.started.v1 | C7: /services/commerce | D7: checkoutGroupId | E7: CheckoutGroup | F7: - | G7: { "checkoutGroupId": "<checkoutGroupId>", "cartId": "<cartId>", "buyerId": "<buyerId>", "totalAmount": 255000.0 } | H7: { "specversion": "1.0", "id": "<uuid = outbox_messages.id>", "source": "/services/commerce", "type": "com.nexus.commerce.checkout.started.v1", "subject": "<checkoutGroupId>", "time": "2026-10-27T07:10:00Z", "datacontenttype": "application/json", "dataschema": "https://schemas.nexus.internal/commerce/checkout-started/1.0", "traceparent": "00-<trace-id>-<span-id>-01", "correlationid": "<correlationId>", "causationid": "<id of causing event>", "partitionkey": "<checkoutGroupId>", "legacytype": "CheckoutStarted", "data": { "checkoutGroupId": "<checkoutGroupId>", "cartId": "<cartId>", "buyerId": "<buyerId>", "totalAmount": 255000.0 } } | I7: CHK-02 | J7: Event Log | K7: In SRS 5.2 | L7: Draft
A8: OrderCreated | B8: com.nexus.commerce.order.created.v1 | C8: /services/commerce | D8: orderId | E8: Order / AuctionOrder | F8: yes | G8: { "orderType": "REGULAR", "orderId": "<orderId>", "orderNo": "<orderNo>", "buyerId": "<buyerId>", "sellerId": "<sellerId>", "totalAmount": 255000.0, "paymentDeadlineAt": "2026-10-27T07:10:00Z", "checkoutGroupId": null, "auctionId": null, "winningBidId": null, "items": [ { "skuId": "<skuId>", "quantity": 1 } ], "winningAmount": 255000.0 } | H8: { "specversion": "1.0", "id": "<uuid = outbox_messages.id>", "source": "/services/commerce", "type": "com.nexus.commerce.order.created.v1", "subject": "<orderId>", "time": "2026-10-27T07:10:00Z", "datacontenttype": "application/json", "dataschema": "https://schemas.nexus.internal/commerce/order-created/1.0", "traceparent": "00-<trace-id>-<span-id>-01", "correlationid": "<correlationId>", "causationid": "<id of causing event>", "partitionkey": "<orderId>", "legacytype": "OrderCreated", "ordertype": "REGULAR", "data": { "orderType": "REGULAR", "orderId": "<orderId>", "orderNo": "<orderNo>", "buyerId": "<buyerId>", "sellerId": "<sellerId>", "totalAmount": 255000.0, "paymentDeadlineAt": "2026-10-27T07:10:00Z", "checkoutGroupId": null, "auctionId": null, "winningBidId": null, "items": [ { "skuId": "<skuId>", "quantity": 1 } ], "winningAmount": 255000.0 } } | I8: CHK-02; AO-01 | J8: Notification, Event Log, Auction (AUCTION) | K8: Agreed (Auction) | L8: Draft
A9: OrderPaid | B9: com.nexus.commerce.order.paid.v1 | C9: /services/commerce | D9: orderId | E9: Order / AuctionOrder | F9: yes | G9: { "orderType": "REGULAR", "orderId": "<orderId>", "orderNo": "<orderNo>", "buyerId": "<buyerId>", "sellerId": "<sellerId>", "totalAmount": 255000.0, "paymentDeadlineAt": "2026-10-27T07:10:00Z", "checkoutGroupId": null, "auctionId": null, "winningBidId": null, "paidAt": "2026-10-27T07:10:00Z", "walletTransactionId": "<walletTransactionId>", "sellerRespondDeadlineAt": "2026-10-27T07:10:00Z" } | H9: { "specversion": "1.0", "id": "<uuid = outbox_messages.id>", "source": "/services/commerce", "type": "com.nexus.commerce.order.paid.v1", "subject": "<orderId>", "time": "2026-10-27T07:10:00Z", "datacontenttype": "application/json", "dataschema": "https://schemas.nexus.internal/commerce/order-paid/1.0", "traceparent": "00-<trace-id>-<span-id>-01", "correlationid": "<correlationId>", "causationid": "<id of causing event>", "partitionkey": "<orderId>", "legacytype": "OrderPaid", "ordertype": "REGULAR", "data": { "orderType": "REGULAR", "orderId": "<orderId>", "orderNo": "<orderNo>", "buyerId": "<buyerId>", "sellerId": "<sellerId>", "totalAmount": 255000.0, "paymentDeadlineAt": "2026-10-27T07:10:00Z", "checkoutGroupId": null, "auctionId": null, "winningBidId": null, "paidAt": "2026-10-27T07:10:00Z", "walletTransactionId": "<walletTransactionId>", "sellerRespondDeadlineAt": "2026-10-27T07:10:00Z" } } | I9: PAY-01 | J9: Fulfillment, Notification, Auction (AUCTION) | K9: Agreed (Auction) | L9: Draft
A10: OrderPaymentFailed | B10: com.nexus.commerce.order.payment-failed.v1 | C10: /services/commerce | D10: orderId | E10: Order / AuctionOrder | F10: yes | G10: { "orderType": "REGULAR", "orderId": "<orderId>", "orderNo": "<orderNo>", "buyerId": "<buyerId>", "sellerId": "<sellerId>", "totalAmount": 255000.0, "paymentDeadlineAt": "2026-10-27T07:10:00Z", "checkoutGroupId": null, "auctionId": null, "winningBidId": null, "attemptCount": 1, "failureCode": "<failureCode>" } | H10: { "specversion": "1.0", "id": "<uuid = outbox_messages.id>", "source": "/services/commerce", "type": "com.nexus.commerce.order.payment-failed.v1", "subject": "<orderId>", "time": "2026-10-27T07:10:00Z", "datacontenttype": "application/json", "dataschema": "https://schemas.nexus.internal/commerce/order-payment-failed/1.0", "traceparent": "00-<trace-id>-<span-id>-01", "correlationid": "<correlationId>", "causationid": "<id of causing event>", "partitionkey": "<orderId>", "legacytype": "OrderPaymentFailed", "ordertype": "REGULAR", "data": { "orderType": "REGULAR", "orderId": "<orderId>", "orderNo": "<orderNo>", "buyerId": "<buyerId>", "sellerId": "<sellerId>", "totalAmount": 255000.0, "paymentDeadlineAt": "2026-10-27T07:10:00Z", "checkoutGroupId": null, "auctionId": null, "winningBidId": null, "attemptCount": 1, "failureCode": "<failureCode>" } } | I10: PAY-01 | J10: Notification; Auction optional | K10: Agreed (Auction) | L10: Draft
A11: OrderConfirmed | B11: com.nexus.commerce.order.confirmed.v1 | C11: /services/commerce | D11: orderId | E11: Order / AuctionOrder | F11: yes | G11: { "orderType": "REGULAR", "orderId": "<orderId>", "orderNo": "<orderNo>", "buyerId": "<buyerId>", "sellerId": "<sellerId>", "sellerAcceptedAt": "2026-10-27T07:10:00Z", "shippingAddress": "<shippingAddress>", "contactPhone": "<contactPhone>" } | H11: { "specversion": "1.0", "id": "<uuid = outbox_messages.id>", "source": "/services/commerce", "type": "com.nexus.commerce.order.confirmed.v1", "subject": "<orderId>", "time": "2026-10-27T07:10:00Z", "datacontenttype": "application/json", "dataschema": "https://schemas.nexus.internal/commerce/order-confirmed/1.0", "traceparent": "00-<trace-id>-<span-id>-01", "correlationid": "<correlationId>", "causationid": "<id of causing event>", "partitionkey": "<orderId>", "legacytype": "OrderConfirmed", "ordertype": "REGULAR", "data": { "orderType": "REGULAR", "orderId": "<orderId>", "orderNo": "<orderNo>", "buyerId": "<buyerId>", "sellerId": "<sellerId>", "sellerAcceptedAt": "2026-10-27T07:10:00Z", "shippingAddress": "<shippingAddress>", "contactPhone": "<contactPhone>" } } | I11: ORD-04 | J11: Fulfillment-Shipping, Notification | K11: PROPOSED (OQ-20) | L11: Draft
A12: OrderCancelled | B12: com.nexus.commerce.order.cancelled.v1 | C12: /services/commerce | D12: orderId | E12: Order / AuctionOrder | F12: yes | G12: { "orderType": "REGULAR", "orderId": "<orderId>", "orderNo": "<orderNo>", "buyerId": "<buyerId>", "sellerId": "<sellerId>", "totalAmount": 255000.0, "paymentDeadlineAt": "2026-10-27T07:10:00Z", "checkoutGroupId": null, "auctionId": null, "winningBidId": null, "wasPaid": "<wasPaid>", "reasonCode": "<reasonCode>", "actorRole": "<actorRole>", "cancelledAt": "2026-10-27T07:10:00Z", "reasonNote": "<reasonNote>" } | H12: { "specversion": "1.0", "id": "<uuid = outbox_messages.id>", "source": "/services/commerce", "type": "com.nexus.commerce.order.cancelled.v1", "subject": "<orderId>", "time": "2026-10-27T07:10:00Z", "datacontenttype": "application/json", "dataschema": "https://schemas.nexus.internal/commerce/order-cancelled/1.0", "traceparent": "00-<trace-id>-<span-id>-01", "correlationid": "<correlationId>", "causationid": "<id of causing event>", "partitionkey": "<orderId>", "legacytype": "OrderCancelled", "ordertype": "REGULAR", "data": { "orderType": "REGULAR", "orderId": "<orderId>", "orderNo": "<orderNo>", "buyerId": "<buyerId>", "sellerId": "<sellerId>", "totalAmount": 255000.0, "paymentDeadlineAt": "2026-10-27T07:10:00Z", "checkoutGroupId": null, "auctionId": null, "winningBidId": null, "wasPaid": "<wasPaid>", "reasonCode": "<reasonCode>", "actorRole": "<actorRole>", "cancelledAt": "2026-10-27T07:10:00Z", "reasonNote": "<reasonNote>" } } | I12: CHK-05; CHK-06; ORD-05; ORD-06; ORD-09; ORD-22; AO-04 | J12: Fulfillment, Notification, Auction (AUCTION), User | K12: Agreed (Auction) | L12: Draft
... A21: InvoiceGenerated | B21: com.nexus.commerce.invoice.generated.v1 | C21: /services/commerce | D21: invoiceId | E21: Invoice | F21: yes | G21: { "invoiceId": "<invoiceId>", "invoiceNo": "<invoiceNo>", "orderId": "<orderId>", "orderType": "REGULAR", "buyerId": "<buyerId>", "totalAmount": 255000.0, "generatedAt": "2026-10-27T07:10:00Z" } | H21: { "specversion": "1.0", "id": "<uuid = outbox_messages.id>", "source": "/services/commerce", "type": "com.nexus.commerce.invoice.generated.v1", "subject": "<invoiceId>", "time": "2026-10-27T07:10:00Z", "datacontenttype": "application/json", "dataschema": "https://schemas.nexus.internal/commerce/invoice-generated/1.0", "traceparent": "00-<trace-id>-<span-id>-01", "correlationid": "<correlationId>", "causationid": "<id of causing event>", "partitionkey": "<invoiceId>", "legacytype": "InvoiceGenerated", "ordertype": "REGULAR", "data": { "invoiceId": "<invoiceId>", "invoiceNo": "<invoiceNo>", "orderId": "<orderId>", "orderType": "REGULAR", "buyerId": "<buyerId>", "totalAmount": 255000.0, "generatedAt": "2026-10-27T07:10:00Z" } } | I21: ORD-15 | J21: Notification | K21: Not in SRS (G34) | L21: Draft
